{
    "std" : 11.178002307834632,
    "end" : 293.97588000000002,
    "state_parser" : {
        "name" : "SpeedyStatSplit",
        "min_gain_per_sample" : null,
        "false_positive_rate" : null,
        "max_width" : 1000000,
        "window_width" : 10000,
        "prior_segments_per_second" : 40,
        "min_width" : 100,
        "cutoff_freq" : 2000,
        "sampling_freq" : 100000.0
    },
    "name" : "Event",
    "min" : 11.171472343881318,
    "max" : 102.18096699911787,
    "segments" : [
        {
            "std" : 19.904810459959922,
            "end" : 0.00166,
            "name" : "Segment",
            "min" : 25.669898085148706,
            "max" : 102.18096699911787,
            "start" : 0.0,
            "duration" : 0.00166,
            "mean" : 41.796392579807005
        },
        {
            "std" : 0.7177626962349527,
            "end" : 0.04169,
            "name" : "Segment",
            "min" : 36.260329506767455,
            "max" : 41.343355891046805,
            "start" : 0.00166,
            "duration" : 0.04003,
            "mean" : 39.718469720941862
        },
        {
            "std" : 0.90184543672959938,
            "end" : 0.04633,
            "name" : "Segment",
            "min" : 36.944971585683824,
            "max" : 41.318782910841797,
            "start" : 0.04169,
            "duration" : 0.00464,
            "mean" : 39.01734725979253
        },
        {
            "std" : 0.79764000912636313,
            "end" : 0.08287,
            "name" : "Segment",
            "min" : 40.005889049151698,
            "max" : 45.510553742584968,
            "start" : 0.04633,
            "duration" : 0.03654,
            "mean" : 43.631940065919586
        },
        {
            "std" : 0.6222910958450335,
            "end" : 0.16301,
            "name" : "Segment",
            "min" : 39.249613470262304,
            "max" : 43.920784340402008,
            "start" : 0.08287,
            "duration" : 0.08014,
            "mean" : 42.315716460698674
        },
        {
            "std" : 0.72541896114653015,
            "end" : 0.18692,
            "name" : "Segment",
            "min" : 35.886621742156386,
            "max" : 41.061485892995854,
            "start" : 0.16301,
            "duration" : 0.02391,
            "mean" : 39.138314956684589
        },
        {
            "std" : 0.72679883738200635,
            "end" : 0.19125,
            "name" : "Segment",
            "min" : 39.931129921500457,
            "max" : 43.093590694416804,
            "start" : 0.18692,
            "duration" : 0.00433,
            "mean" : 41.935795372722211
        },
        {
            "std" : 0.75148225308418948,
            "end" : 0.24164,
            "name" : "Segment",
            "min" : 35.218378783773325,
            "max" : 41.696079796809748,
            "start" : 0.19125,
            "duration" : 0.05039,
            "mean" : 39.111521687773461
        },
        {
            "std" : 1.8007569145811377,
            "end" : 0.24264,
            "name" : "Segment",
            "min" : 33.091686384902573,
            "max" : 39.632263911292881,
            "start" : 0.24164,
            "duration" : 0.001,
            "mean" : 37.434903338390285
        },
        {
            "std" : 0.72312722360955628,
            "end" : 0.34199,
            "name" : "Segment",
            "min" : 35.040105518957049,
            "max" : 41.163626028231718,
            "start" : 0.24264,
            "duration" : 0.09935,
            "mean" : 39.166400535085437
        },
        {
            "std" : 0.64586460464239526,
            "end" : 0.38041,
            "name" : "Segment",
            "min" : 34.475533568443936,
            "max" : 39.458028080025386,
            "start" : 0.34199,
            "duration" : 0.03842,
            "mean" : 37.974385779107166
        },
        {
            "std" : 0.72343561302785087,
            "end" : 0.3972,
            "name" : "Segment",
            "min" : 32.662912690881889,
            "max" : 36.31760544133035,
            "start" : 0.38041,
            "duration" : 0.01679,
            "mean" : 34.208292266697505
        },
        {
            "std" : 0.96289185337331284,
            "end" : 0.41238,
            "name" : "Segment",
            "min" : 31.795672754928873,
            "max" : 36.952762974389323,
            "start" : 0.3972,
            "duration" : 0.01518,
            "mean" : 34.714303505107644
        },
        {
            "std" : 0.88320934331823964,
            "end" : 0.43501,
            "name" : "Segment",
            "min" : 30.875375163265179,
            "max" : 36.865069960707096,
            "start" : 0.41238,
            "duration" : 0.02263,
            "mean" : 33.680156811181291
        },
        {
            "std" : 1.6021666412693421,
            "end" : 0.48821,
            "name" : "Segment",
            "min" : 37.118578904348112,
            "max" : 46.813077216072116,
            "start" : 0.43501,
            "duration" : 0.0532,
            "mean" : 41.83338362231536
        },
        {
            "std" : 1.3052386316226363,
            "end" : 0.59174,
            "name" : "Segment",
            "min" : 39.387573104945893,
            "max" : 48.597528545563321,
            "start" : 0.48821,
            "duration" : 0.10353,
            "mean" : 43.289772269139249
        },
        {
            "std" : 0.97305004952615759,
            "end" : 0.73109,
            "name" : "Segment",
            "min" : 42.043616714165069,
            "max" : 48.641285431915819,
            "start" : 0.59174,
            "duration" : 0.13935,
            "mean" : 46.17070404714061
        },
        {
            "std" : 0.8881922135370971,
            "end" : 0.80907,
            "name" : "Segment",
            "min" : 38.795741858630926,
            "max" : 46.635121828622587,
            "start" : 0.73109,
            "duration" : 0.07798,
            "mean" : 44.196571342963196
        },
        {
            "std" : 0.94291305718127061,
            "end" : 0.90584,
            "name" : "Segment",
            "min" : 33.024669455568663,
            "max" : 40.542448478002285,
            "start" : 0.80907,
            "duration" : 0.09677,
            "mean" : 36.931659050699579
        },
        {
            "std" : 0.65485594598818997,
            "end" : 0.91316,
            "name" : "Segment",
            "min" : 34.340928788024456,
            "max" : 37.473161076655487,
            "start" : 0.90584,
            "duration" : 0.00732,
            "mean" : 35.892483866943124
        },
        {
            "std" : 1.6386894990867458,
            "end" : 0.9172,
            "name" : "Segment",
            "min" : 32.187619011987778,
            "max" : 41.61201313350395,
            "start" : 0.91316,
            "duration" : 0.00404,
            "mean" : 36.090498314477223
        },
        {
            "std" : 1.2301447272094805,
            "end" : 0.98067,
            "name" : "Segment",
            "min" : 34.934150058982112,
            "max" : 45.718739981219485,
            "start" : 0.9172,
            "duration" : 0.06347,
            "mean" : 42.447880338776173
        },
        {
            "std" : 3.1049037936864501,
            "end" : 0.98464,
            "name" : "Segment",
            "min" : 29.458699447312544,
            "max" : 42.61351730838323,
            "start" : 0.98067,
            "duration" : 0.00397,
            "mean" : 36.946243340658782
        },
        {
            "std" : 2.4701451773666925,
            "end" : 1.02682,
            "name" : "Segment",
            "min" : 33.431187936431208,
            "max" : 45.123762830327863,
            "start" : 0.98464,
            "duration" : 0.04218,
            "mean" : 40.16118279126966
        },
        {
            "std" : 1.9110541079020551,
            "end" : 1.03963,
            "name" : "Segment",
            "min" : 29.400118776056591,
            "max" : 40.787426043196746,
            "start" : 1.02682,
            "duration" : 0.01281,
            "mean" : 37.217592682532313
        },
        {
            "std" : 1.4605088193545841,
            "end" : 1.09008,
            "name" : "Segment",
            "min" : 18.84679943048722,
            "max" : 28.653954958959108,
            "start" : 1.03963,
            "duration" : 0.05045,
            "mean" : 22.967922468622174
        },
        {
            "std" : 1.0744504543977207,
            "end" : 1.16557,
            "name" : "Segment",
            "min" : 16.006003245611236,
            "max" : 22.966071861293276,
            "start" : 1.09008,
            "duration" : 0.07549,
            "mean" : 19.684356826702611
        },
        {
            "std" : 3.3237688503047385,
            "end" : 1.21523,
            "name" : "Segment",
            "min" : 18.138577707370821,
            "max" : 32.547309840415458,
            "start" : 1.16557,
            "duration" : 0.04966,
            "mean" : 24.83506708457816
        },
        {
            "std" : 1.7426262502914249,
            "end" : 1.24745,
            "name" : "Segment",
            "min" : 19.636087539257247,
            "max" : 31.659185337778954,
            "start" : 1.21523,
            "duration" : 0.03222,
            "mean" : 25.789122559798511
        },
        {
            "std" : 3.3607083792580048,
            "end" : 1.24845,
            "name" : "Segment",
            "min" : 26.742521397374443,
            "max" : 35.709512220969359,
            "start" : 1.24745,
            "duration" : 0.001,
            "mean" : 31.232356362657864
        },
        {
            "std" : 2.1018396765641145,
            "end" : 1.29105,
            "name" : "Segment",
            "min" : 21.690578247989041,
            "max" : 37.188149888635785,
            "start" : 1.24845,
            "duration" : 0.0426,
            "mean" : 26.54455937980158
        },
        {
            "std" : 3.7856842579530934,
            "end" : 1.293,
            "name" : "Segment",
            "min" : 25.330460368576098,
            "max" : 38.278110722715638,
            "start" : 1.29105,
            "duration" : 0.00195,
            "mean" : 30.048258960148093
        },
        {
            "std" : 1.1664589364961895,
            "end" : 1.3156,
            "name" : "Segment",
            "min" : 35.192512410599292,
            "max" : 42.533588240626784,
            "start" : 1.293,
            "duration" : 0.0226,
            "mean" : 39.640987390259291
        },
        {
            "std" : 4.3935179772157325,
            "end" : 1.31699,
            "name" : "Segment",
            "min" : 22.714302092619963,
            "max" : 37.259939653209322,
            "start" : 1.3156,
            "duration" : 0.00139,
            "mean" : 27.117542262984532
        },
        {
            "std" : 1.6835558756083484,
            "end" : 1.32605,
            "name" : "Segment",
            "min" : 31.919830344171714,
            "max" : 41.631314105409025,
            "start" : 1.31699,
            "duration" : 0.00906,
            "mean" : 38.686220038654533
        },
        {
            "std" : 1.1579545056860636,
            "end" : 1.41518,
            "name" : "Segment",
            "min" : 31.520488167767006,
            "max" : 42.707946855509675,
            "start" : 1.32605,
            "duration" : 0.08913,
            "mean" : 39.251779751275876
        },
        {
            "std" : 1.7134465279881428,
            "end" : 1.44828,
            "name" : "Segment",
            "min" : 33.563960779277544,
            "max" : 44.7670574540236,
            "start" : 1.41518,
            "duration" : 0.0331,
            "mean" : 40.629116464150954
        },
        {
            "std" : 1.2963340967390857,
            "end" : 1.50789,
            "name" : "Segment",
            "min" : 34.873650974737373,
            "max" : 44.404592196419543,
            "start" : 1.44828,
            "duration" : 0.05961,
            "mean" : 39.71660749640894
        },
        {
            "std" : 2.2503190208304673,
            "end" : 1.5115,
            "name" : "Segment",
            "min" : 37.512824641710516,
            "max" : 46.669716823915955,
            "start" : 1.50789,
            "duration" : 0.00361,
            "mean" : 40.789050875302365
        },
        {
            "std" : 1.4400242264624064,
            "end" : 1.54603,
            "name" : "Segment",
            "min" : 42.273213741016697,
            "max" : 51.453168054594649,
            "start" : 1.5115,
            "duration" : 0.03453,
            "mean" : 46.279768684171927
        },
        {
            "std" : 1.2484437188781823,
            "end" : 1.59716,
            "name" : "Segment",
            "min" : 33.654357765788049,
            "max" : 45.476237451896409,
            "start" : 1.54603,
            "duration" : 0.05113,
            "mean" : 39.667131825522887
        },
        {
            "std" : 1.7060893036902232,
            "end" : 1.68575,
            "name" : "Segment",
            "min" : 42.564046589475758,
            "max" : 51.861995795861084,
            "start" : 1.59716,
            "duration" : 0.08859,
            "mean" : 46.725712213197681
        },
        {
            "std" : 1.0131240924700846,
            "end" : 1.69601,
            "name" : "Segment",
            "min" : 46.327083086306928,
            "max" : 52.78937053674133,
            "start" : 1.68575,
            "duration" : 0.01026,
            "mean" : 50.270962618731723
        },
        {
            "std" : 1.9792731356194933,
            "end" : 1.69964,
            "name" : "Segment",
            "min" : 40.455004057164061,
            "max" : 48.79731287331812,
            "start" : 1.69601,
            "duration" : 0.00363,
            "mean" : 45.402556447260054
        },
        {
            "std" : 0.70348406072745284,
            "end" : 1.70589,
            "name" : "Segment",
            "min" : 44.837585636088946,
            "max" : 48.181523164260682,
            "start" : 1.69964,
            "duration" : 0.00625,
            "mean" : 46.438647101598221
        },
        {
            "std" : 0.64617545151306888,
            "end" : 1.70883,
            "name" : "Segment",
            "min" : 47.940145548229474,
            "max" : 50.849904092113867,
            "start" : 1.70589,
            "duration" : 0.00294,
            "mean" : 49.909243287425888
        },
        {
            "std" : 0.79828146888821094,
            "end" : 1.87415,
            "name" : "Segment",
            "min" : 44.887227247318563,
            "max" : 51.402799886467811,
            "start" : 1.70883,
            "duration" : 0.16532,
            "mean" : 48.989684616952445
        },
        {
            "std" : 0.55993710462194157,
            "end" : 1.88689,
            "name" : "Segment",
            "min" : 45.161437339446145,
            "max" : 47.988628315145775,
            "start" : 1.87415,
            "duration" : 0.01274,
            "mean" : 46.731032167273149
        },
        {
            "std" : 0.84741706024643826,
            "end" : 1.96865,
            "name" : "Segment",
            "min" : 42.117719366606444,
            "max" : 48.618425970210168,
            "start" : 1.88689,
            "duration" : 0.08176,
            "mean" : 46.489217169208054
        },
        {
            "std" : 0.76893993394270654,
            "end" : 2.08289,
            "name" : "Segment",
            "min" : 40.021248090077748,
            "max" : 47.530947125776024,
            "start" : 1.96865,
            "duration" : 0.11424,
            "mean" : 45.211749108966345
        },
        {
            "std" : 0.75508941709907462,
            "end" : 2.14213,
            "name" : "Segment",
            "min" : 41.838712111474088,
            "max" : 47.000237473858682,
            "start" : 2.08289,
            "duration" : 0.05924,
            "mean" : 44.771198104831491
        },
        {
            "std" : 0.67440505083125102,
            "end" : 2.16588,
            "name" : "Segment",
            "min" : 39.814637444924493,
            "max" : 46.033518725093025,
            "start" : 2.14213,
            "duration" : 0.02375,
            "mean" : 43.885039673583059
        },
        {
            "std" : 0.7312212828215382,
            "end" : 2.20114,
            "name" : "Segment",
            "min" : 41.60485631878862,
            "max" : 46.446795573686202,
            "start" : 2.16588,
            "duration" : 0.03526,
            "mean" : 44.313335311107686
        },
        {
            "std" : 0.57668287395832618,
            "end" : 2.2053,
            "name" : "Segment",
            "min" : 41.919613014687741,
            "max" : 44.691950734332423,
            "start" : 2.20114,
            "duration" : 0.00416,
            "mean" : 43.344213020802982
        },
        {
            "std" : 2.0981675064380849,
            "end" : 2.2063,
            "name" : "Segment",
            "min" : 37.139499674032827,
            "max" : 44.139007820067704,
            "start" : 2.2053,
            "duration" : 0.001,
            "mean" : 41.880136009563017
        },
        {
            "std" : 0.546068494261014,
            "end" : 2.21612,
            "name" : "Segment",
            "min" : 42.019628104129637,
            "max" : 44.995989943487317,
            "start" : 2.2063,
            "duration" : 0.00982,
            "mean" : 43.50115517357316
        },
        {
            "std" : 2.2609553707003709,
            "end" : 2.21758,
            "name" : "Segment",
            "min" : 32.262643920875071,
            "max" : 43.341557031759038,
            "start" : 2.21612,
            "duration" : 0.00146,
            "mean" : 38.645227109635861
        },
        {
            "std" : 0.79002074401629019,
            "end" : 2.49584,
            "name" : "Segment",
            "min" : 19.620637820435103,
            "max" : 31.490681513410138,
            "start" : 2.21758,
            "duration" : 0.27826,
            "mean" : 24.972348703769701
        },
        {
            "std" : 0.86480352083497092,
            "end" : 2.53453,
            "name" : "Segment",
            "min" : 21.049405354236761,
            "max" : 27.060828270536032,
            "start" : 2.49584,
            "duration" : 0.03869,
            "mean" : 25.076906128928872
        },
        {
            "std" : 0.67531307847585054,
            "end" : 2.61233,
            "name" : "Segment",
            "min" : 21.023216363460513,
            "max" : 27.006107254754276,
            "start" : 2.53453,
            "duration" : 0.0778,
            "mean" : 24.699325469865439
        },
        {
            "std" : 0.77786869908045209,
            "end" : 2.6628,
            "name" : "Segment",
            "min" : 20.842022593109785,
            "max" : 27.208639351745823,
            "start" : 2.61233,
            "duration" : 0.05047,
            "mean" : 25.00271868731744
        },
        {
            "std" : 0.7320436628793644,
            "end" : 2.77366,
            "name" : "Segment",
            "min" : 19.512263570882933,
            "max" : 26.781481630373658,
            "start" : 2.6628,
            "duration" : 0.11086,
            "mean" : 24.721797562103117
        },
        {
            "std" : 0.7863250452680457,
            "end" : 2.86614,
            "name" : "Segment",
            "min" : 20.77736850648115,
            "max" : 27.440580476766637,
            "start" : 2.77366,
            "duration" : 0.09248,
            "mean" : 25.13215073766499
        },
        {
            "std" : 0.84587291588632152,
            "end" : 2.88563,
            "name" : "Segment",
            "min" : 21.009454384027045,
            "max" : 26.246393208546532,
            "start" : 2.86614,
            "duration" : 0.01949,
            "mean" : 24.461595879122353
        },
        {
            "std" : 0.72388985252499094,
            "end" : 2.91978,
            "name" : "Segment",
            "min" : 21.622587220258229,
            "max" : 26.788976403267093,
            "start" : 2.88563,
            "duration" : 0.03415,
            "mean" : 24.835179769720963
        },
        {
            "std" : 0.65467742330243917,
            "end" : 2.9469,
            "name" : "Segment",
            "min" : 22.824916107162522,
            "max" : 26.919965489496931,
            "start" : 2.91978,
            "duration" : 0.02712,
            "mean" : 25.185204916362171
        },
        {
            "std" : 1.0025313199948713,
            "end" : 2.96258,
            "name" : "Segment",
            "min" : 19.45663868200343,
            "max" : 26.939940591990531,
            "start" : 2.9469,
            "duration" : 0.01568,
            "mean" : 24.657784581766286
        },
        {
            "std" : 0.69830503468049143,
            "end" : 3.04015,
            "name" : "Segment",
            "min" : 22.057420488113586,
            "max" : 27.037114472825895,
            "start" : 2.96258,
            "duration" : 0.07757,
            "mean" : 25.138816279447092
        },
        {
            "std" : 0.71095340479239733,
            "end" : 3.09131,
            "name" : "Segment",
            "min" : 20.379996951510854,
            "max" : 26.846536456796642,
            "start" : 3.04015,
            "duration" : 0.05116,
            "mean" : 24.681328798376455
        },
        {
            "std" : 1.9176157642798124,
            "end" : 3.09231,
            "name" : "Segment",
            "min" : 19.106539145657901,
            "max" : 25.547961518273084,
            "start" : 3.09131,
            "duration" : 0.001,
            "mean" : 23.186930352963895
        },
        {
            "std" : 0.71388542984254266,
            "end" : 3.28004,
            "name" : "Segment",
            "min" : 20.469672589351354,
            "max" : 26.512237628567462,
            "start" : 3.09231,
            "duration" : 0.18773,
            "mean" : 24.605033691757392
        },
        {
            "std" : 1.949753086573947,
            "end" : 3.28122,
            "name" : "Segment",
            "min" : 19.899987884752097,
            "max" : 26.543661453368614,
            "start" : 3.28004,
            "duration" : 0.00118,
            "mean" : 24.336158569987589
        },
        {
            "std" : 0.72608414498674134,
            "end" : 3.35945,
            "name" : "Segment",
            "min" : 20.489055989693167,
            "max" : 27.037239450649608,
            "start" : 3.28122,
            "duration" : 0.07823,
            "mean" : 25.12206076487346
        },
        {
            "std" : 0.75924398278763749,
            "end" : 3.51649,
            "name" : "Segment",
            "min" : 19.479003616439091,
            "max" : 27.09222615949491,
            "start" : 3.35945,
            "duration" : 0.15704,
            "mean" : 24.747875665163395
        },
        {
            "std" : 1.6099499733862235,
            "end" : 3.51749,
            "name" : "Segment",
            "min" : 19.691598724794495,
            "max" : 25.028276892435208,
            "start" : 3.51649,
            "duration" : 0.001,
            "mean" : 22.97045343419088
        },
        {
            "std" : 0.73170709332077244,
            "end" : 3.63635,
            "name" : "Segment",
            "min" : 20.451341368918673,
            "max" : 26.882155678160029,
            "start" : 3.51749,
            "duration" : 0.11886,
            "mean" : 24.798266181662417
        },
        {
            "std" : 0.73241852519018491,
            "end" : 3.71841,
            "name" : "Segment",
            "min" : 20.887985652579498,
            "max" : 27.209871466833516,
            "start" : 3.63635,
            "duration" : 0.08206,
            "mean" : 25.142377459943802
        },
        {
            "std" : 0.47360746980599139,
            "end" : 3.72993,
            "name" : "Segment",
            "min" : 23.052985437831634,
            "max" : 25.89521361409739,
            "start" : 3.71841,
            "duration" : 0.01152,
            "mean" : 24.665816773398305
        },
        {
            "std" : 0.75506971302267123,
            "end" : 3.77395,
            "name" : "Segment",
            "min" : 21.05905144413342,
            "max" : 27.137472098347089,
            "start" : 3.72993,
            "duration" : 0.04402,
            "mean" : 24.936802201678397
        },
        {
            "std" : 0.63282385199557678,
            "end" : 3.7992,
            "name" : "Segment",
            "min" : 22.917961997849552,
            "max" : 26.996153471378726,
            "start" : 3.77395,
            "duration" : 0.02525,
            "mean" : 25.333377061290815
        },
        {
            "std" : 0.91046916640565612,
            "end" : 3.82729,
            "name" : "Segment",
            "min" : 20.609761850765157,
            "max" : 26.918732364970861,
            "start" : 3.7992,
            "duration" : 0.02809,
            "mean" : 24.723983036799901
        },
        {
            "std" : 0.70076332250466189,
            "end" : 3.87543,
            "name" : "Segment",
            "min" : 22.344132879089987,
            "max" : 27.577223369402997,
            "start" : 3.82729,
            "duration" : 0.04814,
            "mean" : 25.224082881006431
        },
        {
            "std" : 0.98486214564759011,
            "end" : 3.88616,
            "name" : "Segment",
            "min" : 21.282458927072508,
            "max" : 26.716094159797855,
            "start" : 3.87543,
            "duration" : 0.01073,
            "mean" : 24.788439491412596
        },
        {
            "std" : 0.60913333734272723,
            "end" : 3.95161,
            "name" : "Segment",
            "min" : 21.820255499583162,
            "max" : 26.889249624798463,
            "start" : 3.88616,
            "duration" : 0.06545,
            "mean" : 25.076280564628735
        },
        {
            "std" : 0.81012363495171236,
            "end" : 4.03497,
            "name" : "Segment",
            "min" : 21.388117836936562,
            "max" : 27.511235553654032,
            "start" : 3.95161,
            "duration" : 0.08336,
            "mean" : 24.955022033341773
        },
        {
            "std" : 0.5616931085753134,
            "end" : 4.07087,
            "name" : "Segment",
            "min" : 23.880666004863432,
            "max" : 26.992411703824839,
            "start" : 4.03497,
            "duration" : 0.0359,
            "mean" : 25.438323279814323
        },
        {
            "std" : 0.3066444608871291,
            "end" : 4.07675,
            "name" : "Segment",
            "min" : 24.186043695185013,
            "max" : 26.061459288282844,
            "start" : 4.07087,
            "duration" : 0.00588,
            "mean" : 24.950006391237807
        },
        {
            "std" : 0.67369914627173411,
            "end" : 4.11498,
            "name" : "Segment",
            "min" : 20.663295547237965,
            "max" : 26.63735007300966,
            "start" : 4.07675,
            "duration" : 0.03823,
            "mean" : 24.855645901513512
        },
        {
            "std" : 0.68077686693337869,
            "end" : 4.25043,
            "name" : "Segment",
            "min" : 20.756125589653806,
            "max" : 28.702422888343808,
            "start" : 4.11498,
            "duration" : 0.13545,
            "mean" : 25.189832518520003
        },
        {
            "std" : 0.87441043323196355,
            "end" : 4.27907,
            "name" : "Segment",
            "min" : 21.789255730945094,
            "max" : 28.614645121662679,
            "start" : 4.25043,
            "duration" : 0.02864,
            "mean" : 25.65413316963415
        },
        {
            "std" : 0.75770446082570075,
            "end" : 4.30272,
            "name" : "Segment",
            "min" : 21.974827998784875,
            "max" : 27.404730639349783,
            "start" : 4.27907,
            "duration" : 0.02365,
            "mean" : 24.898466590402492
        },
        {
            "std" : 1.1271981211267252,
            "end" : 4.31111,
            "name" : "Segment",
            "min" : 21.675742010647607,
            "max" : 27.745316206807555,
            "start" : 4.30272,
            "duration" : 0.00839,
            "mean" : 25.468836149018845
        },
        {
            "std" : 0.75436678782954136,
            "end" : 4.36449,
            "name" : "Segment",
            "min" : 22.278242775190286,
            "max" : 28.118487071534656,
            "start" : 4.31111,
            "duration" : 0.05338,
            "mean" : 25.995306840919927
        },
        {
            "std" : 1.7964429982593053,
            "end" : 4.45645,
            "name" : "Segment",
            "min" : 25.803223756493814,
            "max" : 36.576941233644163,
            "start" : 4.36449,
            "duration" : 0.09196,
            "mean" : 31.447554143237859
        },
        {
            "std" : 1.4734847007286389,
            "end" : 4.54393,
            "name" : "Segment",
            "min" : 27.4420534277276,
            "max" : 39.258844182682772,
            "start" : 4.45645,
            "duration" : 0.08748,
            "mean" : 33.435152044289623
        },
        {
            "std" : 0.96679214529903312,
            "end" : 4.56631,
            "name" : "Segment",
            "min" : 31.34887521992831,
            "max" : 36.395590326864792,
            "start" : 4.54393,
            "duration" : 0.02238,
            "mean" : 33.559483659001621
        },
        {
            "std" : 1.546963992028564,
            "end" : 4.5811,
            "name" : "Segment",
            "min" : 30.335257243106096,
            "max" : 38.6959192480019,
            "start" : 4.56631,
            "duration" : 0.01479,
            "mean" : 33.516573716929607
        },
        {
            "std" : 1.1724728684743875,
            "end" : 4.62566,
            "name" : "Segment",
            "min" : 37.936996434104039,
            "max" : 46.765179243786967,
            "start" : 4.5811,
            "duration" : 0.04456,
            "mean" : 43.654442928186718
        },
        {
            "std" : 0.89499734971873135,
            "end" : 4.65185,
            "name" : "Segment",
            "min" : 41.364960896398955,
            "max" : 46.19031647126539,
            "start" : 4.62566,
            "duration" : 0.02619,
            "mean" : 44.194167832116229
        },
        {
            "std" : 2.012403643076587,
            "end" : 4.66156,
            "name" : "Segment",
            "min" : 33.052492238139692,
            "max" : 43.898187504168966,
            "start" : 4.65185,
            "duration" : 0.00971,
            "mean" : 41.14044932566874
        },
        {
            "std" : 1.2918318287286286,
            "end" : 4.67407,
            "name" : "Segment",
            "min" : 38.58327133937069,
            "max" : 44.878533623145884,
            "start" : 4.66156,
            "duration" : 0.01251,
            "mean" : 42.468075133413926
        },
        {
            "std" : 1.7138800534964902,
            "end" : 4.69785,
            "name" : "Segment",
            "min" : 32.267023397474205,
            "max" : 43.543708670647426,
            "start" : 4.67407,
            "duration" : 0.02378,
            "mean" : 39.814455376697346
        },
        {
            "std" : 2.5824194674618655,
            "end" : 4.69993,
            "name" : "Segment",
            "min" : 30.310638278452281,
            "max" : 41.796036203806921,
            "start" : 4.69785,
            "duration" : 0.00208,
            "mean" : 36.881799886325723
        },
        {
            "std" : 1.5397040134824169,
            "end" : 4.73477,
            "name" : "Segment",
            "min" : 17.470368589522941,
            "max" : 29.617947698726155,
            "start" : 4.69993,
            "duration" : 0.03484,
            "mean" : 21.714255123116775
        },
        {
            "std" : 0.93028332317285656,
            "end" : 4.74646,
            "name" : "Segment",
            "min" : 16.313515748271133,
            "max" : 21.60089610059034,
            "start" : 4.73477,
            "duration" : 0.01169,
            "mean" : 19.400552440873597
        },
        {
            "std" : 1.2196221767010049,
            "end" : 4.74779,
            "name" : "Segment",
            "min" : 20.545348558167152,
            "max" : 25.374933364751151,
            "start" : 4.74646,
            "duration" : 0.00133,
            "mean" : 22.794566215448473
        },
        {
            "std" : 1.6691925856454137,
            "end" : 4.83665,
            "name" : "Segment",
            "min" : 15.461424696867931,
            "max" : 25.743024004421212,
            "start" : 4.74779,
            "duration" : 0.08886,
            "mean" : 19.828222204761893
        },
        {
            "std" : 0.90925360993369131,
            "end" : 4.85418,
            "name" : "Segment",
            "min" : 16.605537775963402,
            "max" : 21.192449100614759,
            "start" : 4.83665,
            "duration" : 0.01753,
            "mean" : 19.033842546778327
        },
        {
            "std" : 1.6268593165147396,
            "end" : 4.88274,
            "name" : "Segment",
            "min" : 16.486211494667145,
            "max" : 26.309075301825889,
            "start" : 4.85418,
            "duration" : 0.02856,
            "mean" : 21.42614980385914
        },
        {
            "std" : 4.3076662257187586,
            "end" : 4.884,
            "name" : "Segment",
            "min" : 20.58294952447298,
            "max" : 35.552882716445502,
            "start" : 4.88274,
            "duration" : 0.00126,
            "mean" : 26.262581601364598
        },
        {
            "std" : 1.6373441590566304,
            "end" : 4.88989,
            "name" : "Segment",
            "min" : 17.854955922623919,
            "max" : 25.87763571241647,
            "start" : 4.884,
            "duration" : 0.00589,
            "mean" : 21.838846876821687
        },
        {
            "std" : 1.1127891190492432,
            "end" : 4.90805,
            "name" : "Segment",
            "min" : 17.174006270107824,
            "max" : 25.147691423088396,
            "start" : 4.88989,
            "duration" : 0.01816,
            "mean" : 21.684771888222841
        },
        {
            "std" : 2.6253396066462495,
            "end" : 4.91272,
            "name" : "Segment",
            "min" : 19.648228056507111,
            "max" : 32.180764458386342,
            "start" : 4.90805,
            "duration" : 0.00467,
            "mean" : 23.628297175020201
        },
        {
            "std" : 1.1173501104269254,
            "end" : 4.92616,
            "name" : "Segment",
            "min" : 18.817402686864991,
            "max" : 24.06524147805284,
            "start" : 4.91272,
            "duration" : 0.01344,
            "mean" : 21.744856976382756
        },
        {
            "std" : 2.9837573443024925,
            "end" : 4.9279,
            "name" : "Segment",
            "min" : 18.286048183155437,
            "max" : 32.481707914134702,
            "start" : 4.92616,
            "duration" : 0.00174,
            "mean" : 21.748732576851236
        },
        {
            "std" : 1.7842283391581104,
            "end" : 5.01591,
            "name" : "Segment",
            "min" : 33.395287747071826,
            "max" : 49.144170957497536,
            "start" : 4.9279,
            "duration" : 0.08801,
            "mean" : 43.535833966727722
        },
        {
            "std" : 0.79164414522883253,
            "end" : 5.02003,
            "name" : "Segment",
            "min" : 43.23479237946912,
            "max" : 47.280723161596008,
            "start" : 5.01591,
            "duration" : 0.00412,
            "mean" : 45.504617216876369
        },
        {
            "std" : 0.9968767719455548,
            "end" : 5.03044,
            "name" : "Segment",
            "min" : 46.007190479816643,
            "max" : 50.567240674674039,
            "start" : 5.02003,
            "duration" : 0.01041,
            "mean" : 48.358649392023707
        },
        {
            "std" : 1.008416734492948,
            "end" : 5.13231,
            "name" : "Segment",
            "min" : 40.684825746730233,
            "max" : 50.082617822031196,
            "start" : 5.03044,
            "duration" : 0.10187,
            "mean" : 45.51972621108871
        },
        {
            "std" : 0.90078788535920529,
            "end" : 5.17303,
            "name" : "Segment",
            "min" : 43.101658927209513,
            "max" : 50.422742747268053,
            "start" : 5.13231,
            "duration" : 0.04072,
            "mean" : 48.473599606478068
        },
        {
            "std" : 1.0080045670283182,
            "end" : 5.19478,
            "name" : "Segment",
            "min" : 42.385388525829029,
            "max" : 49.409609086023593,
            "start" : 5.17303,
            "duration" : 0.02175,
            "mean" : 45.763722879780168
        },
        {
            "std" : 1.3919172038769265,
            "end" : 5.21503,
            "name" : "Segment",
            "min" : 37.727807084745081,
            "max" : 49.704188799458784,
            "start" : 5.19478,
            "duration" : 0.02025,
            "mean" : 45.078860444926356
        },
        {
            "std" : 0.91361753684629732,
            "end" : 5.26437,
            "name" : "Segment",
            "min" : 41.209800650379123,
            "max" : 48.645251144944737,
            "start" : 5.21503,
            "duration" : 0.04934,
            "mean" : 45.405638558794898
        },
        {
            "std" : 0.80720133562502627,
            "end" : 5.36226,
            "name" : "Segment",
            "min" : 44.839223821900099,
            "max" : 50.679903713511862,
            "start" : 5.26437,
            "duration" : 0.09789,
            "mean" : 48.472440826880749
        },
        {
            "std" : 2.0603701413757798,
            "end" : 5.36326,
            "name" : "Segment",
            "min" : 41.991120672207273,
            "max" : 49.554150383422176,
            "start" : 5.36226,
            "duration" : 0.001,
            "mean" : 46.793908018114031
        },
        {
            "std" : 0.87434670471803677,
            "end" : 5.37494,
            "name" : "Segment",
            "min" : 45.031585642632976,
            "max" : 50.781082551578891,
            "start" : 5.36326,
            "duration" : 0.01168,
            "mean" : 48.483234940394574
        },
        {
            "std" : 0.83206678314349491,
            "end" : 5.43713,
            "name" : "Segment",
            "min" : 40.392151572058779,
            "max" : 49.805192306361178,
            "start" : 5.37494,
            "duration" : 0.06219,
            "mean" : 47.372423772004652
        },
        {
            "std" : 0.67710047551650743,
            "end" : 5.58354,
            "name" : "Segment",
            "min" : 40.286150451559863,
            "max" : 45.992333444383604,
            "start" : 5.43713,
            "duration" : 0.14641,
            "mean" : 43.620716570681353
        },
        {
            "std" : 0.65060383842548064,
            "end" : 5.60146,
            "name" : "Segment",
            "min" : 39.897083457745822,
            "max" : 45.386819630845551,
            "start" : 5.58354,
            "duration" : 0.01792,
            "mean" : 43.219676322000289
        },
        {
            "std" : 0.4515945122721326,
            "end" : 5.61006,
            "name" : "Segment",
            "min" : 41.17292047224592,
            "max" : 43.35416124255913,
            "start" : 5.60146,
            "duration" : 0.0086,
            "mean" : 42.317394455047179
        },
        {
            "std" : 1.3736922804706948,
            "end" : 5.61267,
            "name" : "Segment",
            "min" : 34.626029273975924,
            "max" : 41.161479297547949,
            "start" : 5.61006,
            "duration" : 0.00261,
            "mean" : 38.548311660094981
        },
        {
            "std" : 0.63826826587206886,
            "end" : 5.65912,
            "name" : "Segment",
            "min" : 36.179004475053787,
            "max" : 40.952438583390133,
            "start" : 5.61267,
            "duration" : 0.04645,
            "mean" : 39.166886061804732
        },
        {
            "std" : 0.65948148095682246,
            "end" : 5.6642,
            "name" : "Segment",
            "min" : 36.375384774860947,
            "max" : 39.358497641767812,
            "start" : 5.65912,
            "duration" : 0.00508,
            "mean" : 37.83338136272058
        },
        {
            "std" : 0.87864431194544412,
            "end" : 5.70256,
            "name" : "Segment",
            "min" : 30.262434440060293,
            "max" : 38.008270612631321,
            "start" : 5.6642,
            "duration" : 0.03836,
            "mean" : 34.531077294658246
        },
        {
            "std" : 0.98211112739378303,
            "end" : 5.77056,
            "name" : "Segment",
            "min" : 31.181241209876923,
            "max" : 38.994481857093291,
            "start" : 5.70256,
            "duration" : 0.068,
            "mean" : 33.853174947436763
        },
        {
            "std" : 1.5394838757270768,
            "end" : 5.81285,
            "name" : "Segment",
            "min" : 37.259581920267323,
            "max" : 47.728964291957176,
            "start" : 5.77056,
            "duration" : 0.04229,
            "mean" : 41.98200550432486
        },
        {
            "std" : 1.3267380652503644,
            "end" : 5.81597,
            "name" : "Segment",
            "min" : 42.212378549708689,
            "max" : 47.7462227107155,
            "start" : 5.81285,
            "duration" : 0.00312,
            "mean" : 45.034908189958891
        },
        {
            "std" : 1.2392676609422069,
            "end" : 6.03751,
            "name" : "Segment",
            "min" : 37.813396145231572,
            "max" : 49.05436305116887,
            "start" : 5.81597,
            "duration" : 0.22154,
            "mean" : 43.445573468930576
        },
        {
            "std" : 0.99419087916335358,
            "end" : 6.04673,
            "name" : "Segment",
            "min" : 43.118349523610945,
            "max" : 48.27901961280768,
            "start" : 6.03751,
            "duration" : 0.00922,
            "mean" : 46.308134125898142
        },
        {
            "std" : 0.89353354289454767,
            "end" : 6.0609,
            "name" : "Segment",
            "min" : 42.19831003956331,
            "max" : 46.969417150233063,
            "start" : 6.04673,
            "duration" : 0.01417,
            "mean" : 44.796024510998215
        },
        {
            "std" : 1.2175282459375845,
            "end" : 6.07904,
            "name" : "Segment",
            "min" : 37.763080370586195,
            "max" : 45.716928177233356,
            "start" : 6.0609,
            "duration" : 0.01814,
            "mean" : 43.808501187184994
        },
        {
            "std" : 1.0519523706867386,
            "end" : 6.09555,
            "name" : "Segment",
            "min" : 32.887378226636464,
            "max" : 39.81368739900131,
            "start" : 6.07904,
            "duration" : 0.01651,
            "mean" : 36.77192612140005
        },
        {
            "std" : 0.76077288012939948,
            "end" : 6.11377,
            "name" : "Segment",
            "min" : 31.528075039697647,
            "max" : 38.167385515359996,
            "start" : 6.09555,
            "duration" : 0.01822,
            "mean" : 35.69066942181734
        },
        {
            "std" : 0.87041743581706177,
            "end" : 6.16364,
            "name" : "Segment",
            "min" : 32.070393771549917,
            "max" : 40.896290764764586,
            "start" : 6.11377,
            "duration" : 0.04987,
            "mean" : 36.917056910230642
        },
        {
            "std" : 0.92982132459380784,
            "end" : 6.16832,
            "name" : "Segment",
            "min" : 38.718475568298082,
            "max" : 43.018736790203555,
            "start" : 6.16364,
            "duration" : 0.00468,
            "mean" : 41.106351086207489
        },
        {
            "std" : 2.2503932418205426,
            "end" : 6.17371,
            "name" : "Segment",
            "min" : 39.208683906365309,
            "max" : 48.044600332834897,
            "start" : 6.16832,
            "duration" : 0.00539,
            "mean" : 43.309106456285548
        },
        {
            "std" : 1.0834983983956001,
            "end" : 6.17899,
            "name" : "Segment",
            "min" : 38.171930793979151,
            "max" : 42.903514833376988,
            "start" : 6.17371,
            "duration" : 0.00528,
            "mean" : 40.950856438207182
        },
        {
            "std" : 1.4057284353415642,
            "end" : 6.22077,
            "name" : "Segment",
            "min" : 37.629343266808839,
            "max" : 47.114971805734157,
            "start" : 6.17899,
            "duration" : 0.04178,
            "mean" : 42.734945383376861
        },
        {
            "std" : 3.7520921076648697,
            "end" : 6.22485,
            "name" : "Segment",
            "min" : 40.234400001597379,
            "max" : 53.170571236782997,
            "start" : 6.22077,
            "duration" : 0.00408,
            "mean" : 45.771661636188334
        },
        {
            "std" : 1.2291445373823275,
            "end" : 6.23581,
            "name" : "Segment",
            "min" : 39.543479292263086,
            "max" : 47.317572176105266,
            "start" : 6.22485,
            "duration" : 0.01096,
            "mean" : 42.921612166300314
        },
        {
            "std" : 1.5239200204947088,
            "end" : 6.28776,
            "name" : "Segment",
            "min" : 44.947882819060673,
            "max" : 55.556468198484588,
            "start" : 6.23581,
            "duration" : 0.05195,
            "mean" : 51.395833340520653
        },
        {
            "std" : 0.99423798289279763,
            "end" : 6.3276,
            "name" : "Segment",
            "min" : 49.235897123662326,
            "max" : 54.853819803364416,
            "start" : 6.28776,
            "duration" : 0.03984,
            "mean" : 52.287301743887141
        },
        {
            "std" : 1.2211365696348433,
            "end" : 6.37075,
            "name" : "Segment",
            "min" : 44.350517725145394,
            "max" : 54.250863615446569,
            "start" : 6.3276,
            "duration" : 0.04315,
            "mean" : 51.809009326214898
        },
        {
            "std" : 2.0724384008242658,
            "end" : 6.38737,
            "name" : "Segment",
            "min" : 36.011671519598387,
            "max" : 49.27605739082064,
            "start" : 6.37075,
            "duration" : 0.01662,
            "mean" : 45.60612394514888
        },
        {
            "std" : 2.4597137882248288,
            "end" : 6.39242,
            "name" : "Segment",
            "min" : 36.978258518759937,
            "max" : 47.698007128459167,
            "start" : 6.38737,
            "duration" : 0.00505,
            "mean" : 42.4358758714868
        },
        {
            "std" : 1.624450833512372,
            "end" : 6.42307,
            "name" : "Segment",
            "min" : 39.846547725911222,
            "max" : 50.190369191777918,
            "start" : 6.39242,
            "duration" : 0.03065,
            "mean" : 45.522137301064404
        },
        {
            "std" : 2.0913238644087153,
            "end" : 6.43522,
            "name" : "Segment",
            "min" : 26.656036000954551,
            "max" : 40.059125345310797,
            "start" : 6.42307,
            "duration" : 0.01215,
            "mean" : 32.52899564881475
        },
        {
            "std" : 2.7017216365252015,
            "end" : 6.43666,
            "name" : "Segment",
            "min" : 28.808716604139178,
            "max" : 38.36281937363281,
            "start" : 6.43522,
            "duration" : 0.00144,
            "mean" : 34.127463783564401
        },
        {
            "std" : 2.0276281875229918,
            "end" : 6.43918,
            "name" : "Segment",
            "min" : 21.293929163369789,
            "max" : 29.866755313578778,
            "start" : 6.43666,
            "duration" : 0.00252,
            "mean" : 25.001667470009963
        },
        {
            "std" : 2.6889408732488991,
            "end" : 6.45597,
            "name" : "Segment",
            "min" : 24.655702666785334,
            "max" : 40.306858306752524,
            "start" : 6.43918,
            "duration" : 0.01679,
            "mean" : 33.216284317930715
        },
        {
            "std" : 2.2134580008889246,
            "end" : 6.46039,
            "name" : "Segment",
            "min" : 15.80401952693061,
            "max" : 31.775292197809303,
            "start" : 6.45597,
            "duration" : 0.00442,
            "mean" : 18.862574768107585
        },
        {
            "std" : 3.0265492820406426,
            "end" : 6.48798,
            "name" : "Segment",
            "min" : 22.861381678351215,
            "max" : 45.135909080717077,
            "start" : 6.46039,
            "duration" : 0.02759,
            "mean" : 35.316125725355626
        },
        {
            "std" : 1.9096204356762585,
            "end" : 6.49274,
            "name" : "Segment",
            "min" : 13.081121256084078,
            "max" : 31.225740122434136,
            "start" : 6.48798,
            "duration" : 0.00476,
            "mean" : 17.613395417649325
        },
        {
            "std" : 2.6141430771637801,
            "end" : 6.52845,
            "name" : "Segment",
            "min" : 27.008549443517374,
            "max" : 41.729415203120723,
            "start" : 6.49274,
            "duration" : 0.03571,
            "mean" : 35.212645307245957
        },
        {
            "std" : 3.1549104208928758,
            "end" : 6.53582,
            "name" : "Segment",
            "min" : 24.55686275379793,
            "max" : 39.365637048703945,
            "start" : 6.52845,
            "duration" : 0.00737,
            "mean" : 32.990618406669824
        },
        {
            "std" : 2.5281943449282425,
            "end" : 6.56068,
            "name" : "Segment",
            "min" : 28.094570099579098,
            "max" : 43.255554150553621,
            "start" : 6.53582,
            "duration" : 0.02486,
            "mean" : 36.29486275331265
        },
        {
            "std" : 2.7255788777051628,
            "end" : 6.61532,
            "name" : "Segment",
            "min" : 26.899841664588862,
            "max" : 42.956788733116305,
            "start" : 6.56068,
            "duration" : 0.05464,
            "mean" : 33.322917096327906
        },
        {
            "std" : 1.6314820127241487,
            "end" : 6.65627,
            "name" : "Segment",
            "min" : 13.256239416673612,
            "max" : 27.365714515862834,
            "start" : 6.61532,
            "duration" : 0.04095,
            "mean" : 18.13074911423713
        },
        {
            "std" : 2.4223894372894992,
            "end" : 6.7114,
            "name" : "Segment",
            "min" : 22.619928450770111,
            "max" : 40.547085693100954,
            "start" : 6.65627,
            "duration" : 0.05513,
            "mean" : 33.327096718220396
        },
        {
            "std" : 1.7011477905884986,
            "end" : 6.73095,
            "name" : "Segment",
            "min" : 12.602716202191003,
            "max" : 26.513215680371275,
            "start" : 6.7114,
            "duration" : 0.01955,
            "mean" : 18.272816403916821
        },
        {
            "std" : 12.176345341266085,
            "end" : 6.73195,
            "name" : "Segment",
            "min" : 18.392556429457613,
            "max" : 51.268988671365065,
            "start" : 6.73095,
            "duration" : 0.001,
            "mean" : 37.946996399122902
        },
        {
            "std" : 1.6414902549900188,
            "end" : 6.77408,
            "name" : "Segment",
            "min" : 14.060055265383065,
            "max" : 24.757325463740479,
            "start" : 6.73195,
            "duration" : 0.04213,
            "mean" : 18.339983547083488
        },
        {
            "std" : 2.7431503214458179,
            "end" : 6.80039,
            "name" : "Segment",
            "min" : 23.36903439140405,
            "max" : 40.271033366142703,
            "start" : 6.77408,
            "duration" : 0.02631,
            "mean" : 32.183304422288799
        },
        {
            "std" : 1.7719245925315916,
            "end" : 6.82376,
            "name" : "Segment",
            "min" : 13.38219075684105,
            "max" : 24.745159778673425,
            "start" : 6.80039,
            "duration" : 0.02337,
            "mean" : 17.90719444994987
        },
        {
            "std" : 5.5605023041682804,
            "end" : 6.82572,
            "name" : "Segment",
            "min" : 17.550077904310356,
            "max" : 39.812518628211919,
            "start" : 6.82376,
            "duration" : 0.00196,
            "mean" : 22.491396065825676
        },
        {
            "std" : 1.5307835390899232,
            "end" : 6.83882,
            "name" : "Segment",
            "min" : 13.861863935702747,
            "max" : 21.538304851586808,
            "start" : 6.82572,
            "duration" : 0.0131,
            "mean" : 17.652468476457297
        },
        {
            "std" : 0.97458175547215486,
            "end" : 6.95977,
            "name" : "Segment",
            "min" : 12.029077230579519,
            "max" : 22.580064558320682,
            "start" : 6.83882,
            "duration" : 0.12095,
            "mean" : 14.704924457990879
        },
        {
            "std" : 1.1639178407609332,
            "end" : 6.9985,
            "name" : "Segment",
            "min" : 11.818738248495649,
            "max" : 21.6028867199012,
            "start" : 6.95977,
            "duration" : 0.03873,
            "mean" : 14.882417127795859
        },
        {
            "std" : 0.86033366990061744,
            "end" : 7.18833,
            "name" : "Segment",
            "min" : 11.171472343881318,
            "max" : 19.819556342266548,
            "start" : 6.9985,
            "duration" : 0.18983,
            "mean" : 14.618171623323438
        },
        {
            "std" : 1.0924965134647828,
            "end" : 7.18933,
            "name" : "Segment",
            "min" : 14.239821180208446,
            "max" : 18.826310762083363,
            "start" : 7.18833,
            "duration" : 0.001,
            "mean" : 16.661089931249968
        },
        {
            "std" : 0.92820000990538953,
            "end" : 7.58045,
            "name" : "Segment",
            "min" : 11.484956523158743,
            "max" : 19.992630804507627,
            "start" : 7.18933,
            "duration" : 0.39112,
            "mean" : 14.594159636622486
        },
        {
            "std" : 3.4757692241502141,
            "end" : 7.59207,
            "name" : "Segment",
            "min" : 14.070222829603198,
            "max" : 32.347954852566772,
            "start" : 7.58045,
            "duration" : 0.01162,
            "mean" : 19.609234188296998
        },
        {
            "std" : 2.648517518305435,
            "end" : 7.59437,
            "name" : "Segment",
            "min" : 24.817989454997644,
            "max" : 39.176034011513586,
            "start" : 7.59207,
            "duration" : 0.0023,
            "mean" : 35.352444585335867
        },
        {
            "std" : 8.5033254878733029,
            "end" : 7.60022,
            "name" : "Segment",
            "min" : 14.707962734673869,
            "max" : 42.526109672310128,
            "start" : 7.59437,
            "duration" : 0.00585,
            "mean" : 29.006572176039512
        },
        {
            "std" : 3.7536694874733549,
            "end" : 7.60539,
            "name" : "Segment",
            "min" : 24.723704582840455,
            "max" : 42.75982302696994,
            "start" : 7.60022,
            "duration" : 0.00517,
            "mean" : 35.93525744264732
        },
        {
            "std" : 3.0033909190093304,
            "end" : 7.61785,
            "name" : "Segment",
            "min" : 14.717542064140355,
            "max" : 28.937105367521827,
            "start" : 7.60539,
            "duration" : 0.01246,
            "mean" : 21.575835125162445
        },
        {
            "std" : 0.87182982921296315,
            "end" : 7.62513,
            "name" : "Segment",
            "min" : 13.553623677908309,
            "max" : 19.76444302309006,
            "start" : 7.61785,
            "duration" : 0.00728,
            "mean" : 15.672809695706574
        },
        {
            "std" : 1.414706523517711,
            "end" : 7.63604,
            "name" : "Segment",
            "min" : 13.779395651682457,
            "max" : 21.807121108331241,
            "start" : 7.62513,
            "duration" : 0.01091,
            "mean" : 16.892184982966729
        },
        {
            "std" : 2.7499785148361937,
            "end" : 7.64181,
            "name" : "Segment",
            "min" : 13.748759010092231,
            "max" : 27.282098052208525,
            "start" : 7.63604,
            "duration" : 0.00577,
            "mean" : 19.680589292907833
        },
        {
            "std" : 0.82291224023235665,
            "end" : 7.66707,
            "name" : "Segment",
            "min" : 12.086501305239578,
            "max" : 16.923273603328134,
            "start" : 7.64181,
            "duration" : 0.02526,
            "mean" : 14.514943713865138
        },
        {
            "std" : 2.9082901242519266,
            "end" : 7.67582,
            "name" : "Segment",
            "min" : 12.534929638649523,
            "max" : 25.17820339732252,
            "start" : 7.66707,
            "duration" : 0.00875,
            "mean" : 18.020499828472307
        },
        {
            "std" : 0.86908932966234986,
            "end" : 7.70078,
            "name" : "Segment",
            "min" : 12.442704349511672,
            "max" : 17.492152207626898,
            "start" : 7.67582,
            "duration" : 0.02496,
            "mean" : 14.514436680504824
        },
        {
            "std" : 3.119814366856863,
            "end" : 7.70271,
            "name" : "Segment",
            "min" : 14.295994544100598,
            "max" : 24.759176820139768,
            "start" : 7.70078,
            "duration" : 0.00193,
            "mean" : 18.085743574394233
        },
        {
            "std" : 2.77995033711059,
            "end" : 7.70821,
            "name" : "Segment",
            "min" : 16.954963030663812,
            "max" : 28.018586144968555,
            "start" : 7.70271,
            "duration" : 0.0055,
            "mean" : 21.910282788423153
        },
        {
            "std" : 3.0871413475189673,
            "end" : 7.71049,
            "name" : "Segment",
            "min" : 27.011898851683149,
            "max" : 45.916649838721291,
            "start" : 7.70821,
            "duration" : 0.00228,
            "mean" : 43.302613032078341
        },
        {
            "std" : 4.5377300160336906,
            "end" : 7.71334,
            "name" : "Segment",
            "min" : 15.313951994302926,
            "max" : 36.998882418066721,
            "start" : 7.71049,
            "duration" : 0.00285,
            "mean" : 21.290537278480873
        },
        {
            "std" : 2.5214582607961398,
            "end" : 7.71468,
            "name" : "Segment",
            "min" : 24.670508217099421,
            "max" : 38.252573413732222,
            "start" : 7.71334,
            "duration" : 0.00134,
            "mean" : 36.070415636592827
        },
        {
            "std" : 3.0442526689477019,
            "end" : 7.72922,
            "name" : "Segment",
            "min" : 13.692745894594527,
            "max" : 28.234620925461716,
            "start" : 7.71468,
            "duration" : 0.01454,
            "mean" : 19.296610024510475
        },
        {
            "std" : 1.1757187441909367,
            "end" : 7.73326,
            "name" : "Segment",
            "min" : 12.954349766404556,
            "max" : 18.523848913291811,
            "start" : 7.72922,
            "duration" : 0.00404,
            "mean" : 15.238459922557171
        },
        {
            "std" : 2.0862251342489735,
            "end" : 7.73426,
            "name" : "Segment",
            "min" : 16.784486221622057,
            "max" : 24.2398954731948,
            "start" : 7.73326,
            "duration" : 0.001,
            "mean" : 19.876862699484654
        },
        {
            "std" : 1.1670206859523438,
            "end" : 7.74637,
            "name" : "Segment",
            "min" : 11.729795546752547,
            "max" : 18.690759386698744,
            "start" : 7.73426,
            "duration" : 0.01211,
            "mean" : 15.387954651527657
        },
        {
            "std" : 2.021590309583893,
            "end" : 7.74974,
            "name" : "Segment",
            "min" : 14.90287170019834,
            "max" : 22.136891811018259,
            "start" : 7.74637,
            "duration" : 0.00337,
            "mean" : 17.658931856041811
        },
        {
            "std" : 2.5137171937338376,
            "end" : 7.75464,
            "name" : "Segment",
            "min" : 16.388625669608945,
            "max" : 26.134675860478119,
            "start" : 7.74974,
            "duration" : 0.0049,
            "mean" : 21.43116533317114
        },
        {
            "std" : 4.5505500090669528,
            "end" : 7.75629,
            "name" : "Segment",
            "min" : 23.005196162883532,
            "max" : 37.502962863481706,
            "start" : 7.75464,
            "duration" : 0.00165,
            "mean" : 30.359799354702755
        },
        {
            "std" : 2.9604661522969264,
            "end" : 7.77528,
            "name" : "Segment",
            "min" : 14.117966794628453,
            "max" : 25.986093635039591,
            "start" : 7.75629,
            "duration" : 0.01899,
            "mean" : 19.669918975117501
        },
        {
            "std" : 6.3955922535306886,
            "end" : 7.77628,
            "name" : "Segment",
            "min" : 17.01992526267475,
            "max" : 35.46075110164503,
            "start" : 7.77528,
            "duration" : 0.001,
            "mean" : 26.425888163831161
        },
        {
            "std" : 2.4604027597820779,
            "end" : 7.86938,
            "name" : "Segment",
            "min" : 26.830707688300009,
            "max" : 44.048549790657091,
            "start" : 7.77628,
            "duration" : 0.0931,
            "mean" : 35.801913620383132
        },
        {
            "std" : 1.1616068846458925,
            "end" : 7.87569,
            "name" : "Segment",
            "min" : 35.391714775089561,
            "max" : 40.83364602546564,
            "start" : 7.86938,
            "duration" : 0.00631,
            "mean" : 38.101582841284603
        },
        {
            "std" : 3.853205174411968,
            "end" : 7.88097,
            "name" : "Segment",
            "min" : 20.017965013928887,
            "max" : 38.491124085138651,
            "start" : 7.87569,
            "duration" : 0.00528,
            "mean" : 33.768246067124906
        },
        {
            "std" : 2.4853683633014567,
            "end" : 7.91166,
            "name" : "Segment",
            "min" : 24.802149613774901,
            "max" : 41.827710795784668,
            "start" : 7.88097,
            "duration" : 0.03069,
            "mean" : 36.865810317217097
        },
        {
            "std" : 1.1359909799625425,
            "end" : 7.91598,
            "name" : "Segment",
            "min" : 37.895323746021894,
            "max" : 43.225287746587441,
            "start" : 7.91166,
            "duration" : 0.00432,
            "mean" : 40.753969589528346
        },
        {
            "std" : 1.0263348950281916,
            "end" : 7.9216,
            "name" : "Segment",
            "min" : 36.154554201774381,
            "max" : 41.214057173965941,
            "start" : 7.91598,
            "duration" : 0.00562,
            "mean" : 39.226442891397348
        },
        {
            "std" : 1.0456118621488553,
            "end" : 7.93465,
            "name" : "Segment",
            "min" : 33.551509667955649,
            "max" : 39.708797398001252,
            "start" : 7.9216,
            "duration" : 0.01305,
            "mean" : 37.197384183046431
        },
        {
            "std" : 3.2080056603404565,
            "end" : 7.94337,
            "name" : "Segment",
            "min" : 25.680083090413273,
            "max" : 41.991059848389575,
            "start" : 7.93465,
            "duration" : 0.00872,
            "mean" : 35.06675658015849
        },
        {
            "std" : 1.4577880531574057,
            "end" : 7.95658,
            "name" : "Segment",
            "min" : 32.552956856858891,
            "max" : 42.755735827283694,
            "start" : 7.94337,
            "duration" : 0.01321,
            "mean" : 37.802812915159258
        },
        {
            "std" : 2.3856949848672429,
            "end" : 8.00563,
            "name" : "Segment",
            "min" : 27.911767397020643,
            "max" : 42.53093191215882,
            "start" : 7.95658,
            "duration" : 0.04905,
            "mean" : 36.72608853441487
        },
        {
            "std" : 1.9321968366986635,
            "end" : 8.00915,
            "name" : "Segment",
            "min" : 27.584385832740981,
            "max" : 36.799474540881675,
            "start" : 8.00563,
            "duration" : 0.00352,
            "mean" : 33.085259611836044
        },
        {
            "std" : 2.2786294521545596,
            "end" : 8.11866,
            "name" : "Segment",
            "min" : 26.406157682372978,
            "max" : 43.122669095763534,
            "start" : 8.00915,
            "duration" : 0.10951,
            "mean" : 36.987135715884484
        },
        {
            "std" : 1.6576828271347317,
            "end" : 8.13447,
            "name" : "Segment",
            "min" : 35.584954864029356,
            "max" : 45.613780014152255,
            "start" : 8.11866,
            "duration" : 0.01581,
            "mean" : 40.033862678304004
        },
        {
            "std" : 1.6107024368860976,
            "end" : 8.14191,
            "name" : "Segment",
            "min" : 32.959562163444104,
            "max" : 42.641692799831532,
            "start" : 8.13447,
            "duration" : 0.00744,
            "mean" : 38.523071312582445
        },
        {
            "std" : 1.6240272210314519,
            "end" : 8.17906,
            "name" : "Segment",
            "min" : 41.944734782914658,
            "max" : 51.11871936086682,
            "start" : 8.14191,
            "duration" : 0.03715,
            "mean" : 46.592337210629253
        },
        {
            "std" : 0.98627519482649706,
            "end" : 8.24183,
            "name" : "Segment",
            "min" : 44.650939215992032,
            "max" : 52.826362419271476,
            "start" : 8.17906,
            "duration" : 0.06277,
            "mean" : 50.047121392797855
        },
        {
            "std" : 2.0221772623012586,
            "end" : 8.24283,
            "name" : "Segment",
            "min" : 44.521997836581015,
            "max" : 50.841421865589197,
            "start" : 8.24183,
            "duration" : 0.001,
            "mean" : 47.284706927973829
        },
        {
            "std" : 0.80598229740280436,
            "end" : 8.3114,
            "name" : "Segment",
            "min" : 47.735940361411856,
            "max" : 52.927612484606357,
            "start" : 8.24283,
            "duration" : 0.06857,
            "mean" : 50.199166916763993
        },
        {
            "std" : 1.6912941265122794,
            "end" : 8.37161,
            "name" : "Segment",
            "min" : 40.258368543774495,
            "max" : 52.048855327873149,
            "start" : 8.3114,
            "duration" : 0.06021,
            "mean" : 46.483250833346325
        },
        {
            "std" : 0.86818223487179469,
            "end" : 8.4106,
            "name" : "Segment",
            "min" : 47.17290727549851,
            "max" : 52.703776089677227,
            "start" : 8.37161,
            "duration" : 0.03899,
            "mean" : 50.356695789324256
        },
        {
            "std" : 2.4674149717334104,
            "end" : 8.41366,
            "name" : "Segment",
            "min" : 40.905083766247571,
            "max" : 52.311079302608306,
            "start" : 8.4106,
            "duration" : 0.00306,
            "mean" : 46.466669678089467
        },
        {
            "std" : 0.92288035680333846,
            "end" : 8.48976,
            "name" : "Segment",
            "min" : 45.490015903994809,
            "max" : 52.678583532979331,
            "start" : 8.41366,
            "duration" : 0.0761,
            "mean" : 50.220825338546561
        },
        {
            "std" : 1.9400031271992646,
            "end" : 8.4974,
            "name" : "Segment",
            "min" : 45.305136244703824,
            "max" : 58.384414469598518,
            "start" : 8.48976,
            "duration" : 0.00764,
            "mean" : 49.642542229415525
        },
        {
            "std" : 0.95766920366975816,
            "end" : 8.54566,
            "name" : "Segment",
            "min" : 44.939105331288729,
            "max" : 52.347592919816492,
            "start" : 8.4974,
            "duration" : 0.04826,
            "mean" : 50.093155595615428
        },
        {
            "std" : 0.82718263935444336,
            "end" : 8.61806,
            "name" : "Segment",
            "min" : 44.463411607398172,
            "max" : 51.474688101802869,
            "start" : 8.54566,
            "duration" : 0.0724,
            "mean" : 49.025866546344318
        },
        {
            "std" : 0.89090250887180111,
            "end" : 8.66983,
            "name" : "Segment",
            "min" : 39.577027280098541,
            "max" : 48.630307056700495,
            "start" : 8.61806,
            "duration" : 0.05177,
            "mean" : 46.669372829481098
        },
        {
            "std" : 0.72107238880457747,
            "end" : 8.74497,
            "name" : "Segment",
            "min" : 42.338197318044671,
            "max" : 48.868469645484183,
            "start" : 8.66983,
            "duration" : 0.07514,
            "mean" : 46.44571452139521
        },
        {
            "std" : 0.89507323069586486,
            "end" : 8.79634,
            "name" : "Segment",
            "min" : 41.971749334168479,
            "max" : 49.290355430301801,
            "start" : 8.74497,
            "duration" : 0.05137,
            "mean" : 46.400317464273051
        },
        {
            "std" : 0.7639517650183042,
            "end" : 8.83918,
            "name" : "Segment",
            "min" : 40.245398542108539,
            "max" : 47.09199563132325,
            "start" : 8.79634,
            "duration" : 0.04284,
            "mean" : 45.224140977389666
        },
        {
            "std" : 1.4796077362715989,
            "end" : 8.84084,
            "name" : "Segment",
            "min" : 38.404463672139002,
            "max" : 44.960837251601141,
            "start" : 8.83918,
            "duration" : 0.00166,
            "mean" : 43.003563993428884
        },
        {
            "std" : 0.7524672578278323,
            "end" : 8.85537,
            "name" : "Segment",
            "min" : 41.67810398688934,
            "max" : 46.589794081343612,
            "start" : 8.84084,
            "duration" : 0.01453,
            "mean" : 44.493897214361347
        },
        {
            "std" : 0.49696346872234581,
            "end" : 8.86027,
            "name" : "Segment",
            "min" : 44.069899369228729,
            "max" : 46.329726406370732,
            "start" : 8.85537,
            "duration" : 0.0049,
            "mean" : 45.249204575984507
        },
        {
            "std" : 0.84723042302640172,
            "end" : 8.89506,
            "name" : "Segment",
            "min" : 38.428514684549285,
            "max" : 46.065988142953827,
            "start" : 8.86027,
            "duration" : 0.03479,
            "mean" : 44.067662685080094
        },
        {
            "std" : 0.54533501719632171,
            "end" : 8.916,
            "name" : "Segment",
            "min" : 42.017770503925377,
            "max" : 44.905646692762446,
            "start" : 8.89506,
            "duration" : 0.02094,
            "mean" : 43.502177401805938
        },
        {
            "std" : 0.76329217823203144,
            "end" : 9.02518,
            "name" : "Segment",
            "min" : 39.987614911508963,
            "max" : 46.063795878883219,
            "start" : 8.916,
            "duration" : 0.10918,
            "mean" : 43.804404743743532
        },
        {
            "std" : 0.81319025453211513,
            "end" : 9.06497,
            "name" : "Segment",
            "min" : 40.751329570383838,
            "max" : 45.689899324451112,
            "start" : 9.02518,
            "duration" : 0.03979,
            "mean" : 43.360429611394856
        },
        {
            "std" : 2.4207809854742197,
            "end" : 9.0781,
            "name" : "Segment",
            "min" : 42.63345021012023,
            "max" : 53.695845940178266,
            "start" : 9.06497,
            "duration" : 0.01313,
            "mean" : 48.184040195126421
        },
        {
            "std" : 1.7338792339307141,
            "end" : 9.10328,
            "name" : "Segment",
            "min" : 44.959599245252861,
            "max" : 53.457951385773953,
            "start" : 9.0781,
            "duration" : 0.02518,
            "mean" : 49.699843647194818
        },
        {
            "std" : 3.5407900729350965,
            "end" : 9.10643,
            "name" : "Segment",
            "min" : 45.409975811624456,
            "max" : 58.737403137980976,
            "start" : 9.10328,
            "duration" : 0.00315,
            "mean" : 49.221071323602821
        },
        {
            "std" : 5.1446864621304789,
            "end" : 9.10957,
            "name" : "Segment",
            "min" : 23.817183589200749,
            "max" : 45.487561195461247,
            "start" : 9.10643,
            "duration" : 0.00314,
            "mean" : 40.311306300760123
        },
        {
            "std" : 1.4778651481005336,
            "end" : 9.11176,
            "name" : "Segment",
            "min" : 19.663720986138738,
            "max" : 28.859149037992783,
            "start" : 9.10957,
            "duration" : 0.00219,
            "mean" : 24.468858039221693
        },
        {
            "std" : 0.58680465472518517,
            "end" : 9.14873,
            "name" : "Segment",
            "min" : 23.040222700126201,
            "max" : 26.438374980590972,
            "start" : 9.11176,
            "duration" : 0.03697,
            "mean" : 24.847249987712271
        },
        {
            "std" : 0.81711517323332228,
            "end" : 9.18694,
            "name" : "Segment",
            "min" : 21.106012548935791,
            "max" : 26.367623119329487,
            "start" : 9.14873,
            "duration" : 0.03821,
            "mean" : 24.637480751095964
        },
        {
            "std" : 0.56860988771845233,
            "end" : 9.22955,
            "name" : "Segment",
            "min" : 22.594792332510028,
            "max" : 26.853532374202331,
            "start" : 9.18694,
            "duration" : 0.04261,
            "mean" : 24.948978717358962
        },
        {
            "std" : 0.65449898965474407,
            "end" : 9.2593,
            "name" : "Segment",
            "min" : 22.145296594450809,
            "max" : 27.072680245383207,
            "start" : 9.22955,
            "duration" : 0.02975,
            "mean" : 25.370107171013693
        },
        {
            "std" : 0.73455799621491735,
            "end" : 9.43267,
            "name" : "Segment",
            "min" : 20.310589979607339,
            "max" : 27.238531009006199,
            "start" : 9.2593,
            "duration" : 0.17337,
            "mean" : 24.937511331332225
        },
        {
            "std" : 0.68692818350757034,
            "end" : 9.45074,
            "name" : "Segment",
            "min" : 21.424632579911567,
            "max" : 26.042307681110426,
            "start" : 9.43267,
            "duration" : 0.01807,
            "mean" : 24.427335227608459
        },
        {
            "std" : 0.72729854671091299,
            "end" : 9.51884,
            "name" : "Segment",
            "min" : 21.001563996795102,
            "max" : 27.06155296277818,
            "start" : 9.45074,
            "duration" : 0.0681,
            "mean" : 24.977221344160426
        },
        {
            "std" : 0.76302130697838266,
            "end" : 9.5815,
            "name" : "Segment",
            "min" : 19.936191862841813,
            "max" : 27.195685399207736,
            "start" : 9.51884,
            "duration" : 0.06266,
            "mean" : 24.635947351525779
        },
        {
            "std" : 0.75136977415461503,
            "end" : 9.77409,
            "name" : "Segment",
            "min" : 19.351869667600763,
            "max" : 27.154095318070617,
            "start" : 9.5815,
            "duration" : 0.19259,
            "mean" : 24.793042182038121
        },
        {
            "std" : 0.60218303116783689,
            "end" : 9.79495,
            "name" : "Segment",
            "min" : 23.234391831584606,
            "max" : 26.686021340249926,
            "start" : 9.77409,
            "duration" : 0.02086,
            "mean" : 25.219517526304259
        },
        {
            "std" : 0.800586298383407,
            "end" : 9.86153,
            "name" : "Segment",
            "min" : 20.784675124583995,
            "max" : 27.08970756047988,
            "start" : 9.79495,
            "duration" : 0.06658,
            "mean" : 24.85290123535767
        },
        {
            "std" : 0.52595802752578436,
            "end" : 9.88435,
            "name" : "Segment",
            "min" : 23.787334676920661,
            "max" : 27.045586629959836,
            "start" : 9.86153,
            "duration" : 0.02282,
            "mean" : 25.569572868282251
        },
        {
            "std" : 0.74588298315292556,
            "end" : 9.91355,
            "name" : "Segment",
            "min" : 22.446176101837356,
            "max" : 27.000795543966422,
            "start" : 9.88435,
            "duration" : 0.0292,
            "mean" : 25.117162750892021
        },
        {
            "std" : 13.437295614602851,
            "end" : 9.91455,
            "name" : "Segment",
            "min" : 24.658077566031324,
            "max" : 86.861903377671524,
            "start" : 9.91355,
            "duration" : 0.001,
            "mean" : 32.555918681349937
        }
    ],
    "filter_cutoff" : 2000,
    "filter_order" : 1,
    "start" : 284.06133,
    "duration" : 9.9145500000000002,
    "filtered" : true,
    "n" : 261,
    "mean" : 33.445665793520867
}