{
    "std" : 22.285229198503419,
    "end" : 100.39322,
    "state_parser" : {
        "name" : "SpeedyStatSplit",
        "min_gain_per_sample" : null,
        "false_positive_rate" : null,
        "max_width" : 1000000,
        "window_width" : 10000,
        "prior_segments_per_second" : 40,
        "min_width" : 100,
        "cutoff_freq" : 2000,
        "sampling_freq" : 100000.0
    },
    "name" : "Event",
    "min" : 1.0905690730448176,
    "max" : 99.212030915805784,
    "segments" : [
        {
            "std" : 16.181819430568407,
            "end" : 0.001,
            "name" : "Segment",
            "min" : 32.500245673340245,
            "max" : 99.212030915805784,
            "start" : 0.0,
            "duration" : 0.001,
            "mean" : 40.856628683474554
        },
        {
            "std" : 1.0779254896367823,
            "end" : 0.01534,
            "name" : "Segment",
            "min" : 28.396509752631342,
            "max" : 35.625694476020264,
            "start" : 0.001,
            "duration" : 0.01434,
            "mean" : 32.099287455059383
        },
        {
            "std" : 1.3944543202338873,
            "end" : 0.02321,
            "name" : "Segment",
            "min" : 34.993854125501755,
            "max" : 41.43886987112414,
            "start" : 0.01534,
            "duration" : 0.00787,
            "mean" : 38.762795816262688
        },
        {
            "std" : 9.0123427272676366,
            "end" : 0.02443,
            "name" : "Segment",
            "min" : 26.210338266386671,
            "max" : 52.683954059344352,
            "start" : 0.02321,
            "duration" : 0.00122,
            "mean" : 42.993862876826476
        },
        {
            "std" : 0.72136790261411821,
            "end" : 0.16585,
            "name" : "Segment",
            "min" : 20.343200450117038,
            "max" : 26.246679092759198,
            "start" : 0.02443,
            "duration" : 0.14142,
            "mean" : 24.317895609074981
        },
        {
            "std" : 0.84263837961981969,
            "end" : 0.19627,
            "name" : "Segment",
            "min" : 21.34342243824263,
            "max" : 27.266449272830922,
            "start" : 0.16585,
            "duration" : 0.03042,
            "mean" : 25.150899493730236
        },
        {
            "std" : 0.43533507219481576,
            "end" : 0.20885,
            "name" : "Segment",
            "min" : 22.617332434787944,
            "max" : 25.123553796722668,
            "start" : 0.19627,
            "duration" : 0.01258,
            "mean" : 24.166861802593459
        },
        {
            "std" : 0.78429775268739865,
            "end" : 0.21682,
            "name" : "Segment",
            "min" : 21.999853783538676,
            "max" : 27.060234284248565,
            "start" : 0.20885,
            "duration" : 0.00797,
            "mean" : 24.885688649857162
        },
        {
            "std" : 0.76188228560976001,
            "end" : 0.23214,
            "name" : "Segment",
            "min" : 23.297971377460193,
            "max" : 28.26507798665267,
            "start" : 0.21682,
            "duration" : 0.01532,
            "mean" : 25.557056844211534
        },
        {
            "std" : 0.77553349078739264,
            "end" : 0.24912,
            "name" : "Segment",
            "min" : 21.836439594231781,
            "max" : 27.357595304784535,
            "start" : 0.23214,
            "duration" : 0.01698,
            "mean" : 24.541112991918819
        },
        {
            "std" : 1.6567635087894044,
            "end" : 0.28479,
            "name" : "Segment",
            "min" : 26.369333793170409,
            "max" : 35.610730359315212,
            "start" : 0.24912,
            "duration" : 0.03567,
            "mean" : 31.65276236522844
        },
        {
            "std" : 1.7764698072777598,
            "end" : 0.34432,
            "name" : "Segment",
            "min" : 27.294081371657185,
            "max" : 37.50229314652109,
            "start" : 0.28479,
            "duration" : 0.05953,
            "mean" : 32.518358887271404
        },
        {
            "std" : 1.2641555520204393,
            "end" : 0.35288,
            "name" : "Segment",
            "min" : 30.703401709693416,
            "max" : 37.278860376480146,
            "start" : 0.34432,
            "duration" : 0.00856,
            "mean" : 33.884459500632595
        },
        {
            "std" : 1.1693047655673936,
            "end" : 0.36039,
            "name" : "Segment",
            "min" : 32.267482154774733,
            "max" : 37.893687444820017,
            "start" : 0.35288,
            "duration" : 0.00751,
            "mean" : 35.496488077998954
        },
        {
            "std" : 1.4836872627048294,
            "end" : 0.36362,
            "name" : "Segment",
            "min" : 30.306054116500089,
            "max" : 39.784077884709255,
            "start" : 0.36039,
            "duration" : 0.00323,
            "mean" : 32.342374534774791
        },
        {
            "std" : 0.96135756981876519,
            "end" : 0.57147,
            "name" : "Segment",
            "min" : 38.460443475856579,
            "max" : 46.193952583489633,
            "start" : 0.36362,
            "duration" : 0.20785,
            "mean" : 43.024649090128896
        },
        {
            "std" : 0.72251081743610446,
            "end" : 0.58952,
            "name" : "Segment",
            "min" : 40.82505600501073,
            "max" : 45.014331996790482,
            "start" : 0.57147,
            "duration" : 0.01805,
            "mean" : 43.387586356090694
        },
        {
            "std" : 1.6602983353909098,
            "end" : 0.73701,
            "name" : "Segment",
            "min" : 30.052162286440524,
            "max" : 45.929453498710274,
            "start" : 0.58952,
            "duration" : 0.14749,
            "mean" : 38.293326077754067
        },
        {
            "std" : 0.70061443270616508,
            "end" : 0.7396,
            "name" : "Segment",
            "min" : 37.835808877247388,
            "max" : 41.141326112585695,
            "start" : 0.73701,
            "duration" : 0.00259,
            "mean" : 39.697931415632723
        },
        {
            "std" : 1.5963696921030679,
            "end" : 0.79197,
            "name" : "Segment",
            "min" : 29.152636800795523,
            "max" : 42.038759006900293,
            "start" : 0.7396,
            "duration" : 0.05237,
            "mean" : 38.267451244084484
        },
        {
            "std" : 2.3258360732050902,
            "end" : 0.79522,
            "name" : "Segment",
            "min" : 26.583376581194425,
            "max" : 38.537028185445301,
            "start" : 0.79197,
            "duration" : 0.00325,
            "mean" : 34.762570851126895
        },
        {
            "std" : 1.1959684929773293,
            "end" : 0.91217,
            "name" : "Segment",
            "min" : 11.322957161598193,
            "max" : 25.695148985513992,
            "start" : 0.79522,
            "duration" : 0.11695,
            "mean" : 19.032606204727387
        },
        {
            "std" : 0.93603246673793949,
            "end" : 1.0133,
            "name" : "Segment",
            "min" : 14.311267874836949,
            "max" : 21.087435678545237,
            "start" : 0.91217,
            "duration" : 0.10113,
            "mean" : 17.985871183988664
        },
        {
            "std" : 1.5970134339242943,
            "end" : 1.1072,
            "name" : "Segment",
            "min" : 14.212941094046753,
            "max" : 26.357909996643617,
            "start" : 1.0133,
            "duration" : 0.0939,
            "mean" : 18.704382293848163
        },
        {
            "std" : 1.0181578174011516,
            "end" : 1.15011,
            "name" : "Segment",
            "min" : 13.472464924239006,
            "max" : 21.405960081112891,
            "start" : 1.1072,
            "duration" : 0.04291,
            "mean" : 17.706522299901813
        },
        {
            "std" : 1.2185760472329639,
            "end" : 1.16056,
            "name" : "Segment",
            "min" : 15.791331492444804,
            "max" : 22.170516415726841,
            "start" : 1.15011,
            "duration" : 0.01045,
            "mean" : 19.006753850196635
        },
        {
            "std" : 2.9762045555528309,
            "end" : 1.16746,
            "name" : "Segment",
            "min" : 15.729195617915353,
            "max" : 34.038718870036732,
            "start" : 1.16056,
            "duration" : 0.0069,
            "mean" : 20.703416462519677
        },
        {
            "std" : 1.3646868715107718,
            "end" : 1.17093,
            "name" : "Segment",
            "min" : 34.465152521966168,
            "max" : 41.719782450507942,
            "start" : 1.16746,
            "duration" : 0.00347,
            "mean" : 39.640788126561084
        },
        {
            "std" : 1.316852582903242,
            "end" : 1.19632,
            "name" : "Segment",
            "min" : 38.060147436969444,
            "max" : 46.999243976769534,
            "start" : 1.17093,
            "duration" : 0.02539,
            "mean" : 41.446659864347389
        },
        {
            "std" : 0.91966415735420792,
            "end" : 1.29553,
            "name" : "Segment",
            "min" : 40.658764380390927,
            "max" : 47.48517575654445,
            "start" : 1.19632,
            "duration" : 0.09921,
            "mean" : 44.926448731760722
        },
        {
            "std" : 0.87514340528237167,
            "end" : 1.34412,
            "name" : "Segment",
            "min" : 39.692769350823106,
            "max" : 46.312737046548769,
            "start" : 1.29553,
            "duration" : 0.04859,
            "mean" : 44.005451413619234
        },
        {
            "std" : 0.66133446717004407,
            "end" : 1.41615,
            "name" : "Segment",
            "min" : 36.164541317640335,
            "max" : 41.344161565159283,
            "start" : 1.34412,
            "duration" : 0.07203,
            "mean" : 39.627037577670187
        },
        {
            "std" : 0.61384725570696352,
            "end" : 1.44753,
            "name" : "Segment",
            "min" : 35.170398140406256,
            "max" : 40.615229453517109,
            "start" : 1.41615,
            "duration" : 0.03138,
            "mean" : 39.035191528676243
        },
        {
            "std" : 0.56179932923725406,
            "end" : 1.47861,
            "name" : "Segment",
            "min" : 34.900611701584161,
            "max" : 38.432348818632207,
            "start" : 1.44753,
            "duration" : 0.03108,
            "mean" : 36.975198981167402
        },
        {
            "std" : 0.55627556047950899,
            "end" : 1.49769,
            "name" : "Segment",
            "min" : 34.281615244941328,
            "max" : 37.658512350388953,
            "start" : 1.47861,
            "duration" : 0.01908,
            "mean" : 36.232344722211856
        },
        {
            "std" : 0.99462511400662568,
            "end" : 1.50683,
            "name" : "Segment",
            "min" : 31.729994760536275,
            "max" : 36.753946382744104,
            "start" : 1.49769,
            "duration" : 0.00914,
            "mean" : 34.363946227106062
        },
        {
            "std" : 1.0132848437322026,
            "end" : 1.52805,
            "name" : "Segment",
            "min" : 29.417820334521601,
            "max" : 39.099358637611829,
            "start" : 1.50683,
            "duration" : 0.02122,
            "mean" : 33.345100242002324
        },
        {
            "std" : 1.2494910592273982,
            "end" : 1.59975,
            "name" : "Segment",
            "min" : 38.548851511164969,
            "max" : 46.71817032742905,
            "start" : 1.52805,
            "duration" : 0.0717,
            "mean" : 42.359684603398826
        },
        {
            "std" : 0.78124082517475635,
            "end" : 1.62178,
            "name" : "Segment",
            "min" : 41.381185345170756,
            "max" : 46.585995996422085,
            "start" : 1.59975,
            "duration" : 0.02203,
            "mean" : 43.99825796795912
        },
        {
            "std" : 0.98033250534924687,
            "end" : 1.68618,
            "name" : "Segment",
            "min" : 36.458337261707264,
            "max" : 45.539193691981964,
            "start" : 1.62178,
            "duration" : 0.0644,
            "mean" : 42.648907821252912
        },
        {
            "std" : 1.0181346650468091,
            "end" : 1.72219,
            "name" : "Segment",
            "min" : 30.861773638177727,
            "max" : 39.136269679841156,
            "start" : 1.68618,
            "duration" : 0.03601,
            "mean" : 36.005882233960129
        },
        {
            "std" : 0.92204114202379961,
            "end" : 1.76008,
            "name" : "Segment",
            "min" : 30.02301409165954,
            "max" : 39.195444228323488,
            "start" : 1.72219,
            "duration" : 0.03789,
            "mean" : 35.282476367799212
        },
        {
            "std" : 1.1425330523283503,
            "end" : 1.77919,
            "name" : "Segment",
            "min" : 39.250135782808023,
            "max" : 45.756260298213391,
            "start" : 1.76008,
            "duration" : 0.01911,
            "mean" : 43.186381624127918
        },
        {
            "std" : 1.0792871944007636,
            "end" : 1.79171,
            "name" : "Segment",
            "min" : 39.29227432264058,
            "max" : 44.792050862771561,
            "start" : 1.77919,
            "duration" : 0.01252,
            "mean" : 42.19357230563584
        },
        {
            "std" : 1.261952577536795,
            "end" : 1.80501,
            "name" : "Segment",
            "min" : 36.179145344775975,
            "max" : 44.686237184088831,
            "start" : 1.79171,
            "duration" : 0.0133,
            "mean" : 39.829342520756917
        },
        {
            "std" : 1.6406753493104493,
            "end" : 1.82424,
            "name" : "Segment",
            "min" : 31.012034070974792,
            "max" : 41.588343849084104,
            "start" : 1.80501,
            "duration" : 0.01923,
            "mean" : 38.821843104882802
        },
        {
            "std" : 1.8708705226529692,
            "end" : 1.84108,
            "name" : "Segment",
            "min" : 28.706959310963111,
            "max" : 42.265085318648083,
            "start" : 1.82424,
            "duration" : 0.01684,
            "mean" : 37.153917756596094
        },
        {
            "std" : 1.2990608913869781,
            "end" : 1.8445,
            "name" : "Segment",
            "min" : 20.365483964093791,
            "max" : 28.475060716162556,
            "start" : 1.84108,
            "duration" : 0.00342,
            "mean" : 25.324239081890052
        },
        {
            "std" : 0.62822492125917739,
            "end" : 1.8636,
            "name" : "Segment",
            "min" : 22.067405523773363,
            "max" : 26.884857673723936,
            "start" : 1.8445,
            "duration" : 0.0191,
            "mean" : 24.798014324557567
        },
        {
            "std" : 1.6702693060225595,
            "end" : 1.86812,
            "name" : "Segment",
            "min" : 18.692610753116117,
            "max" : 25.732989969204848,
            "start" : 1.8636,
            "duration" : 0.00452,
            "mean" : 23.61614245410011
        },
        {
            "std" : 0.85574675892262209,
            "end" : 1.88828,
            "name" : "Segment",
            "min" : 19.508110674452521,
            "max" : 26.147723633545343,
            "start" : 1.86812,
            "duration" : 0.02016,
            "mean" : 24.42453813405508
        },
        {
            "std" : 0.90143781410040913,
            "end" : 1.9125,
            "name" : "Segment",
            "min" : 19.90966874122676,
            "max" : 25.392280914047245,
            "start" : 1.88828,
            "duration" : 0.02422,
            "mean" : 22.854083512535539
        },
        {
            "std" : 1.0680023567540056,
            "end" : 2.02831,
            "name" : "Segment",
            "min" : 19.842193930216006,
            "max" : 28.007410179991922,
            "start" : 1.9125,
            "duration" : 0.11581,
            "mean" : 25.580298285472786
        },
        {
            "std" : 1.3018105503728479,
            "end" : 2.03463,
            "name" : "Segment",
            "min" : 24.141160890585383,
            "max" : 29.834223900179008,
            "start" : 2.02831,
            "duration" : 0.00632,
            "mean" : 27.052751644034824
        },
        {
            "std" : 0.66078088065296359,
            "end" : 2.05983,
            "name" : "Segment",
            "min" : 22.923499408927899,
            "max" : 27.563478352879102,
            "start" : 2.03463,
            "duration" : 0.0252,
            "mean" : 25.192511526989556
        },
        {
            "std" : 1.0782922810805207,
            "end" : 2.07178,
            "name" : "Segment",
            "min" : 22.842600212505932,
            "max" : 29.083910424190112,
            "start" : 2.05983,
            "duration" : 0.01195,
            "mean" : 25.652315974694936
        },
        {
            "std" : 1.8840621239751072,
            "end" : 2.08532,
            "name" : "Segment",
            "min" : 27.632835293576399,
            "max" : 38.398313884459519,
            "start" : 2.07178,
            "duration" : 0.01354,
            "mean" : 34.296056083594422
        },
        {
            "std" : 1.53969071017792,
            "end" : 2.10323,
            "name" : "Segment",
            "min" : 28.546756133827571,
            "max" : 37.435487743926657,
            "start" : 2.08532,
            "duration" : 0.01791,
            "mean" : 31.397668532202111
        },
        {
            "std" : 2.3768794358655581,
            "end" : 2.10765,
            "name" : "Segment",
            "min" : 29.823550228135478,
            "max" : 42.143604779147594,
            "start" : 2.10323,
            "duration" : 0.00442,
            "mean" : 32.880895271570004
        },
        {
            "std" : 1.6740379570307153,
            "end" : 2.10931,
            "name" : "Segment",
            "min" : 41.543546218718888,
            "max" : 48.035489005452128,
            "start" : 2.10765,
            "duration" : 0.00166,
            "mean" : 45.631913045983815
        },
        {
            "std" : 1.3919498041394309,
            "end" : 2.13349,
            "name" : "Segment",
            "min" : 44.812371825883403,
            "max" : 52.069111131882238,
            "start" : 2.10931,
            "duration" : 0.02418,
            "mean" : 48.501276368174288
        },
        {
            "std" : 1.2167537760311777,
            "end" : 2.15626,
            "name" : "Segment",
            "min" : 41.67401479709094,
            "max" : 49.342827129469264,
            "start" : 2.13349,
            "duration" : 0.02277,
            "mean" : 46.127659398832705
        },
        {
            "std" : 0.92172874210269973,
            "end" : 2.21166,
            "name" : "Segment",
            "min" : 44.986532025584452,
            "max" : 52.680616069876343,
            "start" : 2.15626,
            "duration" : 0.0554,
            "mean" : 49.960818260732474
        },
        {
            "std" : 0.49968328727528605,
            "end" : 2.21786,
            "name" : "Segment",
            "min" : 48.684298398061756,
            "max" : 50.95136546848542,
            "start" : 2.21166,
            "duration" : 0.0062,
            "mean" : 50.164366500838199
        },
        {
            "std" : 1.3184173394469225,
            "end" : 2.22183,
            "name" : "Segment",
            "min" : 43.778551384352035,
            "max" : 49.291579861188872,
            "start" : 2.21786,
            "duration" : 0.00397,
            "mean" : 46.786219530967571
        },
        {
            "std" : 0.92987109687687497,
            "end" : 2.26559,
            "name" : "Segment",
            "min" : 45.622810239685059,
            "max" : 52.551687671954561,
            "start" : 2.22183,
            "duration" : 0.04376,
            "mean" : 50.035238464209783
        },
        {
            "std" : 1.0632212117751769,
            "end" : 2.30302,
            "name" : "Segment",
            "min" : 42.078002562680908,
            "max" : 51.624831903189175,
            "start" : 2.26559,
            "duration" : 0.03743,
            "mean" : 49.477289845707254
        },
        {
            "std" : 0.75815043493774525,
            "end" : 2.32093,
            "name" : "Segment",
            "min" : 47.402485677028565,
            "max" : 51.959196318721226,
            "start" : 2.30302,
            "duration" : 0.01791,
            "mean" : 50.266100782492572
        },
        {
            "std" : 1.8139871023460816,
            "end" : 2.3229,
            "name" : "Segment",
            "min" : 43.017078581818055,
            "max" : 51.591969202004812,
            "start" : 2.32093,
            "duration" : 0.00197,
            "mean" : 49.338306017079532
        },
        {
            "std" : 1.1398164695564335,
            "end" : 2.32549,
            "name" : "Segment",
            "min" : 43.518646817619157,
            "max" : 48.005512005383011,
            "start" : 2.3229,
            "duration" : 0.00259,
            "mean" : 45.632681111310113
        },
        {
            "std" : 0.91121374042246894,
            "end" : 2.35735,
            "name" : "Segment",
            "min" : 45.020879423455064,
            "max" : 52.179936686362701,
            "start" : 2.32549,
            "duration" : 0.03186,
            "mean" : 49.772643113904699
        },
        {
            "std" : 0.9243054521085684,
            "end" : 2.36885,
            "name" : "Segment",
            "min" : 44.447319266518775,
            "max" : 50.589234879567712,
            "start" : 2.35735,
            "duration" : 0.0115,
            "mean" : 48.566037964475427
        },
        {
            "std" : 0.86883266211939458,
            "end" : 2.38397,
            "name" : "Segment",
            "min" : 42.11085688772161,
            "max" : 46.78503193408573,
            "start" : 2.36885,
            "duration" : 0.01512,
            "mean" : 45.039636336034839
        },
        {
            "std" : 0.87836775832979896,
            "end" : 2.42295,
            "name" : "Segment",
            "min" : 44.478106170478149,
            "max" : 50.966940576726579,
            "start" : 2.38397,
            "duration" : 0.03898,
            "mean" : 48.942140307022356
        },
        {
            "std" : 0.73958279256940851,
            "end" : 2.47171,
            "name" : "Segment",
            "min" : 42.700514920320465,
            "max" : 47.31075023931777,
            "start" : 2.42295,
            "duration" : 0.04876,
            "mean" : 45.315826340913581
        },
        {
            "std" : 0.98956214536839626,
            "end" : 2.47271,
            "name" : "Segment",
            "min" : 41.481560299941108,
            "max" : 45.137191899579172,
            "start" : 2.47171,
            "duration" : 0.001,
            "mean" : 43.332590494368112
        },
        {
            "std" : 0.8530750606492673,
            "end" : 2.55383,
            "name" : "Segment",
            "min" : 41.393413330304959,
            "max" : 47.496901619703564,
            "start" : 2.47271,
            "duration" : 0.08112,
            "mean" : 45.091366581681847
        },
        {
            "std" : 0.91422521862981643,
            "end" : 2.62529,
            "name" : "Segment",
            "min" : 38.171533246415628,
            "max" : 45.753740923876755,
            "start" : 2.55383,
            "duration" : 0.07146,
            "mean" : 43.432963723162743
        },
        {
            "std" : 0.60724530558972678,
            "end" : 2.64625,
            "name" : "Segment",
            "min" : 39.983929852395661,
            "max" : 44.093657418629569,
            "start" : 2.62529,
            "duration" : 0.02096,
            "mean" : 42.572576760179494
        },
        {
            "std" : 0.85868934321727119,
            "end" : 2.67688,
            "name" : "Segment",
            "min" : 39.17337237239046,
            "max" : 45.837672247207465,
            "start" : 2.64625,
            "duration" : 0.03063,
            "mean" : 43.14510752247844
        },
        {
            "std" : 0.7604424318619194,
            "end" : 2.72212,
            "name" : "Segment",
            "min" : 39.128187964092142,
            "max" : 44.80544868075657,
            "start" : 2.67688,
            "duration" : 0.04524,
            "mean" : 42.431928554618153
        },
        {
            "std" : 0.6859422551233687,
            "end" : 2.82882,
            "name" : "Segment",
            "min" : 39.655359914533747,
            "max" : 45.160612500382776,
            "start" : 2.72212,
            "duration" : 0.1067,
            "mean" : 42.931828895642774
        },
        {
            "std" : 0.65604135434525879,
            "end" : 2.85006,
            "name" : "Segment",
            "min" : 39.047798781690936,
            "max" : 43.932743093962699,
            "start" : 2.82882,
            "duration" : 0.02124,
            "mean" : 42.074423340383269
        },
        {
            "std" : 0.84294108079235675,
            "end" : 2.91554,
            "name" : "Segment",
            "min" : 39.584733809543948,
            "max" : 45.284406300569096,
            "start" : 2.85006,
            "duration" : 0.06548,
            "mean" : 42.675942991069903
        },
        {
            "std" : 0.61594743062236179,
            "end" : 2.92834,
            "name" : "Segment",
            "min" : 40.322147722032945,
            "max" : 44.425186511154926,
            "start" : 2.91554,
            "duration" : 0.0128,
            "mean" : 41.760824894389842
        },
        {
            "std" : 1.8511533450893174,
            "end" : 2.94716,
            "name" : "Segment",
            "min" : 42.506478583232067,
            "max" : 55.917923366859199,
            "start" : 2.92834,
            "duration" : 0.01882,
            "mean" : 48.151096256224228
        },
        {
            "std" : 1.81564016895736,
            "end" : 2.97079,
            "name" : "Segment",
            "min" : 44.671344096214845,
            "max" : 56.789388983578924,
            "start" : 2.94716,
            "duration" : 0.02363,
            "mean" : 50.421554787410777
        },
        {
            "std" : 1.8188103872039609,
            "end" : 2.97906,
            "name" : "Segment",
            "min" : 45.279256993383257,
            "max" : 54.985359950052171,
            "start" : 2.97079,
            "duration" : 0.00827,
            "mean" : 48.703693739786374
        },
        {
            "std" : 3.1428766282071097,
            "end" : 2.98372,
            "name" : "Segment",
            "min" : 44.890005096713892,
            "max" : 56.691337646807234,
            "start" : 2.97906,
            "duration" : 0.00466,
            "mean" : 49.940408915619393
        },
        {
            "std" : 1.6674388575684456,
            "end" : 2.9911,
            "name" : "Segment",
            "min" : 42.509752231675556,
            "max" : 50.906736005811517,
            "start" : 2.98372,
            "duration" : 0.00738,
            "mean" : 46.576934320679548
        },
        {
            "std" : 3.204737473868037,
            "end" : 2.99558,
            "name" : "Segment",
            "min" : 46.13563831860646,
            "max" : 62.238476201834565,
            "start" : 2.9911,
            "duration" : 0.00448,
            "mean" : 52.934893253125601
        },
        {
            "std" : 2.5677327844920077,
            "end" : 3.00548,
            "name" : "Segment",
            "min" : 45.070189282094958,
            "max" : 56.752156651681851,
            "start" : 2.99558,
            "duration" : 0.0099,
            "mean" : 49.711180188319219
        },
        {
            "std" : 1.092577436698728,
            "end" : 3.00842,
            "name" : "Segment",
            "min" : 44.896031456911345,
            "max" : 50.764139706609939,
            "start" : 3.00548,
            "duration" : 0.00294,
            "mean" : 47.229709940183561
        },
        {
            "std" : 3.5438529383214288,
            "end" : 3.01265,
            "name" : "Segment",
            "min" : 38.331806100574894,
            "max" : 49.811065390611788,
            "start" : 3.00842,
            "duration" : 0.00423,
            "mean" : 42.910731186034823
        },
        {
            "std" : 2.5349271475414143,
            "end" : 3.015,
            "name" : "Segment",
            "min" : 47.045216447672111,
            "max" : 56.024632902587037,
            "start" : 3.01265,
            "duration" : 0.00235,
            "mean" : 50.935971415248964
        },
        {
            "std" : 2.5394638391753319,
            "end" : 3.03667,
            "name" : "Segment",
            "min" : 40.94495015609801,
            "max" : 59.389164648992278,
            "start" : 3.015,
            "duration" : 0.02167,
            "mean" : 48.660845975000186
        },
        {
            "std" : 0.33352417368625042,
            "end" : 3.03778,
            "name" : "Segment",
            "min" : 42.209565202956298,
            "max" : 43.474276443276494,
            "start" : 3.03667,
            "duration" : 0.00111,
            "mean" : 43.04075582620807
        },
        {
            "std" : 4.8764342194741115,
            "end" : 3.04,
            "name" : "Segment",
            "min" : 23.562724321087178,
            "max" : 42.090280652690574,
            "start" : 3.03778,
            "duration" : 0.00222,
            "mean" : 34.455466964370125
        },
        {
            "std" : 1.5834748811510537,
            "end" : 3.04504,
            "name" : "Segment",
            "min" : 34.94212760732804,
            "max" : 42.40554701613091,
            "start" : 3.04,
            "duration" : 0.00504,
            "mean" : 38.803222706348208
        },
        {
            "std" : 1.1332186428830642,
            "end" : 3.06741,
            "name" : "Segment",
            "min" : 32.677606642738951,
            "max" : 40.249168255932624,
            "start" : 3.04504,
            "duration" : 0.02237,
            "mean" : 35.614501551291788
        },
        {
            "std" : 1.2223460867961338,
            "end" : 3.13423,
            "name" : "Segment",
            "min" : 36.180986890156717,
            "max" : 46.311174934419384,
            "start" : 3.06741,
            "duration" : 0.06682,
            "mean" : 42.911679424833828
        },
        {
            "std" : 4.494062450006135,
            "end" : 3.13523,
            "name" : "Segment",
            "min" : 22.330408380592726,
            "max" : 44.066633880477625,
            "start" : 3.13423,
            "duration" : 0.001,
            "mean" : 41.01444246296974
        },
        {
            "std" : 3.0682270537732994,
            "end" : 3.13623,
            "name" : "Segment",
            "min" : 5.3819905485339783,
            "max" : 20.798070821873633,
            "start" : 3.13523,
            "duration" : 0.001,
            "mean" : 7.3425029213153179
        },
        {
            "std" : 0.72475771711577852,
            "end" : 3.17195,
            "name" : "Segment",
            "min" : 4.9559765461080225,
            "max" : 9.1053260337443458,
            "start" : 3.13623,
            "duration" : 0.03572,
            "mean" : 6.8187770686332234
        },
        {
            "std" : 0.63578866066727835,
            "end" : 3.18891,
            "name" : "Segment",
            "min" : 5.5090716959665293,
            "max" : 9.0491287527692084,
            "start" : 3.17195,
            "duration" : 0.01696,
            "mean" : 7.2694949423318196
        },
        {
            "std" : 0.50732451444686166,
            "end" : 3.23442,
            "name" : "Segment",
            "min" : 7.1759118678468576,
            "max" : 10.580326745278683,
            "start" : 3.18891,
            "duration" : 0.04551,
            "mean" : 8.6859917847755082
        },
        {
            "std" : 0.895186960669073,
            "end" : 3.25365,
            "name" : "Segment",
            "min" : 5.6136661032535544,
            "max" : 16.246059392493702,
            "start" : 3.23442,
            "duration" : 0.01923,
            "mean" : 7.2147743074141468
        },
        {
            "std" : 5.1231676126710326,
            "end" : 3.25516,
            "name" : "Segment",
            "min" : 17.404261380691199,
            "max" : 44.207926420547139,
            "start" : 3.25365,
            "duration" : 0.00151,
            "mean" : 41.474229757750045
        },
        {
            "std" : 1.8886030777875848,
            "end" : 3.27341,
            "name" : "Segment",
            "min" : 32.11329902043574,
            "max" : 44.047620126359242,
            "start" : 3.25516,
            "duration" : 0.01825,
            "mean" : 39.477899819033382
        },
        {
            "std" : 1.8622973452253868,
            "end" : 3.29069,
            "name" : "Segment",
            "min" : 29.148397869414776,
            "max" : 40.396336219521487,
            "start" : 3.27341,
            "duration" : 0.01728,
            "mean" : 37.316835646758065
        },
        {
            "std" : 0.89412263666777458,
            "end" : 3.33016,
            "name" : "Segment",
            "min" : 21.087210026189069,
            "max" : 28.85165823729076,
            "start" : 3.29069,
            "duration" : 0.03947,
            "mean" : 25.532077715527066
        },
        {
            "std" : 0.7179140771921082,
            "end" : 3.35557,
            "name" : "Segment",
            "min" : 21.873938974690549,
            "max" : 26.704943848400994,
            "start" : 3.33016,
            "duration" : 0.02541,
            "mean" : 24.54665853107397
        },
        {
            "std" : 0.82251200832075644,
            "end" : 3.38666,
            "name" : "Segment",
            "min" : 20.346903432832033,
            "max" : 25.426402157271159,
            "start" : 3.35557,
            "duration" : 0.03109,
            "mean" : 23.200202951475923
        },
        {
            "std" : 0.66991826808002908,
            "end" : 3.39717,
            "name" : "Segment",
            "min" : 19.989851907413168,
            "max" : 24.091356983825239,
            "start" : 3.38666,
            "duration" : 0.01051,
            "mean" : 22.3352373299535
        },
        {
            "std" : 1.1130676794694867,
            "end" : 3.42143,
            "name" : "Segment",
            "min" : 22.742309784651024,
            "max" : 27.881980137307071,
            "start" : 3.39717,
            "duration" : 0.02426,
            "mean" : 25.734959603820705
        },
        {
            "std" : 0.61412413948971267,
            "end" : 3.42826,
            "name" : "Segment",
            "min" : 22.609346502144305,
            "max" : 25.705232365297501,
            "start" : 3.42143,
            "duration" : 0.00683,
            "mean" : 24.661530092179664
        },
        {
            "std" : 1.1549794360683099,
            "end" : 3.5,
            "name" : "Segment",
            "min" : 20.150321164535644,
            "max" : 29.47679983835517,
            "start" : 3.42826,
            "duration" : 0.07174,
            "mean" : 25.244884169029422
        },
        {
            "std" : 0.81761790247095745,
            "end" : 3.50172,
            "name" : "Segment",
            "min" : 26.13028874803992,
            "max" : 29.423677180744843,
            "start" : 3.5,
            "duration" : 0.00172,
            "mean" : 27.754494462826585
        },
        {
            "std" : 1.9310299934799251,
            "end" : 3.52909,
            "name" : "Segment",
            "min" : 28.894514142740253,
            "max" : 41.37373443238122,
            "start" : 3.50172,
            "duration" : 0.02737,
            "mean" : 34.000244454551947
        },
        {
            "std" : 1.3532675917144217,
            "end" : 3.54615,
            "name" : "Segment",
            "min" : 42.011348258005391,
            "max" : 51.630617067584453,
            "start" : 3.52909,
            "duration" : 0.01706,
            "mean" : 48.240227584735273
        },
        {
            "std" : 1.564655123193605,
            "end" : 3.56148,
            "name" : "Segment",
            "min" : 42.017509529112886,
            "max" : 50.484535730454567,
            "start" : 3.54615,
            "duration" : 0.01533,
            "mean" : 46.059470933940666
        },
        {
            "std" : 0.79784973215811716,
            "end" : 3.57162,
            "name" : "Segment",
            "min" : 47.930987627990532,
            "max" : 52.305135512516507,
            "start" : 3.56148,
            "duration" : 0.01014,
            "mean" : 49.95291382697863
        },
        {
            "std" : 0.87047552565077924,
            "end" : 3.64549,
            "name" : "Segment",
            "min" : 43.656028384467952,
            "max" : 51.206251173357657,
            "start" : 3.57162,
            "duration" : 0.07387,
            "mean" : 48.776698621030135
        },
        {
            "std" : 0.81068154515550572,
            "end" : 3.74223,
            "name" : "Segment",
            "min" : 40.240282572967331,
            "max" : 51.926397876073636,
            "start" : 3.64549,
            "duration" : 0.09674,
            "mean" : 45.284404988305241
        },
        {
            "std" : 0.96614616687247246,
            "end" : 3.75033,
            "name" : "Segment",
            "min" : 41.250210979618444,
            "max" : 46.159193466377687,
            "start" : 3.74223,
            "duration" : 0.0081,
            "mean" : 44.520282785762895
        },
        {
            "std" : 0.58870722373536721,
            "end" : 3.7757,
            "name" : "Segment",
            "min" : 43.304578959901129,
            "max" : 46.522171920182544,
            "start" : 3.75033,
            "duration" : 0.02537,
            "mean" : 45.035137333408706
        },
        {
            "std" : 1.0487761510703535,
            "end" : 3.77875,
            "name" : "Segment",
            "min" : 38.944102054848166,
            "max" : 44.859915968263429,
            "start" : 3.7757,
            "duration" : 0.00305,
            "mean" : 43.170048213384355
        },
        {
            "std" : 0.66555322522638516,
            "end" : 3.78746,
            "name" : "Segment",
            "min" : 41.315038534171023,
            "max" : 45.861170055385593,
            "start" : 3.77875,
            "duration" : 0.00871,
            "mean" : 44.193340396828866
        },
        {
            "std" : 0.75371253188957354,
            "end" : 3.85083,
            "name" : "Segment",
            "min" : 38.779272665871908,
            "max" : 45.322678315456912,
            "start" : 3.78746,
            "duration" : 0.06337,
            "mean" : 43.40817273043703
        },
        {
            "std" : 0.68090911204096827,
            "end" : 3.87419,
            "name" : "Segment",
            "min" : 38.631908554146293,
            "max" : 43.910823861380834,
            "start" : 3.85083,
            "duration" : 0.02336,
            "mean" : 42.323122459875847
        },
        {
            "std" : 0.7017465669579197,
            "end" : 3.97993,
            "name" : "Segment",
            "min" : 37.186801982769836,
            "max" : 45.039509682885885,
            "start" : 3.87419,
            "duration" : 0.10574,
            "mean" : 42.66669413572253
        },
        {
            "std" : 0.85812092101385962,
            "end" : 4.00169,
            "name" : "Segment",
            "min" : 39.28571342573801,
            "max" : 45.250871770417703,
            "start" : 3.97993,
            "duration" : 0.02176,
            "mean" : 43.157068715785719
        },
        {
            "std" : 0.78208368780244031,
            "end" : 4.03537,
            "name" : "Segment",
            "min" : 38.274161522823498,
            "max" : 44.531094772417738,
            "start" : 4.00169,
            "duration" : 0.03368,
            "mean" : 42.394032369668238
        },
        {
            "std" : 0.76043754461888857,
            "end" : 4.05114,
            "name" : "Segment",
            "min" : 38.571765177654221,
            "max" : 44.673003866765654,
            "start" : 4.03537,
            "duration" : 0.01577,
            "mean" : 42.894232524714255
        },
        {
            "std" : 0.53226676149744723,
            "end" : 4.06713,
            "name" : "Segment",
            "min" : 40.844514250571208,
            "max" : 44.018154107942244,
            "start" : 4.05114,
            "duration" : 0.01599,
            "mean" : 42.154787152041223
        },
        {
            "std" : 0.76693581566807023,
            "end" : 4.15312,
            "name" : "Segment",
            "min" : 39.140921159454017,
            "max" : 48.135672283960226,
            "start" : 4.06713,
            "duration" : 0.08599,
            "mean" : 42.366828777151817
        },
        {
            "std" : 0.87486524132017673,
            "end" : 4.38818,
            "name" : "Segment",
            "min" : 37.95261895325114,
            "max" : 45.269476671130754,
            "start" : 4.15312,
            "duration" : 0.23506,
            "mean" : 42.567432274685643
        },
        {
            "std" : 0.73763615580122333,
            "end" : 4.3974,
            "name" : "Segment",
            "min" : 38.744960652663138,
            "max" : 44.62419169949024,
            "start" : 4.38818,
            "duration" : 0.00922,
            "mean" : 41.573066144178732
        },
        {
            "std" : 1.9582511999783743,
            "end" : 4.46077,
            "name" : "Segment",
            "min" : 41.670604003113588,
            "max" : 53.992007305907762,
            "start" : 4.3974,
            "duration" : 0.06337,
            "mean" : 48.131279576093647
        },
        {
            "std" : 2.9575480475663021,
            "end" : 4.4867,
            "name" : "Segment",
            "min" : 43.782725370315283,
            "max" : 63.47853410075836,
            "start" : 4.46077,
            "duration" : 0.02593,
            "mean" : 49.798565707627468
        },
        {
            "std" : 1.4306441401711845,
            "end" : 4.50592,
            "name" : "Segment",
            "min" : 64.362428899235312,
            "max" : 76.143822385078849,
            "start" : 4.4867,
            "duration" : 0.01922,
            "mean" : 73.28597476825891
        },
        {
            "std" : 1.828647073198445,
            "end" : 4.52957,
            "name" : "Segment",
            "min" : 67.488705624092944,
            "max" : 76.293915306710204,
            "start" : 4.50592,
            "duration" : 0.02365,
            "mean" : 71.417984510327258
        },
        {
            "std" : 1.3247526324153556,
            "end" : 4.57541,
            "name" : "Segment",
            "min" : 73.582322948365686,
            "max" : 82.002391985151135,
            "start" : 4.52957,
            "duration" : 0.04584,
            "mean" : 79.066875830125866
        },
        {
            "std" : 0.82223538952967057,
            "end" : 4.58169,
            "name" : "Segment",
            "min" : 74.234676036273001,
            "max" : 79.987840083250404,
            "start" : 4.57541,
            "duration" : 0.00628,
            "mean" : 76.698846166805765
        },
        {
            "std" : 1.4795662052062408,
            "end" : 4.58754,
            "name" : "Segment",
            "min" : 76.877519201333669,
            "max" : 84.5379452758159,
            "start" : 4.58169,
            "duration" : 0.00585,
            "mean" : 82.188323199800294
        },
        {
            "std" : 0.84203830223663179,
            "end" : 4.61767,
            "name" : "Segment",
            "min" : 78.561251858609523,
            "max" : 84.246369320675768,
            "start" : 4.58754,
            "duration" : 0.03013,
            "mean" : 81.973519554973166
        },
        {
            "std" : 1.2666561732437269,
            "end" : 4.63437,
            "name" : "Segment",
            "min" : 73.353127376116063,
            "max" : 82.744955552943395,
            "start" : 4.61767,
            "duration" : 0.0167,
            "mean" : 77.532085960738726
        },
        {
            "std" : 0.95415813230435775,
            "end" : 4.6972,
            "name" : "Segment",
            "min" : 79.616803303816837,
            "max" : 84.825798367162918,
            "start" : 4.63437,
            "duration" : 0.06283,
            "mean" : 82.23191331649484
        },
        {
            "std" : 0.86757717843760973,
            "end" : 4.74628,
            "name" : "Segment",
            "min" : 77.976976412065724,
            "max" : 85.376413534979747,
            "start" : 4.6972,
            "duration" : 0.04908,
            "mean" : 80.973586219018458
        },
        {
            "std" : 0.32709023567785017,
            "end" : 4.74932,
            "name" : "Segment",
            "min" : 79.874747468452028,
            "max" : 81.203558582608082,
            "start" : 4.74628,
            "duration" : 0.00304,
            "mean" : 80.558188900582778
        },
        {
            "std" : 1.8486489235980197,
            "end" : 4.75052,
            "name" : "Segment",
            "min" : 74.720441701290852,
            "max" : 82.175229535852367,
            "start" : 4.74932,
            "duration" : 0.0012,
            "mean" : 79.840364869227443
        },
        {
            "std" : 0.79486911235358337,
            "end" : 4.94237,
            "name" : "Segment",
            "min" : 79.618446347217699,
            "max" : 85.954533013150254,
            "start" : 4.75052,
            "duration" : 0.19185,
            "mean" : 83.494518496084083
        },
        {
            "std" : 0.91724058481839721,
            "end" : 4.97339,
            "name" : "Segment",
            "min" : 78.329105109075229,
            "max" : 84.496715238150429,
            "start" : 4.94237,
            "duration" : 0.03102,
            "mean" : 81.018993785053524
        },
        {
            "std" : 0.77568738569843843,
            "end" : 4.98506,
            "name" : "Segment",
            "min" : 80.504778579303618,
            "max" : 85.275888638017818,
            "start" : 4.97339,
            "duration" : 0.01167,
            "mean" : 83.501449092807505
        },
        {
            "std" : 0.54030173955941441,
            "end" : 4.99148,
            "name" : "Segment",
            "min" : 81.262303606390333,
            "max" : 83.785241306112539,
            "start" : 4.98506,
            "duration" : 0.00642,
            "mean" : 82.299610913096998
        },
        {
            "std" : 0.63753686390929665,
            "end" : 4.99711,
            "name" : "Segment",
            "min" : 83.510081787332609,
            "max" : 86.315973720662214,
            "start" : 4.99148,
            "duration" : 0.00563,
            "mean" : 84.907387595209627
        },
        {
            "std" : 0.89385005055255584,
            "end" : 5.11354,
            "name" : "Segment",
            "min" : 80.400276768511702,
            "max" : 86.611209144422872,
            "start" : 4.99711,
            "duration" : 0.11643,
            "mean" : 83.99875980482534
        },
        {
            "std" : 0.78798585049777803,
            "end" : 5.13513,
            "name" : "Segment",
            "min" : 82.468632734787917,
            "max" : 86.221507896003104,
            "start" : 5.11354,
            "duration" : 0.02159,
            "mean" : 84.418013560424583
        },
        {
            "std" : 0.61748648947781903,
            "end" : 5.13803,
            "name" : "Segment",
            "min" : 84.329279037904271,
            "max" : 86.361019749624234,
            "start" : 5.13513,
            "duration" : 0.0029,
            "mean" : 85.532679405081737
        },
        {
            "std" : 0.77952895266821698,
            "end" : 5.18734,
            "name" : "Segment",
            "min" : 81.124404509101339,
            "max" : 86.04577208546425,
            "start" : 5.13803,
            "duration" : 0.04931,
            "mean" : 84.0946690689901
        },
        {
            "std" : 0.73150693539391376,
            "end" : 5.21304,
            "name" : "Segment",
            "min" : 78.564409831138065,
            "max" : 84.917514573762944,
            "start" : 5.18734,
            "duration" : 0.0257,
            "mean" : 81.968371820301343
        },
        {
            "std" : 0.77861264697827992,
            "end" : 5.21763,
            "name" : "Segment",
            "min" : 81.706635057722835,
            "max" : 84.93378080294525,
            "start" : 5.21304,
            "duration" : 0.00459,
            "mean" : 83.139746675842986
        },
        {
            "std" : 0.86433911478849013,
            "end" : 5.24939,
            "name" : "Segment",
            "min" : 81.376475085239079,
            "max" : 86.289920035424672,
            "start" : 5.21763,
            "duration" : 0.03176,
            "mean" : 84.259166640907665
        },
        {
            "std" : 1.0468398242498558,
            "end" : 5.27977,
            "name" : "Segment",
            "min" : 77.86240294353793,
            "max" : 85.893446789092366,
            "start" : 5.24939,
            "duration" : 0.03038,
            "mean" : 82.716330624830462
        },
        {
            "std" : 0.79941476595062677,
            "end" : 5.34047,
            "name" : "Segment",
            "min" : 82.356159494251571,
            "max" : 86.642285483186242,
            "start" : 5.27977,
            "duration" : 0.0607,
            "mean" : 84.626115277780727
        },
        {
            "std" : 0.7874395937781753,
            "end" : 5.3678,
            "name" : "Segment",
            "min" : 79.364666835781364,
            "max" : 85.544228927661308,
            "start" : 5.34047,
            "duration" : 0.02733,
            "mean" : 82.459813718464872
        },
        {
            "std" : 0.72017324817943051,
            "end" : 5.3826,
            "name" : "Segment",
            "min" : 81.466497728128914,
            "max" : 86.414388801076697,
            "start" : 5.3678,
            "duration" : 0.0148,
            "mean" : 84.95079119378525
        },
        {
            "std" : 0.84997492649896189,
            "end" : 5.39382,
            "name" : "Segment",
            "min" : 79.436259304046047,
            "max" : 84.937465346782005,
            "start" : 5.3826,
            "duration" : 0.01122,
            "mean" : 82.755632223067451
        },
        {
            "std" : 0.88573859861592186,
            "end" : 5.459,
            "name" : "Segment",
            "min" : 80.504340970346519,
            "max" : 86.847065518296048,
            "start" : 5.39382,
            "duration" : 0.06518,
            "mean" : 84.266439816161338
        },
        {
            "std" : 1.2184285187217603,
            "end" : 5.48973,
            "name" : "Segment",
            "min" : 79.323385315527986,
            "max" : 86.816820255973781,
            "start" : 5.459,
            "duration" : 0.03073,
            "mean" : 84.391179534559924
        },
        {
            "std" : 0.81434891523345776,
            "end" : 5.53662,
            "name" : "Segment",
            "min" : 80.704455443774094,
            "max" : 87.077153000303525,
            "start" : 5.48973,
            "duration" : 0.04689,
            "mean" : 84.070520855422117
        },
        {
            "std" : 0.91370981639145066,
            "end" : 5.55281,
            "name" : "Segment",
            "min" : 82.351803115352567,
            "max" : 86.612448654606851,
            "start" : 5.53662,
            "duration" : 0.01619,
            "mean" : 84.556981248328569
        },
        {
            "std" : 0.7170333877093833,
            "end" : 5.57872,
            "name" : "Segment",
            "min" : 77.856589590617062,
            "max" : 84.909305794802663,
            "start" : 5.55281,
            "duration" : 0.02591,
            "mean" : 82.576839435742215
        },
        {
            "std" : 1.0396600688833124,
            "end" : 5.62942,
            "name" : "Segment",
            "min" : 80.494520227712997,
            "max" : 87.399918083162873,
            "start" : 5.57872,
            "duration" : 0.0507,
            "mean" : 84.525218029421566
        },
        {
            "std" : 0.45367427659120402,
            "end" : 5.66007,
            "name" : "Segment",
            "min" : 79.827388782377739,
            "max" : 84.356553239023484,
            "start" : 5.62942,
            "duration" : 0.03065,
            "mean" : 82.834131709803813
        },
        {
            "std" : 1.7492536677077111,
            "end" : 5.66381,
            "name" : "Segment",
            "min" : 73.595801886766182,
            "max" : 83.1520653189082,
            "start" : 5.66007,
            "duration" : 0.00374,
            "mean" : 82.035596292230792
        },
        {
            "std" : 0.52963852436586345,
            "end" : 5.67756,
            "name" : "Segment",
            "min" : 80.590170422961805,
            "max" : 84.691474316103196,
            "start" : 5.66381,
            "duration" : 0.01375,
            "mean" : 82.649406501397692
        },
        {
            "std" : 1.5392352946078993,
            "end" : 5.68174,
            "name" : "Segment",
            "min" : 75.259134739793822,
            "max" : 83.890233435733251,
            "start" : 5.67756,
            "duration" : 0.00418,
            "mean" : 82.177862060690984
        },
        {
            "std" : 0.85702914365708061,
            "end" : 5.69657,
            "name" : "Segment",
            "min" : 81.89211934514033,
            "max" : 86.852940044320988,
            "start" : 5.68174,
            "duration" : 0.01483,
            "mean" : 84.690813647430048
        },
        {
            "std" : 0.97851087620537691,
            "end" : 5.73828,
            "name" : "Segment",
            "min" : 82.749790246266244,
            "max" : 87.974820319871895,
            "start" : 5.69657,
            "duration" : 0.04171,
            "mean" : 85.312223998279549
        },
        {
            "std" : 1.6946360163329328,
            "end" : 5.73928,
            "name" : "Segment",
            "min" : 79.90614035187221,
            "max" : 85.461181598216669,
            "start" : 5.73828,
            "duration" : 0.001,
            "mean" : 83.041137021582728
        },
        {
            "std" : 0.87683769999843342,
            "end" : 5.77396,
            "name" : "Segment",
            "min" : 80.518117414974853,
            "max" : 87.407520922105363,
            "start" : 5.73928,
            "duration" : 0.03468,
            "mean" : 84.75382821409471
        },
        {
            "std" : 0.97499352635618985,
            "end" : 5.83308,
            "name" : "Segment",
            "min" : 82.589389152890732,
            "max" : 87.927902790875933,
            "start" : 5.77396,
            "duration" : 0.05912,
            "mean" : 85.249117861162674
        },
        {
            "std" : 0.61143880735610678,
            "end" : 5.85386,
            "name" : "Segment",
            "min" : 79.107280996604445,
            "max" : 84.903087347047176,
            "start" : 5.83308,
            "duration" : 0.02078,
            "mean" : 83.43564380511225
        },
        {
            "std" : 0.56656779555806702,
            "end" : 5.88908,
            "name" : "Segment",
            "min" : 79.539063731135187,
            "max" : 85.752211035289335,
            "start" : 5.85386,
            "duration" : 0.03522,
            "mean" : 84.27457414039273
        },
        {
            "std" : 2.0771993499747268,
            "end" : 5.89099,
            "name" : "Segment",
            "min" : 76.850436082762371,
            "max" : 85.66916727500066,
            "start" : 5.88908,
            "duration" : 0.00191,
            "mean" : 83.571606061161489
        },
        {
            "std" : 0.47840273704253677,
            "end" : 5.902,
            "name" : "Segment",
            "min" : 82.353262950405039,
            "max" : 84.472079729445994,
            "start" : 5.89099,
            "duration" : 0.01101,
            "mean" : 83.50384689775828
        },
        {
            "std" : 0.53140111951484392,
            "end" : 5.9189,
            "name" : "Segment",
            "min" : 82.522036207155637,
            "max" : 86.197305841674776,
            "start" : 5.902,
            "duration" : 0.0169,
            "mean" : 84.41054307201621
        },
        {
            "std" : 0.46756734655812765,
            "end" : 5.94171,
            "name" : "Segment",
            "min" : 80.745893204499154,
            "max" : 84.136050598176581,
            "start" : 5.9189,
            "duration" : 0.02281,
            "mean" : 82.687394442887793
        },
        {
            "std" : 1.0120136449065325,
            "end" : 5.97356,
            "name" : "Segment",
            "min" : 71.428961982741143,
            "max" : 80.525053928546839,
            "start" : 5.94171,
            "duration" : 0.03185,
            "mean" : 76.02405685153316
        },
        {
            "std" : 0.81198396549949636,
            "end" : 5.9781,
            "name" : "Segment",
            "min" : 72.36125340810645,
            "max" : 76.401994255305624,
            "start" : 5.97356,
            "duration" : 0.00454,
            "mean" : 75.037439705040114
        },
        {
            "std" : 0.84092726362157277,
            "end" : 6.02185,
            "name" : "Segment",
            "min" : 69.31615870739958,
            "max" : 75.119119210494773,
            "start" : 5.9781,
            "duration" : 0.04375,
            "mean" : 73.391124336201557
        },
        {
            "std" : 2.7012421552300996,
            "end" : 6.02285,
            "name" : "Segment",
            "min" : 70.164479027522134,
            "max" : 80.717309813272806,
            "start" : 6.02185,
            "duration" : 0.001,
            "mean" : 73.57998970057551
        },
        {
            "std" : 0.69142399545538191,
            "end" : 6.06804,
            "name" : "Segment",
            "min" : 76.642686045405824,
            "max" : 85.528253428442454,
            "start" : 6.02285,
            "duration" : 0.04519,
            "mean" : 83.365773781337438
        },
        {
            "std" : 0.60820610965283917,
            "end" : 6.10172,
            "name" : "Segment",
            "min" : 82.371694273644096,
            "max" : 85.925872753013294,
            "start" : 6.06804,
            "duration" : 0.03368,
            "mean" : 84.381921162374752
        },
        {
            "std" : 1.8964418506406948,
            "end" : 6.10272,
            "name" : "Segment",
            "min" : 77.103740970967721,
            "max" : 84.630329123864499,
            "start" : 6.10172,
            "duration" : 0.001,
            "mean" : 82.212736163638553
        },
        {
            "std" : 0.72959931360447561,
            "end" : 6.12507,
            "name" : "Segment",
            "min" : 81.274289031366152,
            "max" : 86.059892431374365,
            "start" : 6.10272,
            "duration" : 0.02235,
            "mean" : 84.196773986527333
        },
        {
            "std" : 0.38313123849457337,
            "end" : 6.12652,
            "name" : "Segment",
            "min" : 84.907712512565567,
            "max" : 86.376513239084233,
            "start" : 6.12507,
            "duration" : 0.00145,
            "mean" : 85.463878549377668
        },
        {
            "std" : 0.54808959672457924,
            "end" : 6.15507,
            "name" : "Segment",
            "min" : 81.768222911863404,
            "max" : 85.933135673249041,
            "start" : 6.12652,
            "duration" : 0.02855,
            "mean" : 84.295568127082433
        },
        {
            "std" : 0.47631029265200053,
            "end" : 6.1681,
            "name" : "Segment",
            "min" : 80.980069636987736,
            "max" : 83.816008606588468,
            "start" : 6.15507,
            "duration" : 0.01303,
            "mean" : 82.697207123846113
        },
        {
            "std" : 1.5772173570700567,
            "end" : 6.17346,
            "name" : "Segment",
            "min" : 72.316337240431224,
            "max" : 80.793232314210456,
            "start" : 6.1681,
            "duration" : 0.00536,
            "mean" : 75.728437581791056
        },
        {
            "std" : 0.91989311593956635,
            "end" : 6.23791,
            "name" : "Segment",
            "min" : 71.460909603546767,
            "max" : 78.41753124362134,
            "start" : 6.17346,
            "duration" : 0.06445,
            "mean" : 76.140849130202511
        },
        {
            "std" : 0.97420556192551777,
            "end" : 6.24501,
            "name" : "Segment",
            "min" : 69.670596530219839,
            "max" : 75.23831127417408,
            "start" : 6.23791,
            "duration" : 0.0071,
            "mean" : 73.40388208902398
        },
        {
            "std" : 2.2675699414042416,
            "end" : 6.24614,
            "name" : "Segment",
            "min" : 67.345244698501276,
            "max" : 74.637178897581421,
            "start" : 6.24501,
            "duration" : 0.00113,
            "mean" : 71.553430899739681
        },
        {
            "std" : 0.71694442771648104,
            "end" : 6.26548,
            "name" : "Segment",
            "min" : 68.230110450069589,
            "max" : 74.845193156030177,
            "start" : 6.24614,
            "duration" : 0.01934,
            "mean" : 73.454904318933657
        },
        {
            "std" : 1.6497721114816695,
            "end" : 6.2907,
            "name" : "Segment",
            "min" : 54.945001837182687,
            "max" : 67.80411864257826,
            "start" : 6.26548,
            "duration" : 0.02522,
            "mean" : 58.955071971425468
        },
        {
            "std" : 1.2412593654626267,
            "end" : 6.33299,
            "name" : "Segment",
            "min" : 49.764473452525728,
            "max" : 60.355919105524656,
            "start" : 6.2907,
            "duration" : 0.04229,
            "mean" : 56.439975538248248
        },
        {
            "std" : 1.5952060899662581,
            "end" : 6.33857,
            "name" : "Segment",
            "min" : 49.839797405041189,
            "max" : 57.465510435712204,
            "start" : 6.33299,
            "duration" : 0.00558,
            "mean" : 54.599985903883699
        },
        {
            "std" : 2.2618547188425371,
            "end" : 6.34253,
            "name" : "Segment",
            "min" : 46.413404440887597,
            "max" : 55.532864239669095,
            "start" : 6.33857,
            "duration" : 0.00396,
            "mean" : 51.116227376526538
        },
        {
            "std" : 1.0894116193679155,
            "end" : 6.35757,
            "name" : "Segment",
            "min" : 53.155830761010066,
            "max" : 59.813657480004828,
            "start" : 6.34253,
            "duration" : 0.01504,
            "mean" : 55.869627316440187
        },
        {
            "std" : 1.8812196421407759,
            "end" : 6.37276,
            "name" : "Segment",
            "min" : 48.167078906455757,
            "max" : 58.015467023228403,
            "start" : 6.35757,
            "duration" : 0.01519,
            "mean" : 54.657943980222782
        },
        {
            "std" : 0.90276853912787691,
            "end" : 6.45962,
            "name" : "Segment",
            "min" : 38.802652536343707,
            "max" : 47.688220267776792,
            "start" : 6.37276,
            "duration" : 0.08686,
            "mean" : 43.802404944216448
        },
        {
            "std" : 0.73567496373910024,
            "end" : 6.50791,
            "name" : "Segment",
            "min" : 38.445352180251398,
            "max" : 44.66279948247989,
            "start" : 6.45962,
            "duration" : 0.04829,
            "mean" : 42.737205718029415
        },
        {
            "std" : 0.68180110219135026,
            "end" : 6.53165,
            "name" : "Segment",
            "min" : 41.8145606978267,
            "max" : 45.28324572436378,
            "start" : 6.50791,
            "duration" : 0.02374,
            "mean" : 43.675125823783624
        },
        {
            "std" : 0.80261036589707779,
            "end" : 6.55418,
            "name" : "Segment",
            "min" : 40.300641221152588,
            "max" : 45.093388040873364,
            "start" : 6.53165,
            "duration" : 0.02253,
            "mean" : 42.789278057381388
        },
        {
            "std" : 0.32215404388230096,
            "end" : 6.55883,
            "name" : "Segment",
            "min" : 42.259222835896985,
            "max" : 43.753395760728317,
            "start" : 6.55418,
            "duration" : 0.00465,
            "mean" : 43.04951026229962
        },
        {
            "std" : 0.7816453026306982,
            "end" : 6.61934,
            "name" : "Segment",
            "min" : 40.070853154456763,
            "max" : 45.525961704840441,
            "start" : 6.55883,
            "duration" : 0.06051,
            "mean" : 43.572556979363476
        },
        {
            "std" : 0.86280020223889331,
            "end" : 6.65897,
            "name" : "Segment",
            "min" : 40.684474221446123,
            "max" : 45.907708684517303,
            "start" : 6.61934,
            "duration" : 0.03963,
            "mean" : 43.923775468273085
        },
        {
            "std" : 0.41588313196502158,
            "end" : 6.66185,
            "name" : "Segment",
            "min" : 41.784836257477671,
            "max" : 43.924482099292049,
            "start" : 6.65897,
            "duration" : 0.00288,
            "mean" : 43.270992038646149
        },
        {
            "std" : 0.64282364993750041,
            "end" : 6.69448,
            "name" : "Segment",
            "min" : 40.64112469088154,
            "max" : 44.049872967822495,
            "start" : 6.66185,
            "duration" : 0.03263,
            "mean" : 42.514169066082651
        },
        {
            "std" : 0.74112319999836429,
            "end" : 6.79617,
            "name" : "Segment",
            "min" : 39.856464392138804,
            "max" : 45.674144088507617,
            "start" : 6.69448,
            "duration" : 0.10169,
            "mean" : 43.589657337260284
        },
        {
            "std" : 0.70250398699726879,
            "end" : 6.99266,
            "name" : "Segment",
            "min" : 37.854725167947961,
            "max" : 45.540500400578523,
            "start" : 6.79617,
            "duration" : 0.19649,
            "mean" : 43.076748209674186
        },
        {
            "std" : 0.63840916300889694,
            "end" : 7.00415,
            "name" : "Segment",
            "min" : 42.103983161414554,
            "max" : 45.218782915760421,
            "start" : 6.99266,
            "duration" : 0.01149,
            "mean" : 43.681980300437516
        },
        {
            "std" : 8.8731801010796634,
            "end" : 7.00711,
            "name" : "Segment",
            "min" : 45.285018105679782,
            "max" : 87.777645388815472,
            "start" : 7.00415,
            "duration" : 0.00296,
            "mean" : 80.342194690672827
        },
        {
            "std" : 0.76376827125952373,
            "end" : 7.00896,
            "name" : "Segment",
            "min" : 77.552913286724461,
            "max" : 82.25039608034119,
            "start" : 7.00711,
            "duration" : 0.00185,
            "mean" : 79.112440904924284
        },
        {
            "std" : 1.0020711814004251,
            "end" : 7.03494,
            "name" : "Segment",
            "min" : 76.668756551536248,
            "max" : 88.715476927528329,
            "start" : 7.00896,
            "duration" : 0.02598,
            "mean" : 85.004647846913613
        },
        {
            "std" : 3.5054832838958494,
            "end" : 7.03594,
            "name" : "Segment",
            "min" : 67.201054642039637,
            "max" : 85.512700475103301,
            "start" : 7.03494,
            "duration" : 0.001,
            "mean" : 83.666218096643917
        },
        {
            "std" : 6.030716199498646,
            "end" : 7.04368,
            "name" : "Segment",
            "min" : 21.318233528048143,
            "max" : 65.163129163650495,
            "start" : 7.03594,
            "duration" : 0.00774,
            "mean" : 34.35629709079052
        },
        {
            "std" : 0.94530398101120339,
            "end" : 7.04714,
            "name" : "Segment",
            "min" : 22.552049854659437,
            "max" : 28.385528165116774,
            "start" : 7.04368,
            "duration" : 0.00346,
            "mean" : 26.385468855063639
        },
        {
            "std" : 0.87336695728581726,
            "end" : 7.29894,
            "name" : "Segment",
            "min" : 15.459201665649367,
            "max" : 24.814902516436632,
            "start" : 7.04714,
            "duration" : 0.2518,
            "mean" : 19.781350211237939
        },
        {
            "std" : 0.57342480922360317,
            "end" : 7.31745,
            "name" : "Segment",
            "min" : 17.785862225286657,
            "max" : 21.097597504126302,
            "start" : 7.29894,
            "duration" : 0.01851,
            "mean" : 19.557429400706486
        },
        {
            "std" : 1.1901474803846888,
            "end" : 7.33649,
            "name" : "Segment",
            "min" : 15.373988115791592,
            "max" : 24.455257181093998,
            "start" : 7.31745,
            "duration" : 0.01904,
            "mean" : 19.951584285860154
        },
        {
            "std" : 0.86001402446098518,
            "end" : 7.48476,
            "name" : "Segment",
            "min" : 15.57073259060637,
            "max" : 24.140944939842505,
            "start" : 7.33649,
            "duration" : 0.14827,
            "mean" : 19.771586011294438
        },
        {
            "std" : 1.1627695416931003,
            "end" : 7.53226,
            "name" : "Segment",
            "min" : 15.854309239172149,
            "max" : 24.789249673461082,
            "start" : 7.48476,
            "duration" : 0.0475,
            "mean" : 19.98113201552983
        },
        {
            "std" : 0.874975246454195,
            "end" : 8.05717,
            "name" : "Segment",
            "min" : 16.101512627335524,
            "max" : 23.97796465091163,
            "start" : 7.53226,
            "duration" : 0.52491,
            "mean" : 19.778214400234571
        },
        {
            "std" : 0.73235044971602492,
            "end" : 8.11096,
            "name" : "Segment",
            "min" : 17.202316970023976,
            "max" : 22.547821828628436,
            "start" : 8.05717,
            "duration" : 0.05379,
            "mean" : 19.689287258507818
        },
        {
            "std" : 0.95434156870439057,
            "end" : 8.17628,
            "name" : "Segment",
            "min" : 17.223665947757567,
            "max" : 24.728430799990587,
            "start" : 8.11096,
            "duration" : 0.06532,
            "mean" : 19.939678169803312
        },
        {
            "std" : 1.2241604257592749,
            "end" : 8.18723,
            "name" : "Segment",
            "min" : 18.040183945483243,
            "max" : 25.339808993051705,
            "start" : 8.17628,
            "duration" : 0.01095,
            "mean" : 20.50695576807739
        },
        {
            "std" : 0.89004700255274605,
            "end" : 8.27552,
            "name" : "Segment",
            "min" : 16.751134005071187,
            "max" : 24.365209858063388,
            "start" : 8.18723,
            "duration" : 0.08829,
            "mean" : 19.785920831769488
        },
        {
            "std" : 1.0320238152451724,
            "end" : 8.27658,
            "name" : "Segment",
            "min" : 20.64109381809606,
            "max" : 24.254242668696886,
            "start" : 8.27552,
            "duration" : 0.00106,
            "mean" : 22.701454662716245
        },
        {
            "std" : 0.95799142693250783,
            "end" : 8.37326,
            "name" : "Segment",
            "min" : 15.856574794989612,
            "max" : 24.262630406921875,
            "start" : 8.27658,
            "duration" : 0.09668,
            "mean" : 19.823440260472839
        },
        {
            "std" : 0.5245756788314675,
            "end" : 8.38171,
            "name" : "Segment",
            "min" : 18.815942748643227,
            "max" : 22.219172507779849,
            "start" : 8.37326,
            "duration" : 0.00845,
            "mean" : 19.881912209023533
        },
        {
            "std" : 4.9044932298593826,
            "end" : 8.38271,
            "name" : "Segment",
            "min" : 5.5435940211191026,
            "max" : 20.067330493753047,
            "start" : 8.38171,
            "duration" : 0.001,
            "mean" : 15.647823346387078
        },
        {
            "std" : 0.94154267177479745,
            "end" : 8.53371,
            "name" : "Segment",
            "min" : 16.158505818008361,
            "max" : 24.994810275124063,
            "start" : 8.38271,
            "duration" : 0.151,
            "mean" : 19.852298800613823
        },
        {
            "std" : 0.87672741302231205,
            "end" : 8.64882,
            "name" : "Segment",
            "min" : 16.831344245180297,
            "max" : 24.693931486704681,
            "start" : 8.53371,
            "duration" : 0.11511,
            "mean" : 19.843587133252896
        },
        {
            "std" : 1.7074654989572626,
            "end" : 8.64982,
            "name" : "Segment",
            "min" : 19.191377966638797,
            "max" : 24.835174350283548,
            "start" : 8.64882,
            "duration" : 0.001,
            "mean" : 21.636351625100538
        },
        {
            "std" : 0.75561608169502636,
            "end" : 8.67223,
            "name" : "Segment",
            "min" : 17.314532547719928,
            "max" : 22.523939621045397,
            "start" : 8.64982,
            "duration" : 0.02241,
            "mean" : 19.657854013392189
        },
        {
            "std" : 6.494799255261503,
            "end" : 8.67323,
            "name" : "Segment",
            "min" : 2.8788740569199702,
            "max" : 20.850457901412835,
            "start" : 8.67223,
            "duration" : 0.001,
            "mean" : 12.142954038213468
        },
        {
            "std" : 0.97038496283368469,
            "end" : 8.73082,
            "name" : "Segment",
            "min" : 16.720269665266464,
            "max" : 26.072343434851838,
            "start" : 8.67323,
            "duration" : 0.05759,
            "mean" : 19.858683998769699
        },
        {
            "std" : 1.1154213523823788,
            "end" : 8.74392,
            "name" : "Segment",
            "min" : 16.835765719208393,
            "max" : 24.535408484057079,
            "start" : 8.73082,
            "duration" : 0.0131,
            "mean" : 20.21068738291514
        },
        {
            "std" : 0.70735827460467793,
            "end" : 8.77899,
            "name" : "Segment",
            "min" : 16.973053547257283,
            "max" : 22.540130378583463,
            "start" : 8.74392,
            "duration" : 0.03507,
            "mean" : 19.60647460669659
        },
        {
            "std" : 0.90423820060834503,
            "end" : 8.79132,
            "name" : "Segment",
            "min" : 18.182909165886297,
            "max" : 23.234609441597826,
            "start" : 8.77899,
            "duration" : 0.01233,
            "mean" : 20.313430988072163
        },
        {
            "std" : 0.95276710547030707,
            "end" : 8.89401,
            "name" : "Segment",
            "min" : 15.475685969472826,
            "max" : 25.359937074871844,
            "start" : 8.79132,
            "duration" : 0.10269,
            "mean" : 19.762008824003988
        },
        {
            "std" : 0.66202349191310683,
            "end" : 8.89736,
            "name" : "Segment",
            "min" : 16.3723993033848,
            "max" : 18.886405484937573,
            "start" : 8.89401,
            "duration" : 0.00335,
            "mean" : 17.655769959930311
        },
        {
            "std" : 0.74346115258635048,
            "end" : 8.91825,
            "name" : "Segment",
            "min" : 18.011657012636594,
            "max" : 22.558396615996372,
            "start" : 8.89736,
            "duration" : 0.02089,
            "mean" : 19.760541005054129
        },
        {
            "std" : 1.1490574580104871,
            "end" : 8.92168,
            "name" : "Segment",
            "min" : 18.962392437236964,
            "max" : 23.860505826017409,
            "start" : 8.91825,
            "duration" : 0.00343,
            "mean" : 20.613393600810102
        },
        {
            "std" : 3.1902820936991549,
            "end" : 8.92268,
            "name" : "Segment",
            "min" : 10.630621242330745,
            "max" : 19.547728769268449,
            "start" : 8.92168,
            "duration" : 0.001,
            "mean" : 15.46110911550698
        },
        {
            "std" : 0.90999792239514887,
            "end" : 9.34651,
            "name" : "Segment",
            "min" : 16.086558363781322,
            "max" : 25.158278020095903,
            "start" : 8.92268,
            "duration" : 0.42383,
            "mean" : 19.849564376679428
        },
        {
            "std" : 3.1607228793449087,
            "end" : 9.34857,
            "name" : "Segment",
            "min" : 10.842184507250881,
            "max" : 21.627356126848834,
            "start" : 9.34651,
            "duration" : 0.00206,
            "mean" : 17.53056879006169
        },
        {
            "std" : 0.84071723181434455,
            "end" : 9.40258,
            "name" : "Segment",
            "min" : 17.074037126535718,
            "max" : 23.909937869739235,
            "start" : 9.34857,
            "duration" : 0.05401,
            "mean" : 19.78287585929359
        },
        {
            "std" : 3.489806820887924,
            "end" : 9.40594,
            "name" : "Segment",
            "min" : 5.5523291259695098,
            "max" : 18.505015898681261,
            "start" : 9.40258,
            "duration" : 0.00336,
            "mean" : 11.906314228737424
        },
        {
            "std" : 1.2062183489075073,
            "end" : 9.40856,
            "name" : "Segment",
            "min" : 17.569070074385586,
            "max" : 23.044474708766582,
            "start" : 9.40594,
            "duration" : 0.00262,
            "mean" : 20.184261505656256
        },
        {
            "std" : 0.80527448210396768,
            "end" : 9.46068,
            "name" : "Segment",
            "min" : 16.751969560362141,
            "max" : 24.359211192167983,
            "start" : 9.40856,
            "duration" : 0.05212,
            "mean" : 19.694313445279452
        },
        {
            "std" : 1.5665764944599749,
            "end" : 9.46267,
            "name" : "Segment",
            "min" : 19.223633002309978,
            "max" : 24.739940392843828,
            "start" : 9.46068,
            "duration" : 0.00199,
            "mean" : 21.344244931578061
        },
        {
            "std" : 0.83451196019445961,
            "end" : 9.50642,
            "name" : "Segment",
            "min" : 17.54406810609909,
            "max" : 23.96877299006254,
            "start" : 9.46267,
            "duration" : 0.04375,
            "mean" : 19.797409578787139
        },
        {
            "std" : 1.6783318593192811,
            "end" : 9.50742,
            "name" : "Segment",
            "min" : 19.848745284167151,
            "max" : 25.614733009299975,
            "start" : 9.50642,
            "duration" : 0.001,
            "mean" : 22.290817526386849
        },
        {
            "std" : 0.26089155614924187,
            "end" : 9.50937,
            "name" : "Segment",
            "min" : 19.962513738170784,
            "max" : 21.02321249122296,
            "start" : 9.50742,
            "duration" : 0.00195,
            "mean" : 20.521878563697967
        },
        {
            "std" : 1.0752750592697902,
            "end" : 9.52481,
            "name" : "Segment",
            "min" : 16.234417128970371,
            "max" : 24.063825419650371,
            "start" : 9.50937,
            "duration" : 0.01544,
            "mean" : 19.88875957392202
        },
        {
            "std" : 0.69773483829704042,
            "end" : 9.56697,
            "name" : "Segment",
            "min" : 17.558885609966488,
            "max" : 22.460613529295017,
            "start" : 9.52481,
            "duration" : 0.04216,
            "mean" : 19.60136764220276
        },
        {
            "std" : 1.819077133240671,
            "end" : 9.57021,
            "name" : "Segment",
            "min" : 18.512181498601372,
            "max" : 25.642679097178011,
            "start" : 9.56697,
            "duration" : 0.00324,
            "mean" : 20.923001711361035
        },
        {
            "std" : 0.82193397183764849,
            "end" : 9.63388,
            "name" : "Segment",
            "min" : 17.003592817967565,
            "max" : 24.146559879785276,
            "start" : 9.57021,
            "duration" : 0.06367,
            "mean" : 19.73591964060007
        },
        {
            "std" : 1.6117513912804786,
            "end" : 9.63488,
            "name" : "Segment",
            "min" : 19.943159162267033,
            "max" : 25.136743645060626,
            "start" : 9.63388,
            "duration" : 0.001,
            "mean" : 21.862228689772564
        },
        {
            "std" : 0.97971399136190895,
            "end" : 9.70214,
            "name" : "Segment",
            "min" : 15.779931482732914,
            "max" : 25.081578386920366,
            "start" : 9.63488,
            "duration" : 0.06726,
            "mean" : 19.810921731436071
        },
        {
            "std" : 1.7843413684013958,
            "end" : 9.70571,
            "name" : "Segment",
            "min" : 18.246299893382776,
            "max" : 25.232891690267152,
            "start" : 9.70214,
            "duration" : 0.00357,
            "mean" : 20.702573046581996
        },
        {
            "std" : 0.87132831923856502,
            "end" : 9.85562,
            "name" : "Segment",
            "min" : 16.183086006790298,
            "max" : 25.600899371112764,
            "start" : 9.70571,
            "duration" : 0.14991,
            "mean" : 19.810818651401778
        },
        {
            "std" : 1.9732678334081339,
            "end" : 9.85671,
            "name" : "Segment",
            "min" : 20.395756632232938,
            "max" : 26.519900475835559,
            "start" : 9.85562,
            "duration" : 0.00109,
            "mean" : 22.974312897235091
        },
        {
            "std" : 0.84423266558818177,
            "end" : 9.94614,
            "name" : "Segment",
            "min" : 16.816374508699724,
            "max" : 24.484141512018727,
            "start" : 9.85671,
            "duration" : 0.08943,
            "mean" : 19.759334992891961
        },
        {
            "std" : 1.1901678979783019,
            "end" : 9.95176,
            "name" : "Segment",
            "min" : 18.338582803492482,
            "max" : 23.843324960119773,
            "start" : 9.94614,
            "duration" : 0.00562,
            "mean" : 20.702487732453839
        },
        {
            "std" : 0.78026986981520929,
            "end" : 10.04355,
            "name" : "Segment",
            "min" : 15.686895938683184,
            "max" : 24.69307722284837,
            "start" : 9.95176,
            "duration" : 0.09179,
            "mean" : 19.855588674345675
        },
        {
            "std" : 0.97662329864757824,
            "end" : 10.04558,
            "name" : "Segment",
            "min" : 16.066576667294267,
            "max" : 19.74846446514551,
            "start" : 10.04355,
            "duration" : 0.00203,
            "mean" : 17.941023592522619
        },
        {
            "std" : 0.96037921090497147,
            "end" : 10.15802,
            "name" : "Segment",
            "min" : 16.526230734827557,
            "max" : 24.110927351385691,
            "start" : 10.04558,
            "duration" : 0.11244,
            "mean" : 19.855060865490906
        },
        {
            "std" : 2.5628327840331719,
            "end" : 10.15945,
            "name" : "Segment",
            "min" : 11.102480140468996,
            "max" : 19.516984761337458,
            "start" : 10.15802,
            "duration" : 0.00143,
            "mean" : 16.401510521428175
        },
        {
            "std" : 0.99491953509619058,
            "end" : 10.29791,
            "name" : "Segment",
            "min" : 15.961587848458006,
            "max" : 26.508931775818528,
            "start" : 10.15945,
            "duration" : 0.13846,
            "mean" : 19.937153963172339
        },
        {
            "std" : 0.5718689650977784,
            "end" : 10.31442,
            "name" : "Segment",
            "min" : 18.343343583857735,
            "max" : 21.188290729304896,
            "start" : 10.29791,
            "duration" : 0.01651,
            "mean" : 19.71024884909237
        },
        {
            "std" : 1.2174960161746269,
            "end" : 10.33356,
            "name" : "Segment",
            "min" : 16.328728719215967,
            "max" : 25.733438646612747,
            "start" : 10.31442,
            "duration" : 0.01914,
            "mean" : 19.907293399472763
        },
        {
            "std" : 0.80526836731506013,
            "end" : 10.41789,
            "name" : "Segment",
            "min" : 16.384927859600054,
            "max" : 22.924793650025418,
            "start" : 10.33356,
            "duration" : 0.08433,
            "mean" : 19.7526815065258
        },
        {
            "std" : 3.0127970839461309,
            "end" : 10.42372,
            "name" : "Segment",
            "min" : 3.9262841317012764,
            "max" : 18.037168151957438,
            "start" : 10.41789,
            "duration" : 0.00583,
            "mean" : 12.04231277165788
        },
        {
            "std" : 3.7413681832789685,
            "end" : 10.42523,
            "name" : "Segment",
            "min" : 1.0905690730448176,
            "max" : 17.436953447006704,
            "start" : 10.42372,
            "duration" : 0.00151,
            "mean" : 3.6727533647522295
        },
        {
            "std" : 0.8958592018419308,
            "end" : 10.56819,
            "name" : "Segment",
            "min" : 16.352289050912031,
            "max" : 24.05182899528506,
            "start" : 10.42523,
            "duration" : 0.14296,
            "mean" : 19.685524546236671
        },
        {
            "std" : 1.0509808898520312,
            "end" : 10.57521,
            "name" : "Segment",
            "min" : 17.391134772169863,
            "max" : 23.665963938806815,
            "start" : 10.56819,
            "duration" : 0.00702,
            "mean" : 20.414573920940544
        },
        {
            "std" : 0.84972094700481593,
            "end" : 10.89206,
            "name" : "Segment",
            "min" : 16.569799209164476,
            "max" : 25.727411710001594,
            "start" : 10.57521,
            "duration" : 0.31685,
            "mean" : 19.82300388325628
        },
        {
            "std" : 1.2631855290024034,
            "end" : 10.9011,
            "name" : "Segment",
            "min" : 18.338101082817492,
            "max" : 24.834500745633154,
            "start" : 10.89206,
            "duration" : 0.00904,
            "mean" : 20.462091768087873
        },
        {
            "std" : 0.70041167083632294,
            "end" : 10.91242,
            "name" : "Segment",
            "min" : 17.660147496439176,
            "max" : 21.39181323372604,
            "start" : 10.9011,
            "duration" : 0.01132,
            "mean" : 19.74785004838791
        },
        {
            "std" : 15.211683883671597,
            "end" : 10.91342,
            "name" : "Segment",
            "min" : 19.30048510452567,
            "max" : 85.607257793424637,
            "start" : 10.91242,
            "duration" : 0.001,
            "mean" : 26.659517217713809
        }
    ],
    "filter_cutoff" : 2000,
    "filter_order" : 1,
    "start" : 89.479799999999997,
    "duration" : 10.91342,
    "filtered" : true,
    "n" : 294,
    "mean" : 39.021751681109116
}