{
    "std" : 17.002239488080871,
    "end" : 328.03458999999998,
    "state_parser" : {
        "name" : "SpeedyStatSplit",
        "min_gain_per_sample" : null,
        "false_positive_rate" : null,
        "max_width" : 1000000,
        "window_width" : 10000,
        "prior_segments_per_second" : 40,
        "min_width" : 100,
        "cutoff_freq" : 2000,
        "sampling_freq" : 100000.0
    },
    "name" : "Event",
    "min" : 9.3269207276749366,
    "max" : 106.89960810595166,
    "segments" : [
        {
            "std" : 12.441166764785848,
            "end" : 0.00252,
            "name" : "Segment",
            "min" : 39.633301832793514,
            "max" : 106.89960810595166,
            "start" : 0.0,
            "duration" : 0.00252,
            "mean" : 49.771146313676532
        },
        {
            "std" : 1.8596506160722448,
            "end" : 0.01053,
            "name" : "Segment",
            "min" : 39.397636338249342,
            "max" : 49.880563631959141,
            "start" : 0.00252,
            "duration" : 0.00801,
            "mean" : 41.989132944634285
        },
        {
            "std" : 0.79686283952838866,
            "end" : 0.02045,
            "name" : "Segment",
            "min" : 40.80172748143125,
            "max" : 44.834544066293716,
            "start" : 0.01053,
            "duration" : 0.00992,
            "mean" : 42.620244467493293
        },
        {
            "std" : 0.8380982704470068,
            "end" : 0.02448,
            "name" : "Segment",
            "min" : 37.208621196792265,
            "max" : 41.547479567040803,
            "start" : 0.02045,
            "duration" : 0.00403,
            "mean" : 39.415078135450827
        },
        {
            "std" : 1.8656168477402646,
            "end" : 0.03121,
            "name" : "Segment",
            "min" : 39.802032716392603,
            "max" : 48.045528589857753,
            "start" : 0.02448,
            "duration" : 0.00673,
            "mean" : 42.479009512744575
        },
        {
            "std" : 2.5499709717085484,
            "end" : 0.03497,
            "name" : "Segment",
            "min" : 39.3062883851468,
            "max" : 48.838565413249874,
            "start" : 0.03121,
            "duration" : 0.00376,
            "mean" : 45.553790302374985
        },
        {
            "std" : 1.815694757099243,
            "end" : 0.05726,
            "name" : "Segment",
            "min" : 37.573543345159791,
            "max" : 47.12699739386909,
            "start" : 0.03497,
            "duration" : 0.02229,
            "mean" : 41.484695666924068
        },
        {
            "std" : 1.980808922426075,
            "end" : 0.05861,
            "name" : "Segment",
            "min" : 33.293531343205458,
            "max" : 39.839138050325381,
            "start" : 0.05726,
            "duration" : 0.00135,
            "mean" : 36.148220177442454
        },
        {
            "std" : 0.8786941931204908,
            "end" : 0.06172,
            "name" : "Segment",
            "min" : 38.174761053184938,
            "max" : 43.513754204828714,
            "start" : 0.05861,
            "duration" : 0.00311,
            "mean" : 40.955768323264799
        },
        {
            "std" : 0.38439136794058071,
            "end" : 0.06294,
            "name" : "Segment",
            "min" : 43.556223161379251,
            "max" : 45.113501766505578,
            "start" : 0.06172,
            "duration" : 0.00122,
            "mean" : 44.402881664499162
        },
        {
            "std" : 1.5338190779151522,
            "end" : 0.07196,
            "name" : "Segment",
            "min" : 42.651457970196013,
            "max" : 50.600000056933041,
            "start" : 0.06294,
            "duration" : 0.00902,
            "mean" : 47.858851573362891
        },
        {
            "std" : 0.71428729789504464,
            "end" : 0.10472,
            "name" : "Segment",
            "min" : 42.94209335290752,
            "max" : 47.565333141060599,
            "start" : 0.07196,
            "duration" : 0.03276,
            "mean" : 44.995130653825854
        },
        {
            "std" : 2.1870151565271927,
            "end" : 0.10745,
            "name" : "Segment",
            "min" : 37.52978795655968,
            "max" : 46.52294802033996,
            "start" : 0.10472,
            "duration" : 0.00273,
            "mean" : 43.381548205767956
        },
        {
            "std" : 0.90645295830148098,
            "end" : 0.14881,
            "name" : "Segment",
            "min" : 39.513341012974706,
            "max" : 47.006287502333521,
            "start" : 0.10745,
            "duration" : 0.04136,
            "mean" : 44.767368993645974
        },
        {
            "std" : 0.88635036605914674,
            "end" : 0.18386,
            "name" : "Segment",
            "min" : 38.73461656943762,
            "max" : 45.80753787736473,
            "start" : 0.14881,
            "duration" : 0.03505,
            "mean" : 43.869355892846862
        },
        {
            "std" : 0.87011155859973544,
            "end" : 0.238,
            "name" : "Segment",
            "min" : 32.953284588852263,
            "max" : 39.987889119148967,
            "start" : 0.18386,
            "duration" : 0.05414,
            "mean" : 36.698208898005547
        },
        {
            "std" : 0.81471956023248249,
            "end" : 0.3306,
            "name" : "Segment",
            "min" : 32.665667823091788,
            "max" : 39.749092028719026,
            "start" : 0.238,
            "duration" : 0.0926,
            "mean" : 36.912584652369958
        },
        {
            "std" : 0.94929235506023091,
            "end" : 0.36572,
            "name" : "Segment",
            "min" : 31.658982593000495,
            "max" : 39.507643684715667,
            "start" : 0.3306,
            "duration" : 0.03512,
            "mean" : 36.706958355757223
        },
        {
            "std" : 1.0360500210717378,
            "end" : 0.37433,
            "name" : "Segment",
            "min" : 31.830360079166041,
            "max" : 39.483633614700935,
            "start" : 0.36572,
            "duration" : 0.00861,
            "mean" : 35.82419280935467
        },
        {
            "std" : 1.4589680380179604,
            "end" : 0.39002,
            "name" : "Segment",
            "min" : 39.888943760302553,
            "max" : 48.113395079465384,
            "start" : 0.37433,
            "duration" : 0.01569,
            "mean" : 44.467286604722368
        },
        {
            "std" : 1.3336597289055467,
            "end" : 0.4402,
            "name" : "Segment",
            "min" : 38.171830178433943,
            "max" : 48.848450843750058,
            "start" : 0.39002,
            "duration" : 0.05018,
            "mean" : 43.472099944087176
        },
        {
            "std" : 0.96456238126652738,
            "end" : 0.48824,
            "name" : "Segment",
            "min" : 40.630898981001209,
            "max" : 46.908549475568513,
            "start" : 0.4402,
            "duration" : 0.04804,
            "mean" : 44.214362687344739
        },
        {
            "std" : 1.9274718261808645,
            "end" : 0.48955,
            "name" : "Segment",
            "min" : 44.946804432382805,
            "max" : 50.234160480541114,
            "start" : 0.48824,
            "duration" : 0.00131,
            "mean" : 47.487450900330344
        },
        {
            "std" : 1.0304075147032632,
            "end" : 0.50528,
            "name" : "Segment",
            "min" : 39.697848596661487,
            "max" : 46.537313944904369,
            "start" : 0.48955,
            "duration" : 0.01573,
            "mean" : 44.144781362860478
        },
        {
            "std" : 0.59616716182676821,
            "end" : 0.51324,
            "name" : "Segment",
            "min" : 42.039958835869065,
            "max" : 44.828661915610901,
            "start" : 0.50528,
            "duration" : 0.00796,
            "mean" : 43.270652682734919
        },
        {
            "std" : 1.4308350958528171,
            "end" : 0.53971,
            "name" : "Segment",
            "min" : 36.941824661403778,
            "max" : 45.432148309399437,
            "start" : 0.51324,
            "duration" : 0.02647,
            "mean" : 42.898438026096379
        },
        {
            "std" : 1.0642417077996755,
            "end" : 0.57445,
            "name" : "Segment",
            "min" : 30.116302179305695,
            "max" : 39.807455340565504,
            "start" : 0.53971,
            "duration" : 0.03474,
            "mean" : 35.538427333052411
        },
        {
            "std" : 1.1064775947554553,
            "end" : 0.73268,
            "name" : "Segment",
            "min" : 29.727995410855261,
            "max" : 39.817175006703806,
            "start" : 0.57445,
            "duration" : 0.15823,
            "mean" : 33.991622498705553
        },
        {
            "std" : 3.341793358277136,
            "end" : 0.74696,
            "name" : "Segment",
            "min" : 37.652135617504285,
            "max" : 51.782882480613132,
            "start" : 0.73268,
            "duration" : 0.01428,
            "mean" : 45.912579263423609
        },
        {
            "std" : 0.69218169571873067,
            "end" : 0.75099,
            "name" : "Segment",
            "min" : 46.884161774077995,
            "max" : 50.598984306358446,
            "start" : 0.74696,
            "duration" : 0.00403,
            "mean" : 49.282451019126441
        },
        {
            "std" : 1.8318608660113664,
            "end" : 0.75331,
            "name" : "Segment",
            "min" : 44.177437963644692,
            "max" : 50.806578782021731,
            "start" : 0.75099,
            "duration" : 0.00232,
            "mean" : 47.396605171563081
        },
        {
            "std" : 2.1037744381581303,
            "end" : 0.76519,
            "name" : "Segment",
            "min" : 39.22740786418953,
            "max" : 51.891300648552495,
            "start" : 0.75331,
            "duration" : 0.01188,
            "mean" : 45.267024884346327
        },
        {
            "std" : 0.8892056791766263,
            "end" : 0.8077,
            "name" : "Segment",
            "min" : 45.604706497090888,
            "max" : 52.283157720108754,
            "start" : 0.76519,
            "duration" : 0.04251,
            "mean" : 50.249429382262406
        },
        {
            "std" : 0.42714672128505382,
            "end" : 0.81199,
            "name" : "Segment",
            "min" : 48.188426458015009,
            "max" : 50.391705692831664,
            "start" : 0.8077,
            "duration" : 0.00429,
            "mean" : 49.456173287740064
        },
        {
            "std" : 0.7991766540904367,
            "end" : 0.8224,
            "name" : "Segment",
            "min" : 45.638109715827042,
            "max" : 50.183805796502043,
            "start" : 0.81199,
            "duration" : 0.01041,
            "mean" : 48.818973479164114
        },
        {
            "std" : 1.1289229304267732,
            "end" : 0.83352,
            "name" : "Segment",
            "min" : 41.750830475494482,
            "max" : 48.442598495976412,
            "start" : 0.8224,
            "duration" : 0.01112,
            "mean" : 45.087694116138785
        },
        {
            "std" : 1.066473741378851,
            "end" : 0.87023,
            "name" : "Segment",
            "min" : 38.972051235399476,
            "max" : 47.552633088644498,
            "start" : 0.83352,
            "duration" : 0.03671,
            "mean" : 43.796895762238158
        },
        {
            "std" : 1.7106902690464256,
            "end" : 0.88221,
            "name" : "Segment",
            "min" : 36.18095940093108,
            "max" : 47.715412783561007,
            "start" : 0.87023,
            "duration" : 0.01198,
            "mean" : 43.674814455092566
        },
        {
            "std" : 0.43796964692557994,
            "end" : 0.88702,
            "name" : "Segment",
            "min" : 42.482909404090449,
            "max" : 44.88267687668295,
            "start" : 0.88221,
            "duration" : 0.00481,
            "mean" : 43.81360262162876
        },
        {
            "std" : 1.005416328312738,
            "end" : 0.90163,
            "name" : "Segment",
            "min" : 40.512586268453212,
            "max" : 46.376186041314227,
            "start" : 0.88702,
            "duration" : 0.01461,
            "mean" : 43.81392690687909
        },
        {
            "std" : 1.3676413797165634,
            "end" : 0.90714,
            "name" : "Segment",
            "min" : 38.968605477191474,
            "max" : 45.141753565904928,
            "start" : 0.90163,
            "duration" : 0.00551,
            "mean" : 42.787595740092065
        },
        {
            "std" : 1.12006462321644,
            "end" : 0.91783,
            "name" : "Segment",
            "min" : 41.311891712712338,
            "max" : 47.344792626666845,
            "start" : 0.90714,
            "duration" : 0.01069,
            "mean" : 44.434238223291047
        },
        {
            "std" : 1.525481131021293,
            "end" : 1.03375,
            "name" : "Segment",
            "min" : 39.462546284213829,
            "max" : 52.000527505076292,
            "start" : 0.91783,
            "duration" : 0.11592,
            "mean" : 45.926728996738632
        },
        {
            "std" : 1.2084297805060784,
            "end" : 1.07888,
            "name" : "Segment",
            "min" : 42.261649853258419,
            "max" : 50.297250193794511,
            "start" : 1.03375,
            "duration" : 0.04513,
            "mean" : 46.801126698072011
        },
        {
            "std" : 1.0845055489601654,
            "end" : 1.08662,
            "name" : "Segment",
            "min" : 41.606046003135631,
            "max" : 47.63176830290849,
            "start" : 1.07888,
            "duration" : 0.00774,
            "mean" : 45.310905526759718
        },
        {
            "std" : 1.2928191973090664,
            "end" : 1.10844,
            "name" : "Segment",
            "min" : 42.909731550805994,
            "max" : 49.702603477273726,
            "start" : 1.08662,
            "duration" : 0.02182,
            "mean" : 46.557546927302461
        },
        {
            "std" : 0.9121835871951034,
            "end" : 1.17243,
            "name" : "Segment",
            "min" : 41.353909904553305,
            "max" : 51.251612862614849,
            "start" : 1.10844,
            "duration" : 0.06399,
            "mean" : 48.809744197553798
        },
        {
            "std" : 0.87857472278242621,
            "end" : 1.42946,
            "name" : "Segment",
            "min" : 41.562668877233868,
            "max" : 50.485003026876306,
            "start" : 1.17243,
            "duration" : 0.25703,
            "mean" : 48.115164716424076
        },
        {
            "std" : 1.7728235409680759,
            "end" : 1.43046,
            "name" : "Segment",
            "min" : 42.20094683556858,
            "max" : 49.972690541306406,
            "start" : 1.42946,
            "duration" : 0.001,
            "mean" : 46.024749405097381
        },
        {
            "std" : 0.84720395006791105,
            "end" : 1.71264,
            "name" : "Segment",
            "min" : 42.79490805068545,
            "max" : 50.475783311756466,
            "start" : 1.43046,
            "duration" : 0.28218,
            "mean" : 48.058090717625646
        },
        {
            "std" : 0.84674386307574256,
            "end" : 1.74286,
            "name" : "Segment",
            "min" : 42.725766877465965,
            "max" : 49.271015381006535,
            "start" : 1.71264,
            "duration" : 0.03022,
            "mean" : 47.2790371739924
        },
        {
            "std" : 0.8069778900871466,
            "end" : 1.77638,
            "name" : "Segment",
            "min" : 45.209845459375998,
            "max" : 50.446548270242097,
            "start" : 1.74286,
            "duration" : 0.03352,
            "mean" : 48.063602911659963
        },
        {
            "std" : 0.72005536854437246,
            "end" : 2.15852,
            "name" : "Segment",
            "min" : 39.94349418159473,
            "max" : 47.359886582867524,
            "start" : 1.77638,
            "duration" : 0.38214,
            "mean" : 45.158396238380483
        },
        {
            "std" : 0.75001380381763294,
            "end" : 2.3731,
            "name" : "Segment",
            "min" : 40.147997232655506,
            "max" : 46.612170326263332,
            "start" : 2.15852,
            "duration" : 0.21458,
            "mean" : 44.428688956774053
        },
        {
            "std" : 0.85096971920564268,
            "end" : 2.42483,
            "name" : "Segment",
            "min" : 43.416315407366199,
            "max" : 50.169431245080723,
            "start" : 2.3731,
            "duration" : 0.05173,
            "mean" : 47.987751769340449
        },
        {
            "std" : 0.7272738697193244,
            "end" : 2.56168,
            "name" : "Segment",
            "min" : 41.748247503973552,
            "max" : 47.562796086799139,
            "start" : 2.42483,
            "duration" : 0.13685,
            "mean" : 45.214570783807908
        },
        {
            "std" : 0.69965044613824168,
            "end" : 2.61301,
            "name" : "Segment",
            "min" : 41.728636959875573,
            "max" : 46.222405885596224,
            "start" : 2.56168,
            "duration" : 0.05133,
            "mean" : 44.330230146080375
        },
        {
            "std" : 0.74312958227101111,
            "end" : 2.75483,
            "name" : "Segment",
            "min" : 39.272201125672566,
            "max" : 46.548430716229376,
            "start" : 2.61301,
            "duration" : 0.14182,
            "mean" : 44.484770489771741
        },
        {
            "std" : 0.6460381706726126,
            "end" : 2.79001,
            "name" : "Segment",
            "min" : 40.611050307564895,
            "max" : 46.830818763181512,
            "start" : 2.75483,
            "duration" : 0.03518,
            "mean" : 44.613769589330857
        },
        {
            "std" : 0.88135522725117343,
            "end" : 2.79174,
            "name" : "Segment",
            "min" : 45.467585874843479,
            "max" : 49.123764925932619,
            "start" : 2.79001,
            "duration" : 0.00173,
            "mean" : 47.193822335140766
        },
        {
            "std" : 4.3043764417169204,
            "end" : 2.79505,
            "name" : "Segment",
            "min" : 27.87113558726211,
            "max" : 44.946512811253612,
            "start" : 2.79174,
            "duration" : 0.00331,
            "mean" : 37.878722709924496
        },
        {
            "std" : 0.86418527552772628,
            "end" : 2.82676,
            "name" : "Segment",
            "min" : 37.212623513456833,
            "max" : 43.035863148324673,
            "start" : 2.79505,
            "duration" : 0.03171,
            "mean" : 40.806195903196212
        },
        {
            "std" : 1.8693937071243938,
            "end" : 2.87705,
            "name" : "Segment",
            "min" : 29.277594003368172,
            "max" : 41.54113879932531,
            "start" : 2.82676,
            "duration" : 0.05029,
            "mean" : 38.235732199883053
        },
        {
            "std" : 3.4346655119256737,
            "end" : 2.87816,
            "name" : "Segment",
            "min" : 28.042885998308606,
            "max" : 38.686985760511142,
            "start" : 2.87705,
            "duration" : 0.00111,
            "mean" : 33.503895724597285
        },
        {
            "std" : 1.9058646953617764,
            "end" : 2.92989,
            "name" : "Segment",
            "min" : 30.387241616687554,
            "max" : 42.427340941179118,
            "start" : 2.87816,
            "duration" : 0.05173,
            "mean" : 37.91177595482791
        },
        {
            "std" : 2.6021314326123037,
            "end" : 2.96279,
            "name" : "Segment",
            "min" : 22.292470413343008,
            "max" : 40.443333764175371,
            "start" : 2.92989,
            "duration" : 0.0329,
            "mean" : 36.648717238530331
        },
        {
            "std" : 1.3066467412413558,
            "end" : 2.97856,
            "name" : "Segment",
            "min" : 33.941327426823129,
            "max" : 41.897000854767548,
            "start" : 2.96279,
            "duration" : 0.01577,
            "mean" : 37.964191468102101
        },
        {
            "std" : 2.2513018730627139,
            "end" : 3.10099,
            "name" : "Segment",
            "min" : 25.983261903428279,
            "max" : 43.744156314895839,
            "start" : 2.97856,
            "duration" : 0.12243,
            "mean" : 36.787697581022876
        },
        {
            "std" : 3.349419906637217,
            "end" : 3.10232,
            "name" : "Segment",
            "min" : 23.709322572832669,
            "max" : 35.558578091131793,
            "start" : 3.10099,
            "duration" : 0.00133,
            "mean" : 31.1199638721098
        },
        {
            "std" : 2.5617497243621545,
            "end" : 3.17191,
            "name" : "Segment",
            "min" : 9.3269207276749366,
            "max" : 30.780574535215695,
            "start" : 3.10232,
            "duration" : 0.06959,
            "mean" : 16.982691837581235
        },
        {
            "std" : 3.3748704921580961,
            "end" : 3.1792,
            "name" : "Segment",
            "min" : 12.365937501130885,
            "max" : 27.855176570400012,
            "start" : 3.17191,
            "duration" : 0.00729,
            "mean" : 20.750014244051822
        },
        {
            "std" : 2.2160243965634545,
            "end" : 3.19441,
            "name" : "Segment",
            "min" : 9.8400270551860949,
            "max" : 24.379709295542934,
            "start" : 3.1792,
            "duration" : 0.01521,
            "mean" : 15.077253705334968
        },
        {
            "std" : 2.4087115123579323,
            "end" : 3.23286,
            "name" : "Segment",
            "min" : 23.104999325662774,
            "max" : 37.478568255242223,
            "start" : 3.19441,
            "duration" : 0.03845,
            "mean" : 30.770372553664281
        },
        {
            "std" : 1.0202449955590536,
            "end" : 3.26417,
            "name" : "Segment",
            "min" : 36.825244526099816,
            "max" : 45.39766984657512,
            "start" : 3.23286,
            "duration" : 0.03131,
            "mean" : 41.746315763800517
        },
        {
            "std" : 0.94982101383129924,
            "end" : 3.38293,
            "name" : "Segment",
            "min" : 40.068211890158288,
            "max" : 47.7774747291081,
            "start" : 3.26417,
            "duration" : 0.11876,
            "mean" : 44.737065358866673
        },
        {
            "std" : 1.1024641398940216,
            "end" : 3.39326,
            "name" : "Segment",
            "min" : 39.892041731439818,
            "max" : 47.284036353020518,
            "start" : 3.38293,
            "duration" : 0.01033,
            "mean" : 43.827991734173835
        },
        {
            "std" : 0.69845804364228981,
            "end" : 3.43096,
            "name" : "Segment",
            "min" : 41.850827562223998,
            "max" : 46.654302779753138,
            "start" : 3.39326,
            "duration" : 0.0377,
            "mean" : 44.108635147387645
        },
        {
            "std" : 1.8730948745405187,
            "end" : 3.43315,
            "name" : "Segment",
            "min" : 37.435706644183433,
            "max" : 45.870823301460803,
            "start" : 3.43096,
            "duration" : 0.00219,
            "mean" : 43.861807332406222
        },
        {
            "std" : 0.58339701217425155,
            "end" : 3.47965,
            "name" : "Segment",
            "min" : 41.592783841584342,
            "max" : 45.764339512796674,
            "start" : 3.43315,
            "duration" : 0.0465,
            "mean" : 44.058633093561667
        },
        {
            "std" : 0.8235130921108379,
            "end" : 3.52999,
            "name" : "Segment",
            "min" : 36.964241595662394,
            "max" : 46.176800157942623,
            "start" : 3.47965,
            "duration" : 0.05034,
            "mean" : 43.769065121661505
        },
        {
            "std" : 0.73660021833082712,
            "end" : 3.66138,
            "name" : "Segment",
            "min" : 38.575359086440152,
            "max" : 45.482754658329696,
            "start" : 3.52999,
            "duration" : 0.13139,
            "mean" : 43.205439383700998
        },
        {
            "std" : 0.74453270618366429,
            "end" : 3.74787,
            "name" : "Segment",
            "min" : 34.377582382151303,
            "max" : 40.67411382696622,
            "start" : 3.66138,
            "duration" : 0.08649,
            "mean" : 38.3163075666968
        },
        {
            "std" : 0.75965040955321472,
            "end" : 3.76982,
            "name" : "Segment",
            "min" : 33.793966192579326,
            "max" : 39.412948391555297,
            "start" : 3.74787,
            "duration" : 0.02195,
            "mean" : 37.774535174428415
        },
        {
            "std" : 0.73114174286756839,
            "end" : 3.78088,
            "name" : "Segment",
            "min" : 32.359441284341806,
            "max" : 36.859437225448247,
            "start" : 3.76982,
            "duration" : 0.01106,
            "mean" : 34.013765770448323
        },
        {
            "std" : 1.00760122660531,
            "end" : 3.80967,
            "name" : "Segment",
            "min" : 29.712915918100492,
            "max" : 39.249689684157758,
            "start" : 3.78088,
            "duration" : 0.02879,
            "mean" : 33.085968726991624
        },
        {
            "std" : 1.3818100650293057,
            "end" : 3.84248,
            "name" : "Segment",
            "min" : 38.608278716422113,
            "max" : 47.644606354101285,
            "start" : 3.80967,
            "duration" : 0.03281,
            "mean" : 42.269205441148316
        },
        {
            "std" : 1.1137709067876631,
            "end" : 3.86107,
            "name" : "Segment",
            "min" : 39.948885611289796,
            "max" : 47.084237241621324,
            "start" : 3.84248,
            "duration" : 0.01859,
            "mean" : 44.969777968660907
        },
        {
            "std" : 0.63883922370630786,
            "end" : 3.87647,
            "name" : "Segment",
            "min" : 43.155468018587136,
            "max" : 46.642525289724936,
            "start" : 3.86107,
            "duration" : 0.0154,
            "mean" : 44.866924744616881
        },
        {
            "std" : 2.1837410283764394,
            "end" : 3.87998,
            "name" : "Segment",
            "min" : 34.724740082729674,
            "max" : 47.588577291492321,
            "start" : 3.87647,
            "duration" : 0.00351,
            "mean" : 44.241891508401494
        },
        {
            "std" : 0.74031366926397224,
            "end" : 3.90014,
            "name" : "Segment",
            "min" : 42.792172251074611,
            "max" : 46.879180851172862,
            "start" : 3.87998,
            "duration" : 0.02016,
            "mean" : 44.995602767963241
        },
        {
            "std" : 0.97390071806724821,
            "end" : 3.92604,
            "name" : "Segment",
            "min" : 38.808863997161545,
            "max" : 46.16044290623261,
            "start" : 3.90014,
            "duration" : 0.0259,
            "mean" : 43.926580469114612
        },
        {
            "std" : 0.83799107211971291,
            "end" : 3.94474,
            "name" : "Segment",
            "min" : 34.318043027353042,
            "max" : 40.268489417116918,
            "start" : 3.92604,
            "duration" : 0.0187,
            "mean" : 37.106623792991499
        },
        {
            "std" : 3.1008185806290709,
            "end" : 3.94574,
            "name" : "Segment",
            "min" : 35.997711362869936,
            "max" : 44.5230068791317,
            "start" : 3.94474,
            "duration" : 0.001,
            "mean" : 40.670067110320453
        },
        {
            "std" : 0.92017043950889876,
            "end" : 3.96145,
            "name" : "Segment",
            "min" : 33.140632897652509,
            "max" : 38.595326911864859,
            "start" : 3.94574,
            "duration" : 0.01571,
            "mean" : 36.571814875217527
        },
        {
            "std" : 1.0808427980977064,
            "end" : 4.01509,
            "name" : "Segment",
            "min" : 30.959493511532784,
            "max" : 40.160296563576281,
            "start" : 3.96145,
            "duration" : 0.05364,
            "mean" : 35.771008976935903
        },
        {
            "std" : 1.4050820156746147,
            "end" : 4.06644,
            "name" : "Segment",
            "min" : 39.473611919318152,
            "max" : 48.087792693549666,
            "start" : 4.01509,
            "duration" : 0.05135,
            "mean" : 44.172625397681244
        },
        {
            "std" : 0.95683816051695347,
            "end" : 4.07576,
            "name" : "Segment",
            "min" : 41.833719915933379,
            "max" : 46.611808485963131,
            "start" : 4.06644,
            "duration" : 0.00932,
            "mean" : 44.073152390067627
        },
        {
            "std" : 1.1276643742632599,
            "end" : 4.08495,
            "name" : "Segment",
            "min" : 42.694131750431758,
            "max" : 48.517380733364959,
            "start" : 4.07576,
            "duration" : 0.00919,
            "mean" : 45.661957363528671
        },
        {
            "std" : 1.3567551552632067,
            "end" : 4.08781,
            "name" : "Segment",
            "min" : 38.428508886292548,
            "max" : 44.521379384633313,
            "start" : 4.08495,
            "duration" : 0.00286,
            "mean" : 41.141550892885469
        },
        {
            "std" : 1.346610454833572,
            "end" : 4.15259,
            "name" : "Segment",
            "min" : 38.163261233085308,
            "max" : 48.225185389100666,
            "start" : 4.08781,
            "duration" : 0.06478,
            "mean" : 43.164873769872166
        },
        {
            "std" : 1.1951677171731765,
            "end" : 4.2154,
            "name" : "Segment",
            "min" : 31.384813073484512,
            "max" : 41.775996088762426,
            "start" : 4.15259,
            "duration" : 0.06281,
            "mean" : 35.570979150334814
        },
        {
            "std" : 1.0646176119083943,
            "end" : 4.24271,
            "name" : "Segment",
            "min" : 29.390552710714527,
            "max" : 38.604988726438663,
            "start" : 4.2154,
            "duration" : 0.02731,
            "mean" : 33.844343864586207
        },
        {
            "std" : 1.4056703468361851,
            "end" : 4.24381,
            "name" : "Segment",
            "min" : 34.662724673014367,
            "max" : 40.215491664856714,
            "start" : 4.24271,
            "duration" : 0.0011,
            "mean" : 37.008225949447365
        },
        {
            "std" : 0.6843484838581807,
            "end" : 4.25373,
            "name" : "Segment",
            "min" : 31.404235643478145,
            "max" : 36.266553775533652,
            "start" : 4.24381,
            "duration" : 0.00992,
            "mean" : 33.818141721408487
        },
        {
            "std" : 2.2598540318982101,
            "end" : 4.25473,
            "name" : "Segment",
            "min" : 33.439557977556419,
            "max" : 40.725068737273943,
            "start" : 4.25373,
            "duration" : 0.001,
            "mean" : 36.317175961864358
        },
        {
            "std" : 0.80548598601643639,
            "end" : 4.27152,
            "name" : "Segment",
            "min" : 31.427290591298728,
            "max" : 38.191714798737138,
            "start" : 4.25473,
            "duration" : 0.01679,
            "mean" : 33.665065876088427
        },
        {
            "std" : 2.7559037666829624,
            "end" : 4.27996,
            "name" : "Segment",
            "min" : 37.530087376926289,
            "max" : 51.34295319778635,
            "start" : 4.27152,
            "duration" : 0.00844,
            "mean" : 47.954889662721683
        },
        {
            "std" : 3.0958477480046702,
            "end" : 4.29381,
            "name" : "Segment",
            "min" : 38.329560171418947,
            "max" : 51.25900081282542,
            "start" : 4.27996,
            "duration" : 0.01385,
            "mean" : 43.244274000832036
        },
        {
            "std" : 2.3665850129662394,
            "end" : 4.30157,
            "name" : "Segment",
            "min" : 41.419667571357905,
            "max" : 51.360078674309193,
            "start" : 4.29381,
            "duration" : 0.00776,
            "mean" : 47.785725192167178
        },
        {
            "std" : 1.4145794635448343,
            "end" : 4.31377,
            "name" : "Segment",
            "min" : 41.75391978242375,
            "max" : 49.076604533329835,
            "start" : 4.30157,
            "duration" : 0.0122,
            "mean" : 45.216189746876104
        },
        {
            "std" : 2.1941374710523278,
            "end" : 4.34458,
            "name" : "Segment",
            "min" : 40.402686789407362,
            "max" : 51.521423180710727,
            "start" : 4.31377,
            "duration" : 0.03081,
            "mean" : 46.178557120161983
        },
        {
            "std" : 3.823562959339692,
            "end" : 4.34987,
            "name" : "Segment",
            "min" : 37.230937037991964,
            "max" : 52.443628817647429,
            "start" : 4.34458,
            "duration" : 0.00529,
            "mean" : 46.636754736651866
        },
        {
            "std" : 0.94988585200112141,
            "end" : 4.44703,
            "name" : "Segment",
            "min" : 44.619624151167429,
            "max" : 52.728464830841958,
            "start" : 4.34987,
            "duration" : 0.09716,
            "mean" : 50.201591264960193
        },
        {
            "std" : 1.6092797360535775,
            "end" : 4.44803,
            "name" : "Segment",
            "min" : 44.054693255911673,
            "max" : 50.235100948043879,
            "start" : 4.44703,
            "duration" : 0.001,
            "mean" : 48.28412750540538
        },
        {
            "std" : 0.7189365524909892,
            "end" : 4.45861,
            "name" : "Segment",
            "min" : 48.652290462583991,
            "max" : 52.161572943096765,
            "start" : 4.44803,
            "duration" : 0.01058,
            "mean" : 50.570850931121804
        },
        {
            "std" : 1.0022541727714449,
            "end" : 4.46936,
            "name" : "Segment",
            "min" : 44.709234447912245,
            "max" : 52.106678555286685,
            "start" : 4.45861,
            "duration" : 0.01075,
            "mean" : 49.659592040744393
        },
        {
            "std" : 1.016690031701625,
            "end" : 4.5066,
            "name" : "Segment",
            "min" : 40.74158458005666,
            "max" : 51.069775783252588,
            "start" : 4.46936,
            "duration" : 0.03724,
            "mean" : 48.912418437053262
        },
        {
            "std" : 1.3095990202988173,
            "end" : 4.5618,
            "name" : "Segment",
            "min" : 36.431316542437912,
            "max" : 49.243700666219965,
            "start" : 4.5066,
            "duration" : 0.0552,
            "mean" : 44.327815333915026
        },
        {
            "std" : 1.3911932181221125,
            "end" : 4.63553,
            "name" : "Segment",
            "min" : 34.858539938879034,
            "max" : 48.541892793829767,
            "start" : 4.5618,
            "duration" : 0.07373,
            "mean" : 43.591695555108586
        },
        {
            "std" : 1.4010284190314948,
            "end" : 4.66724,
            "name" : "Segment",
            "min" : 40.005625465536284,
            "max" : 49.995223831475144,
            "start" : 4.63553,
            "duration" : 0.03171,
            "mean" : 46.035466644960273
        },
        {
            "std" : 1.3397078959691948,
            "end" : 4.67777,
            "name" : "Segment",
            "min" : 41.742929538079864,
            "max" : 48.374944011147058,
            "start" : 4.66724,
            "duration" : 0.01053,
            "mean" : 44.77371361671382
        },
        {
            "std" : 1.108435033441705,
            "end" : 4.77784,
            "name" : "Segment",
            "min" : 42.891855181055462,
            "max" : 49.983640295921312,
            "start" : 4.67777,
            "duration" : 0.10007,
            "mean" : 47.046486889110518
        },
        {
            "std" : 1.0895026383099884,
            "end" : 4.78761,
            "name" : "Segment",
            "min" : 43.061486269367485,
            "max" : 48.799063668374352,
            "start" : 4.77784,
            "duration" : 0.00977,
            "mean" : 46.178010185334642
        },
        {
            "std" : 1.0331440638208496,
            "end" : 4.80434,
            "name" : "Segment",
            "min" : 42.223494050703216,
            "max" : 49.122212023643577,
            "start" : 4.78761,
            "duration" : 0.01673,
            "mean" : 47.089131176723114
        },
        {
            "std" : 1.4150393264466035,
            "end" : 4.80727,
            "name" : "Segment",
            "min" : 42.370331801458157,
            "max" : 47.955751078674794,
            "start" : 4.80434,
            "duration" : 0.00293,
            "mean" : 45.153919912051805
        },
        {
            "std" : 1.2597461104371785,
            "end" : 4.823,
            "name" : "Segment",
            "min" : 44.258169005609254,
            "max" : 51.515609916175862,
            "start" : 4.80727,
            "duration" : 0.01573,
            "mean" : 47.813078208729898
        },
        {
            "std" : 1.1264609103415981,
            "end" : 4.97894,
            "name" : "Segment",
            "min" : 42.135146642975613,
            "max" : 51.037304478646952,
            "start" : 4.823,
            "duration" : 0.15594,
            "mean" : 47.147041832643815
        },
        {
            "std" : 1.350254125121324,
            "end" : 4.99087,
            "name" : "Segment",
            "min" : 41.67221837039795,
            "max" : 50.840188883947931,
            "start" : 4.97894,
            "duration" : 0.01193,
            "mean" : 48.566641031341014
        },
        {
            "std" : 0.6656407951372677,
            "end" : 5.00012,
            "name" : "Segment",
            "min" : 47.144215865730764,
            "max" : 50.135041356044987,
            "start" : 4.99087,
            "duration" : 0.00925,
            "mean" : 48.596784108846286
        },
        {
            "std" : 0.90060918461191075,
            "end" : 5.16217,
            "name" : "Segment",
            "min" : 43.254353045201768,
            "max" : 50.190084785548997,
            "start" : 5.00012,
            "duration" : 0.16205,
            "mean" : 47.816335484084952
        },
        {
            "std" : 0.47732789911568851,
            "end" : 5.16933,
            "name" : "Segment",
            "min" : 43.977844203216144,
            "max" : 46.502929306820192,
            "start" : 5.16217,
            "duration" : 0.00716,
            "mean" : 45.411567887201919
        },
        {
            "std" : 0.83775255479989352,
            "end" : 5.21905,
            "name" : "Segment",
            "min" : 39.690112468525243,
            "max" : 47.47852627244982,
            "start" : 5.16933,
            "duration" : 0.04972,
            "mean" : 44.898755295485316
        },
        {
            "std" : 0.70144072941902791,
            "end" : 5.32822,
            "name" : "Segment",
            "min" : 39.533705413433339,
            "max" : 46.460154665681102,
            "start" : 5.21905,
            "duration" : 0.10917,
            "mean" : 44.413147158131324
        },
        {
            "std" : 0.93163594118710047,
            "end" : 5.35931,
            "name" : "Segment",
            "min" : 38.074837836570872,
            "max" : 46.170881665954184,
            "start" : 5.32822,
            "duration" : 0.03109,
            "mean" : 43.97840707603784
        },
        {
            "std" : 0.75152831184786262,
            "end" : 5.48171,
            "name" : "Segment",
            "min" : 38.716661998011276,
            "max" : 45.109054150758979,
            "start" : 5.35931,
            "duration" : 0.1224,
            "mean" : 42.961284932789063
        },
        {
            "std" : 0.82719297252440438,
            "end" : 5.67477,
            "name" : "Segment",
            "min" : 36.01969431432363,
            "max" : 45.676014682158602,
            "start" : 5.48171,
            "duration" : 0.19306,
            "mean" : 43.422153039012137
        },
        {
            "std" : 0.60068274672416455,
            "end" : 5.7004,
            "name" : "Segment",
            "min" : 41.458293008119519,
            "max" : 44.557594852848737,
            "start" : 5.67477,
            "duration" : 0.02563,
            "mean" : 43.088967504106542
        },
        {
            "std" : 1.0507757342261972,
            "end" : 5.73634,
            "name" : "Segment",
            "min" : 38.162283196579928,
            "max" : 45.087480351649809,
            "start" : 5.7004,
            "duration" : 0.03594,
            "mean" : 42.800527587232082
        },
        {
            "std" : 0.78731114929714818,
            "end" : 5.82277,
            "name" : "Segment",
            "min" : 39.506415302616908,
            "max" : 45.342133804134399,
            "start" : 5.73634,
            "duration" : 0.08643,
            "mean" : 43.026335477792472
        },
        {
            "std" : 0.89885725409774742,
            "end" : 5.82473,
            "name" : "Segment",
            "min" : 38.825020299610152,
            "max" : 42.230104142522102,
            "start" : 5.82277,
            "duration" : 0.00196,
            "mean" : 40.725313229710046
        },
        {
            "std" : 0.92697199865901103,
            "end" : 6.02313,
            "name" : "Segment",
            "min" : 38.946986408557812,
            "max" : 45.672920272666374,
            "start" : 5.82473,
            "duration" : 0.1984,
            "mean" : 43.026631086063247
        },
        {
            "std" : 0.78695190855876707,
            "end" : 6.05303,
            "name" : "Segment",
            "min" : 39.229594632147524,
            "max" : 44.925521107724009,
            "start" : 6.02313,
            "duration" : 0.0299,
            "mean" : 42.241782319378423
        },
        {
            "std" : 2.4787245822964632,
            "end" : 6.17618,
            "name" : "Segment",
            "min" : 42.323228988699142,
            "max" : 56.682240835076009,
            "start" : 6.05303,
            "duration" : 0.12315,
            "mean" : 50.12155656565281
        },
        {
            "std" : 1.7783114562915801,
            "end" : 6.18684,
            "name" : "Segment",
            "min" : 49.087774017950224,
            "max" : 57.393975594444143,
            "start" : 6.17618,
            "duration" : 0.01066,
            "mean" : 53.472832926961587
        },
        {
            "std" : 3.2386164358718204,
            "end" : 6.20604,
            "name" : "Segment",
            "min" : 44.833317776183797,
            "max" : 63.904923331253791,
            "start" : 6.18684,
            "duration" : 0.0192,
            "mean" : 51.235330782424008
        },
        {
            "std" : 3.350589862843405,
            "end" : 6.24066,
            "name" : "Segment",
            "min" : 46.909984678959411,
            "max" : 67.051956736903108,
            "start" : 6.20604,
            "duration" : 0.03462,
            "mean" : 53.229834947691764
        },
        {
            "std" : 1.5964953314413488,
            "end" : 6.30485,
            "name" : "Segment",
            "min" : 67.446598634655956,
            "max" : 78.695719397256653,
            "start" : 6.24066,
            "duration" : 0.06419,
            "mean" : 75.005152575498997
        },
        {
            "std" : 4.9552926683117224,
            "end" : 6.30585,
            "name" : "Segment",
            "min" : 60.139088643748423,
            "max" : 74.698696559542356,
            "start" : 6.30485,
            "duration" : 0.001,
            "mean" : 69.192327620411874
        },
        {
            "std" : 1.4339921972937024,
            "end" : 6.31492,
            "name" : "Segment",
            "min" : 71.307044878048686,
            "max" : 78.291226168539737,
            "start" : 6.30585,
            "duration" : 0.00907,
            "mean" : 75.350930306493879
        },
        {
            "std" : 1.2449464646467749,
            "end" : 6.32774,
            "name" : "Segment",
            "min" : 72.322800120809191,
            "max" : 78.790032801975869,
            "start" : 6.31492,
            "duration" : 0.01282,
            "mean" : 76.360277383846707
        },
        {
            "std" : 0.85466859733023059,
            "end" : 6.33069,
            "name" : "Segment",
            "min" : 75.787810993796228,
            "max" : 79.460858863244695,
            "start" : 6.32774,
            "duration" : 0.00295,
            "mean" : 77.929030826913916
        },
        {
            "std" : 1.2754471982981781,
            "end" : 6.36737,
            "name" : "Segment",
            "min" : 70.661132500956896,
            "max" : 78.985172396263195,
            "start" : 6.33069,
            "duration" : 0.03668,
            "mean" : 75.670071236016838
        },
        {
            "std" : 1.5835403872580363,
            "end" : 6.39707,
            "name" : "Segment",
            "min" : 68.655151331222484,
            "max" : 78.686801075440499,
            "start" : 6.36737,
            "duration" : 0.0297,
            "mean" : 73.667629485824705
        },
        {
            "std" : 1.2178906781819181,
            "end" : 6.41073,
            "name" : "Segment",
            "min" : 77.83585622204302,
            "max" : 83.059187413678657,
            "start" : 6.39707,
            "duration" : 0.01366,
            "mean" : 80.540800235716105
        },
        {
            "std" : 1.2342434945078204,
            "end" : 6.44845,
            "name" : "Segment",
            "min" : 75.483854416776765,
            "max" : 83.940492646867,
            "start" : 6.41073,
            "duration" : 0.03772,
            "mean" : 78.315745403169799
        },
        {
            "std" : 1.4053486892787745,
            "end" : 6.47361,
            "name" : "Segment",
            "min" : 79.475971027022126,
            "max" : 86.70690720688691,
            "start" : 6.44845,
            "duration" : 0.02516,
            "mean" : 83.218209447085542
        },
        {
            "std" : 1.2689116136686109,
            "end" : 6.48665,
            "name" : "Segment",
            "min" : 79.414522267845754,
            "max" : 86.346614876773756,
            "start" : 6.47361,
            "duration" : 0.01304,
            "mean" : 81.757493204175532
        },
        {
            "std" : 1.2911577632801288,
            "end" : 6.48836,
            "name" : "Segment",
            "min" : 82.669227984167307,
            "max" : 86.86066988524064,
            "start" : 6.48665,
            "duration" : 0.00171,
            "mean" : 85.213002435194369
        },
        {
            "std" : 1.411307711154355,
            "end" : 6.51877,
            "name" : "Segment",
            "min" : 75.841508448655915,
            "max" : 86.435074425685812,
            "start" : 6.48836,
            "duration" : 0.03041,
            "mean" : 82.177843667343481
        },
        {
            "std" : 1.7695840406258101,
            "end" : 6.58691,
            "name" : "Segment",
            "min" : 74.484301402380794,
            "max" : 86.91149928442637,
            "start" : 6.51877,
            "duration" : 0.06814,
            "mean" : 82.754517756376899
        },
        {
            "std" : 1.3622466934974535,
            "end" : 6.62412,
            "name" : "Segment",
            "min" : 76.073409545219434,
            "max" : 86.637726222798051,
            "start" : 6.58691,
            "duration" : 0.03721,
            "mean" : 82.248370791249499
        },
        {
            "std" : 1.6587316853778908,
            "end" : 6.70222,
            "name" : "Segment",
            "min" : 78.232376269992955,
            "max" : 87.015374132486755,
            "start" : 6.62412,
            "duration" : 0.0781,
            "mean" : 82.681133050329038
        },
        {
            "std" : 1.670036944343595,
            "end" : 6.70647,
            "name" : "Segment",
            "min" : 81.022534428240263,
            "max" : 86.433703192891613,
            "start" : 6.70222,
            "duration" : 0.00425,
            "mean" : 84.487509206637469
        },
        {
            "std" : 1.1281960385736354,
            "end" : 6.72835,
            "name" : "Segment",
            "min" : 80.511419404387269,
            "max" : 86.353021267520347,
            "start" : 6.70647,
            "duration" : 0.02188,
            "mean" : 82.166505799939088
        },
        {
            "std" : 1.5733770086966166,
            "end" : 6.74269,
            "name" : "Segment",
            "min" : 79.310713624616994,
            "max" : 86.546973963242493,
            "start" : 6.72835,
            "duration" : 0.01434,
            "mean" : 83.007714409231568
        },
        {
            "std" : 0.91970794036251002,
            "end" : 6.77944,
            "name" : "Segment",
            "min" : 80.423469147579283,
            "max" : 87.337488172074572,
            "start" : 6.74269,
            "duration" : 0.03675,
            "mean" : 85.215371768540663
        },
        {
            "std" : 1.249108398702208,
            "end" : 6.78208,
            "name" : "Segment",
            "min" : 81.570343533192727,
            "max" : 86.18827839123766,
            "start" : 6.77944,
            "duration" : 0.00264,
            "mean" : 83.099201821251157
        },
        {
            "std" : 0.90391295996293952,
            "end" : 6.88111,
            "name" : "Segment",
            "min" : 80.803793252694447,
            "max" : 87.570571500375209,
            "start" : 6.78208,
            "duration" : 0.09903,
            "mean" : 85.412387616462723
        },
        {
            "std" : 0.31001753469285981,
            "end" : 6.88513,
            "name" : "Segment",
            "min" : 85.521502588838985,
            "max" : 87.181251682596525,
            "start" : 6.88111,
            "duration" : 0.00402,
            "mean" : 86.473211963693004
        },
        {
            "std" : 0.75059318819215703,
            "end" : 6.89114,
            "name" : "Segment",
            "min" : 83.851311055370076,
            "max" : 87.172493433704972,
            "start" : 6.88513,
            "duration" : 0.00601,
            "mean" : 85.677617359244763
        },
        {
            "std" : 0.87528274302908338,
            "end" : 6.89772,
            "name" : "Segment",
            "min" : 82.969134297962498,
            "max" : 86.533566998712317,
            "start" : 6.89114,
            "duration" : 0.00658,
            "mean" : 84.659125103307034
        },
        {
            "std" : 0.93193250516620041,
            "end" : 6.96676,
            "name" : "Segment",
            "min" : 80.311463868175181,
            "max" : 87.198015849741594,
            "start" : 6.89772,
            "duration" : 0.06904,
            "mean" : 82.959053769997055
        },
        {
            "std" : 1.0721917349731689,
            "end" : 7.00992,
            "name" : "Segment",
            "min" : 80.71037205052653,
            "max" : 87.186470027769872,
            "start" : 6.96676,
            "duration" : 0.04316,
            "mean" : 84.908764990595671
        },
        {
            "std" : 0.63603293797260829,
            "end" : 7.01758,
            "name" : "Segment",
            "min" : 84.022432705159574,
            "max" : 87.007313012598615,
            "start" : 7.00992,
            "duration" : 0.00766,
            "mean" : 85.339791860449651
        },
        {
            "std" : 1.0969109534461285,
            "end" : 7.03333,
            "name" : "Segment",
            "min" : 80.555348637471269,
            "max" : 87.135800524777522,
            "start" : 7.01758,
            "duration" : 0.01575,
            "mean" : 83.173051777830764
        },
        {
            "std" : 0.82177155040288652,
            "end" : 7.04498,
            "name" : "Segment",
            "min" : 78.840507784685059,
            "max" : 85.078888212038933,
            "start" : 7.03333,
            "duration" : 0.01165,
            "mean" : 82.441604481877008
        },
        {
            "std" : 1.3454508549575714,
            "end" : 7.04808,
            "name" : "Segment",
            "min" : 82.19797830381269,
            "max" : 86.730257900168425,
            "start" : 7.04498,
            "duration" : 0.0031,
            "mean" : 84.149211328602291
        },
        {
            "std" : 1.0191159100670941,
            "end" : 7.05543,
            "name" : "Segment",
            "min" : 79.50858348628762,
            "max" : 86.53776414857127,
            "start" : 7.04808,
            "duration" : 0.00735,
            "mean" : 85.153651596648714
        },
        {
            "std" : 0.77806273419148397,
            "end" : 7.05857,
            "name" : "Segment",
            "min" : 81.832367143379187,
            "max" : 84.617583052744806,
            "start" : 7.05543,
            "duration" : 0.00314,
            "mean" : 83.425733742023539
        },
        {
            "std" : 0.79177440371166585,
            "end" : 7.1276,
            "name" : "Segment",
            "min" : 80.519069689624601,
            "max" : 87.355741958657887,
            "start" : 7.05857,
            "duration" : 0.06903,
            "mean" : 85.2902630489844
        },
        {
            "std" : 0.87250052531191058,
            "end" : 7.17062,
            "name" : "Segment",
            "min" : 76.855025392138103,
            "max" : 86.134644552636345,
            "start" : 7.1276,
            "duration" : 0.04302,
            "mean" : 83.364234694057686
        },
        {
            "std" : 0.61256999980751492,
            "end" : 7.18687,
            "name" : "Segment",
            "min" : 82.254646299117269,
            "max" : 85.472507552966022,
            "start" : 7.17062,
            "duration" : 0.01625,
            "mean" : 83.851457334317118
        },
        {
            "std" : 0.98063313094447668,
            "end" : 7.3775,
            "name" : "Segment",
            "min" : 79.031306673813418,
            "max" : 87.480004908881128,
            "start" : 7.18687,
            "duration" : 0.19063,
            "mean" : 84.977693980835596
        },
        {
            "std" : 0.7232108455910663,
            "end" : 7.41972,
            "name" : "Segment",
            "min" : 77.081685853191104,
            "max" : 85.711275081917606,
            "start" : 7.3775,
            "duration" : 0.04222,
            "mean" : 82.733356934197204
        },
        {
            "std" : 0.97324455823607114,
            "end" : 7.48205,
            "name" : "Segment",
            "min" : 79.36368722074387,
            "max" : 87.381275814689431,
            "start" : 7.41972,
            "duration" : 0.06233,
            "mean" : 84.726033064019433
        },
        {
            "std" : 0.5942272329350673,
            "end" : 7.50767,
            "name" : "Segment",
            "min" : 78.993343265657714,
            "max" : 85.220327292375401,
            "start" : 7.48205,
            "duration" : 0.02562,
            "mean" : 82.854889168819398
        },
        {
            "std" : 1.069209656904454,
            "end" : 7.55975,
            "name" : "Segment",
            "min" : 81.677062713440321,
            "max" : 88.085529174693022,
            "start" : 7.50767,
            "duration" : 0.05208,
            "mean" : 84.987625641479269
        },
        {
            "std" : 0.5698960993733676,
            "end" : 7.60777,
            "name" : "Segment",
            "min" : 81.374576468391638,
            "max" : 86.218073952466057,
            "start" : 7.55975,
            "duration" : 0.04802,
            "mean" : 83.277934364159719
        },
        {
            "std" : 0.51566501335734327,
            "end" : 7.60964,
            "name" : "Segment",
            "min" : 80.548650659381153,
            "max" : 82.676469960685793,
            "start" : 7.60777,
            "duration" : 0.00187,
            "mean" : 81.706726529321145
        },
        {
            "std" : 0.45666038877552645,
            "end" : 7.61454,
            "name" : "Segment",
            "min" : 82.477246722427694,
            "max" : 84.963785790595949,
            "start" : 7.60964,
            "duration" : 0.0049,
            "mean" : 83.430945793487538
        },
        {
            "std" : 0.72217373847421584,
            "end" : 7.62031,
            "name" : "Segment",
            "min" : 83.340080548841627,
            "max" : 87.074474468642222,
            "start" : 7.61454,
            "duration" : 0.00577,
            "mean" : 85.101001527850883
        },
        {
            "std" : 1.0906630564609994,
            "end" : 7.65662,
            "name" : "Segment",
            "min" : 83.359671468988111,
            "max" : 88.507962366235432,
            "start" : 7.62031,
            "duration" : 0.03631,
            "mean" : 85.922152735321319
        },
        {
            "std" : 0.54950045646396362,
            "end" : 7.70638,
            "name" : "Segment",
            "min" : 81.222739014348122,
            "max" : 85.938184018081273,
            "start" : 7.65662,
            "duration" : 0.04976,
            "mean" : 83.925938542131121
        },
        {
            "std" : 1.0259756814444816,
            "end" : 7.76571,
            "name" : "Segment",
            "min" : 80.836971108993396,
            "max" : 87.497599545131692,
            "start" : 7.70638,
            "duration" : 0.05933,
            "mean" : 84.952269173237852
        },
        {
            "std" : 0.74778248141835124,
            "end" : 7.78953,
            "name" : "Segment",
            "min" : 78.029619580303716,
            "max" : 84.926932199603385,
            "start" : 7.76571,
            "duration" : 0.02382,
            "mean" : 82.892950294460078
        },
        {
            "std" : 2.0599633285254297,
            "end" : 7.79396,
            "name" : "Segment",
            "min" : 75.037762485019243,
            "max" : 86.820518411853428,
            "start" : 7.78953,
            "duration" : 0.00443,
            "mean" : 83.167749122650491
        },
        {
            "std" : 0.89187143442836625,
            "end" : 7.84543,
            "name" : "Segment",
            "min" : 82.387268855892515,
            "max" : 89.354050446844681,
            "start" : 7.79396,
            "duration" : 0.05147,
            "mean" : 84.879258073591686
        },
        {
            "std" : 0.69552868591182271,
            "end" : 7.84656,
            "name" : "Segment",
            "min" : 83.864996337601767,
            "max" : 86.735066853650835,
            "start" : 7.84543,
            "duration" : 0.00113,
            "mean" : 85.396015415148014
        },
        {
            "std" : 0.57779622030481814,
            "end" : 7.92318,
            "name" : "Segment",
            "min" : 79.20330852876728,
            "max" : 85.96808152299424,
            "start" : 7.84656,
            "duration" : 0.07662,
            "mean" : 82.963750514106536
        },
        {
            "std" : 0.92045995499408828,
            "end" : 7.94092,
            "name" : "Segment",
            "min" : 82.917699388034748,
            "max" : 88.05650145923407,
            "start" : 7.92318,
            "duration" : 0.01774,
            "mean" : 84.979846667814215
        },
        {
            "std" : 4.4643718281445972,
            "end" : 7.94192,
            "name" : "Segment",
            "min" : 83.736665871460602,
            "max" : 103.78564448977366,
            "start" : 7.94092,
            "duration" : 0.001,
            "mean" : 86.416285683344086
        }
    ],
    "filter_cutoff" : 2000,
    "filter_order" : 1,
    "start" : 320.09267,
    "duration" : 7.9419199999999996,
    "filtered" : true,
    "n" : 201,
    "mean" : 51.972659188223432
}